{
   "date_update": "01 May 2024 16:03 UTC",
   "values": [
      {
         "Nombre": "Night Milking by winabees",
         "Informacion": "Una peque\u00f1a aventura sobre el orde\u00f1o de noche",
         "Desde": "",
         "Hasta": "2024/05/01 20:00",
         "URL": "https://winabees.itch.io/night-milking",
         "IMG": "https://img.itch.zone/aW1hZ2UvMjQ1NDM5OC8xNDU1MTA1OS5wbmc=/347x500/tCUZMW.png",
         "Distribuidora": "Itch io",
         "Borde": "border-image: linear-gradient(to right, red 54%, yellow 54%) 1;"
      },
      {
         "Nombre": "Plumbing Night by winabees",
         "Informacion": "Eres fontanero y alguien quiere arreglar sus tuber\u00edas en el s\u00f3tano.",
         "Desde": "",
         "Hasta": "2024/05/01 20:00",
         "URL": "https://winabees.itch.io/plumbing-night",
         "IMG": "https://img.itch.zone/aW1hZ2UvMjIxNzkxNC8xMzEyMTYzOC5wbmc=/347x500/FBEPq1.png",
         "Distribuidora": "Itch io",
         "Borde": "border-image: linear-gradient(to right, red 54%, yellow 54%) 1;"
      },
      {
         "Nombre": "O&O SafeErase 17 Pro",
         "Informacion": "La soluci\u00f3n completa para la protecci\u00f3n de tus datos",
         "Desde": "",
         "Hasta": "2024/05/02 09:00",
         "URL": "https://sharewareonsale.com/s/free-oo-safeerase-17-pro-100-discount",
         "IMG": "https://sharewareonsale.com/wp-content/uploads/2024/04/O-O-SafeErase-Professional-Boxshot.png",
         "Distribuidora": "SharewareOnSale",
         "Borde": "border-image: linear-gradient(to right, red 0%, yellow 0%) 1;"
      },
      {
         "Nombre": "Photo Enhancer AI",
         "Informacion": "Una soluci\u00f3n de mejora de im\u00e1genes y fotograf\u00edas basada en IA para ampliar fotograf\u00edas, reducir el ruido y eliminar las im\u00e1genes borrosas.",
         "Desde": "",
         "Hasta": "2024/05/02 09:00",
         "URL": "https://sharewareonsale.com/s/free-photo-enhancer-ai-100-discount",
         "IMG": "https://cdn.sharewareonsale.com/wp-content/uploads/2021/12/901-200x200.png?9187",
         "Distribuidora": "SharewareOnSale",
         "Borde": "border-image: linear-gradient(to right, red 0%, yellow 0%) 1;"
      },
      {
         "Nombre": "Firelinker by SeeOne",
         "Informacion": "\"Cada 500 a\u00f1os, nace un legendario drag\u00f3n enlazador de fuego, con el \u00fanico prop\u00f3sito de unir la llama y mantener vivos a los dragonantes\".",
         "Desde": "",
         "Hasta": "2024/05/02 16:30",
         "URL": "https://seeone.itch.io/firelinker",
         "IMG": "https://img.itch.zone/aW1hZ2UvMjU4OTI1MS8xNTYxOTM2Ni5wbmc=/347x500/xYUkxy.png",
         "Distribuidora": "Itch io",
         "Borde": "border-color: #00ff00;"
      },
      {
         "Nombre": "INDUSTRIA",
         "Informacion": "INDUSTRIA es un juego de disparos en primera persona que te traslada desde el Berl\u00edn Oriental hasta una realidad paralela poco antes del fin de la Guerra Fr\u00eda. Mientras buscas a tu compa\u00f1ero de trabajo desaparecido, descifras un pasado oscuro en una misteriosa dimensi\u00f3n paralela.",
         "Desde": "2024/04/25",
         "Hasta": "2024/05/02 17:00",
         "URL": "https://store.epicgames.com/p/industria",
         "IMG": "https://cdn1.epicgames.com/salesEvent/salesEvent/EGS_INDUSTRIA_Bleakmill_S1_2560x1440-6ac8f445f036547e0f7cc20dd4fd814f",
         "Distribuidora": "Epic Game",
         "Borde": "border-color: #00ff00;"
      },
      {
         "Nombre": "Agony by Guillotine",
         "Informacion": "Agony es un juego de terror slasher inspirado en el contenido de las pel\u00edculas de los 80 y 90",
         "Desde": "",
         "Hasta": "2024/05/02 22:30",
         "URL": "https://khoyman.itch.io/agony",
         "IMG": "https://img.itch.zone/aW1hZ2UvMjQ4MTUyMy8xNDc2MjAxMC5qcGc=/347x500/bN%2FVfF.jpg",
         "Distribuidora": "Itch io",
         "Borde": "border-color: #00ff00;"
      },
      {
         "Nombre": "ChronoPhobia by Guillotine",
         "Informacion": "Un d\u00eda te enteras de que tu hermano Harry est\u00e1 enfermo y vas a verlo a Baltimore, que est\u00e1 a 1400 km.",
         "Desde": "",
         "Hasta": "2024/05/02 22:30",
         "URL": "https://khoyman.itch.io/chronophobia",
         "IMG": "https://img.itch.zone/aW1hZ2UvMjE3NDkyNC8xMjgzODUwOC5naWY=/347x500/Hya3B1.gif",
         "Distribuidora": "Itch io",
         "Borde": "border-color: #00ff00;"
      },
      {
         "Nombre": "ChronoPhobia_Ep2(TheCross) by Guillotine",
         "Informacion": "NOTA: LA VERSI\u00d3N DEMO EST\u00c1 DISPONIBLE A CONTINUACI\u00d3N",
         "Desde": "",
         "Hasta": "2024/05/02 22:30",
         "URL": "https://khoyman.itch.io/chronophobia-ep2thecross",
         "IMG": "https://img.itch.zone/aW1hZ2UvMjE5OTUzOS8xMzAxMzQ3Mi5qcGc=/347x500/f02fCw.jpg",
         "Distribuidora": "Itch io",
         "Borde": "border-color: #00ff00;"
      },
      {
         "Nombre": "Delusion by Guillotine",
         "Informacion": "SINOPSIS:",
         "Desde": "",
         "Hasta": "2024/05/02 22:30",
         "URL": "https://khoyman.itch.io/delusion",
         "IMG": "https://img.itch.zone/aW1hZ2UvMjQ1NzYyOC8xNDY0NDE4Ny5qcGc=/347x500/Fc8DCk.jpg",
         "Distribuidora": "Itch io",
         "Borde": "border-color: #00ff00;"
      },
      {
         "Nombre": "Devil's Valley by Guillotine",
         "Informacion": "El juego Devil's Valley trata sobre la pelea de un padre con un cient\u00edfico llamado Vector. Para sus propios fines, este cient\u00edfico trabaja con pacientes con esquizofrenia para deshacerse de su enfermedad para siempre. Pero a veces esta acci\u00f3n resulta contraproducente. Como hija del personaje principal, Friedrich padece esta enfermedad. \u00c9l cae en la trampa de los vectores y t\u00fa tienes que desempe\u00f1ar el papel de padre.",
         "Desde": "",
         "Hasta": "2024/05/02 22:30",
         "URL": "https://khoyman.itch.io/devils-valley",
         "IMG": "https://img.itch.zone/aW1hZ2UvMjYzNDM0Ny8xNTcyMDI2OS5qcGc=/347x500/vufTs%2F.jpg",
         "Distribuidora": "Itch io",
         "Borde": "border-color: #00ff00;"
      },
      {
         "Nombre": "IRON BELLY by Guillotine",
         "Informacion": "Este juego trata sobre un soldado ingl\u00e9s llamado John que escap\u00f3 de las manos de los soldados rusos y se encuentra con un tren de vapor en su camino. Se da cuenta de que el sistema de este tren es diferente al de otros trenes.",
         "Desde": "",
         "Hasta": "2024/05/02 22:30",
         "URL": "https://khoyman.itch.io/iron-belly",
         "IMG": "https://img.itch.zone/aW1hZ2UvMjU5OTA5OS8xNTUwNjM2Mi5qcGc=/347x500/tll25s.jpg",
         "Distribuidora": "Itch io",
         "Borde": "border-color: #00ff00;"
      },
      {
         "Nombre": "Midnight Hobbies - Collection 1 by Guillotine",
         "Informacion": "Son las 3 de la medianoche. A\u00fan no te has dormido. Tu familia se ha ido de viaje de emergencia y tienes que quedarte solo una noche. Puede que te d\u00e9 un poco de miedo porque s\u00f3lo tienes 13 a\u00f1os. La lluvia golpea el cristal. No sabes qu\u00e9 hacer. De repente recuerdas que compraste 2 juegos nuevos por la ma\u00f1ana. Valle del Diablo y Revive. \u00bfQuieres mantenerte ocupado? Te levantas, enciendes tu PS1 y empiezas a jugar.",
         "Desde": "",
         "Hasta": "2024/05/02 22:30",
         "URL": "https://khoyman.itch.io/midnight-hobbies1",
         "IMG": "https://img.itch.zone/aW1hZ2UvMjY1MDk3NS8xNTgwMTY1Ny5naWY=/347x500/hMz%2FXV.gif",
         "Distribuidora": "Itch io",
         "Borde": "border-color: #00ff00;"
      },
      {
         "Nombre": "One Night in Baiko by Guillotine",
         "Informacion": "One Night in Baiko, un juego de terror estilo Psx con efectos nost\u00e1lgicos",
         "Desde": "",
         "Hasta": "2024/05/02 22:30",
         "URL": "https://khoyman.itch.io/one-night-in-baiko",
         "IMG": "https://img.itch.zone/aW1hZ2UvMjI3ODEwMC8xMzQ5OTA2OC5wbmc=/347x500/baQMbK.png",
         "Distribuidora": "Itch io",
         "Borde": "border-color: #00ff00;"
      },
      {
         "Nombre": "Revive by Guillotine",
         "Informacion": "Este juego trata sobre una persona llamada Luke que perdi\u00f3 a su perro llamado Kevin en un accidente. Luke vivi\u00f3 toda su vida s\u00f3lo con su perro. As\u00ed que no ten\u00eda a nadie m\u00e1s para continuar con su vida. Luke no puede soportar esta situaci\u00f3n y hace lo m\u00e1s siniestro para revivir a su perro.",
         "Desde": "",
         "Hasta": "2024/05/02 22:30",
         "URL": "https://khoyman.itch.io/revive",
         "IMG": "https://img.itch.zone/aW1hZ2UvMjQ5NDM4My8xNTEyMDU0Ny5naWY=/347x500/fDA6S8.gif",
         "Distribuidora": "Itch io",
         "Borde": "border-color: #00ff00;"
      },
      {
         "Nombre": "The Deepest Frequency by Guillotine",
         "Informacion": "The Deepest Frequency es un juego de talasofobia y control de un submarino en las profundidades del Oc\u00e9ano Atl\u00e1ntico.",
         "Desde": "",
         "Hasta": "2024/05/02 22:30",
         "URL": "https://khoyman.itch.io/thedeepestfrequency",
         "IMG": "https://img.itch.zone/aW1hZ2UvMjIzNTQ1MC8xMzIzOTE1Ny5qcGc=/347x500/Gl8rnM.jpg",
         "Distribuidora": "Itch io",
         "Borde": "border-color: #00ff00;"
      },
      {
         "Nombre": "Dino X Gost TD by Elxuj777",
         "Informacion": "Dino X Gost TD es una torre de defensa en la que luchas con dinosaurios para defender la base horaria, los dinosaurios deben morir (Gost es una marca comercial)",
         "Desde": "",
         "Hasta": "2024/05/03 00:00",
         "URL": "https://elxuj777.itch.io/dino-x-gost-td",
         "IMG": "https://img.itch.zone/aW1hZ2UvMjY2NzA3NS8xNTg5NDAxNi5qcGVn/347x500/YisZRf.jpeg",
         "Distribuidora": "Itch io",
         "Borde": "border-color: #00ff00;"
      },
      {
         "Nombre": "Forest Beta version 1.0 by Monster Energi Games",
         "Informacion": "Mi juego de bosque beta",
         "Desde": "",
         "Hasta": "2024/05/03 00:00",
         "URL": "https://poop-game-makers.itch.io/forest-beta-version-10",
         "IMG": "https://img.itch.zone/aW1nLzExMjY5NDc2LnBuZw==/347x500/%2FcCvlN.png",
         "Distribuidora": "Itch io",
         "Borde": "border-color: #00ff00;"
      },
      {
         "Nombre": "Gost Shooter by Elxuj777",
         "Informacion": "Gost Shooter es un juego basado en el cl\u00e1sico shooter en 2D con salas generadas aleatoriamente.",
         "Desde": "",
         "Hasta": "2024/05/03 00:00",
         "URL": "https://elxuj777.itch.io/gost-shooter",
         "IMG": "https://img.itch.zone/aW1hZ2UvMjU5MjY0MS8xNTg5NDA4MS5wbmc=/347x500/M0K%2Bfz.png",
         "Distribuidora": "Itch io",
         "Borde": "border-color: #00ff00;"
      },
      {
         "Nombre": "GTA V lite (mobile) by Elxuj777",
         "Informacion": "GTA V m\u00f3vil en serio, pero no est\u00e1 disponible el mapa completo y el juego puede retrasarse",
         "Desde": "",
         "Hasta": "2024/05/03 00:00",
         "URL": "https://elxuj777.itch.io/gta-v-lite-mobile",
         "IMG": "https://img.itch.zone/aW1hZ2UvMjY2OTQ1My8xNTkwODQ5Ni5qcGVn/347x500/4L8wpp.jpeg",
         "Distribuidora": "Itch io",
         "Borde": "border-color: #00ff00;"
      },
      {
         "Nombre": "High Life Racing by Elxuj777",
         "Informacion": "Un juego de carreras arcade con 3 mapas (en el juego hay niveles con nombre) y 1 autom\u00f3vil.",
         "Desde": "",
         "Hasta": "2024/05/03 00:00",
         "URL": "https://elxuj777.itch.io/high-life-racing",
         "IMG": "https://img.itch.zone/aW1hZ2UvMjY2MDMxNS8xNTg1MjcyMS5qcGc=/347x500/QgGhqZ.jpg",
         "Distribuidora": "Itch io",
         "Borde": "border-color: #00ff00;"
      },
      {
         "Nombre": "Ashampoo Snap 15",
         "Informacion": "Ashampoo Snap captura su escritorio como capturas de pantalla y videos. Las capturas de pantalla se pueden editar, comentar y compartir libremente a trav\u00e9s de redes, nubes o correo electr\u00f3nico.",
         "Desde": "",
         "Hasta": "2024/05/03 09:00",
         "URL": "https://sharewareonsale.com/s/free-ashampoo-snap-15-100-discount",
         "IMG": "https://cdn.sharewareonsale.com/wp-content/uploads/2024/04/scr-ashampoo-snap-15-presentation.jpg?9187",
         "Distribuidora": "SharewareOnSale",
         "Borde": "border-color: #00ff00;"
      },
      {
         "Nombre": "Smart Game Booster 5 Pro",
         "Informacion": "Aumente los FPS para una experiencia de juego m\u00e1s fluida con un solo clic",
         "Desde": "",
         "Hasta": "2024/05/03 09:00",
         "URL": "https://sharewareonsale.com/s/free-smart-game-booster-5-pro-100-discount",
         "IMG": "https://cdn.sharewareonsale.com/wp-content/uploads/2024/04/sgb-box1.png?9187",
         "Distribuidora": "SharewareOnSale",
         "Borde": "border-color: #00ff00;"
      },
      {
         "Nombre": "Nightmare by NekitGames",
         "Informacion": "Te has encontrado en un mundo lleno de pesadillas, \u00bfpodr\u00e1s salir de \u00e9l? Vamos a ver",
         "Desde": "",
         "Hasta": "2024/05/03 23:00",
         "URL": "https://nekitgames.itch.io/nightmare",
         "IMG": "https://img.itch.zone/aW1hZ2UvMjUwNTE4NC8xNDg4NDI3MS5wbmc=/347x500/taSR%2F7.png",
         "Distribuidora": "Itch io",
         "Borde": "border-color: #00ff00;"
      },
      {
         "Nombre": "Ashampoo Disk Space Explorer",
         "Informacion": "Disk Space Explorer 2023 brinda a los usuarios una imagen clara del uso del espacio en disco de sus unidades y les ayuda a encontrar archivos redundantes. A diferencia del Explorador de Windows, el programa tambi\u00e9n puede mostrar resultados por carpeta o tipo de archivo. Esto hace que sea muy f\u00e1cil encontrar posibles acaparadores de recursos, por ejemplo, archivos de v\u00eddeo, utilizando los filtros de tipo de archivo integrados. Cuando se trata del uso de espacio en disco por carpetas, los gr\u00e1ficos de barras revelan r\u00e1pidamente sus porcentajes del espacio total en disco. Los filtros de tipo de archivo tambi\u00e9n brindan a los usuarios una nueva perspectiva de sus unidades y los archivos que contienen. Despu\u00e9s de todo, \u00bfqui\u00e9n puede decir realmente cu\u00e1ntas fotos o canciones contiene una unidad y cu\u00e1nto espacio ocupan los archivos de inmediato? Todos los filtros basados \u200b\u200ben formatos son totalmente personalizables y los usuarios pueden incluso agregar o eliminar formatos adicionales y agrupar varios formatos para ejecutar an\u00e1lisis personalizados. Disk Space Explorer 2023 se basa en la \u00faltima tecnolog\u00eda WinOptimizer y ofrece informaci\u00f3n r\u00e1pida y precisa sobre el uso del espacio en disco local.",
         "Desde": "",
         "Hasta": "2024/05/04 09:00",
         "URL": "https://sharewareonsale.com/s/free-ashampoo-disk-space-explorer-2023-100-discount",
         "IMG": "https://cdn.sharewareonsale.com/wp-content/uploads/2023/07/front1-1.png?9187",
         "Distribuidora": "SharewareOnSale",
         "Borde": "border-color: #00ff00;"
      },
      {
         "Nombre": "Ashampoo Home Design 9",
         "Informacion": "Ashampoo Home Design 9\u00a0permite a los usuarios dise\u00f1ar, amueblar y visualizar la casa, ampliaci\u00f3n o redecoraci\u00f3n de la casa de sus sue\u00f1os en sus PC. El asistente de proyectos combinado con m\u00faltiples funciones autom\u00e1ticas ayuda a los usuarios a comenzar r\u00e1pidamente y facilita enormemente los c\u00e1lculos complejos. El amplio cat\u00e1logo de objetos abarca desde muebles hasta electrodom\u00e9sticos y decoraci\u00f3n. Se cubren todos los aspectos de la planificaci\u00f3n de la construcci\u00f3n. La impresionante vista 3D admite visitas virtuales para inspeccionar edificios que ya se encuentran en la fase de planificaci\u00f3n. Ashampoo Home Design 9 viene con paredes, techos, ventanas, puertas, huecos, tragaluces, paneles solares, chimeneas y electrodom\u00e9sticos de calidad profesional. Tres niveles de dise\u00f1o (2D, 3D, secci\u00f3n transversal) proporcionan la m\u00e1xima claridad en cada paso de planificaci\u00f3n. El software de dise\u00f1o para el hogar tambi\u00e9n admite importaciones de SketchUp y Collada para muebles a\u00fan m\u00e1s detallados. Incluye un cat\u00e1logo ampliado con m\u00e1s de 250 nuevos objetos 3D, nuevas puertas, el cat\u00e1logo de balcones en grupos y muros de contenci\u00f3n para la planificaci\u00f3n del terreno y el jard\u00edn. Las barandillas ahora se pueden utilizar en muchas variaciones, y el dimensionamiento autom\u00e1tico para planos de planta 2D y los textos de posici\u00f3n autom\u00e1ticos para marcar paredes y ventanas facilitan mucho su trabajo. Las nuevas funciones, como el elemento de terreno con l\u00edmites 3D, las vallas como barandillas y el pr\u00e1ctico di\u00e1logo de flecha norte para colocar, girar y escalar, proporcionan a\u00fan m\u00e1s facilidad de uso y flexibilidad.",
         "Desde": "",
         "Hasta": "2024/05/04 09:00",
         "URL": "https://sharewareonsale.com/s/free-ashampoo-home-design-9-100-discount",
         "IMG": "https://cdn.sharewareonsale.com/wp-content/uploads/2024/04/boxshot.png?9187",
         "Distribuidora": "SharewareOnSale",
         "Borde": "border-color: #00ff00;"
      },
      {
         "Nombre": "Audials One 2024",
         "Informacion": "Audials One 2024 es la mejor grabadora de transmisi\u00f3n de m\u00fasica, videos, radio y podcasts.",
         "Desde": "",
         "Hasta": "2024/05/04 09:00",
         "URL": "https://sharewareonsale.com/s/free-audials-one-2024-100-discount",
         "IMG": "https://cdn.sharewareonsale.com/wp-content/uploads/2023/12/Audials-One-2024-SE_EN_4.png?7297",
         "Distribuidora": "SharewareOnSale",
         "Borde": "border-color: #00ff00;"
      },
      {
         "Nombre": "Minesweeper: ESCAPE by DV GameDev",
         "Informacion": "",
         "Desde": "",
         "Hasta": "2024/05/04 23:00",
         "URL": "https://dv-gamedev.itch.io/minesweeper-escape",
         "IMG": "https://img.itch.zone/aW1hZ2UvMjIxNDgzMy8xMzE1MzQ1My5wbmc=/347x500/b3WS9y.png",
         "Distribuidora": "Itch io",
         "Borde": "border-color: #00ff00;"
      },
      {
         "Nombre": "Cubix: Mazes Unfold by KitCatGuy",
         "Informacion": "EL JUEGO EST\u00c1 ACTUALMENTE EN BETA. ESPERA ERRORES.",
         "Desde": "",
         "Hasta": "2024/05/05 00:00",
         "URL": "https://kitcatguy.itch.io/cubix-mazes-unfold",
         "IMG": "https://img.itch.zone/aW1hZ2UvMjYwMDc1Ny8xNTQ5MTMzOC5wbmc=/347x500/nzm1I1.png",
         "Distribuidora": "Itch io",
         "Borde": "border-color: #00ff00;"
      },
      {
         "Nombre": "Easy Photo Denoise 9",
         "Informacion": "Easy Photo Denoise ayuda a reducir el ruido en fotograf\u00edas tomadas en la oscuridad o con poca luz, temblores de manos o configuraciones ISO incorrectas.",
         "Desde": "",
         "Hasta": "2024/05/05 09:00",
         "URL": "https://sharewareonsale.com/s/free-easy-photo-denoise-100-discount",
         "IMG": "https://cdn.sharewareonsale.com/wp-content/uploads/2021/11/box_epd.png?9187",
         "Distribuidora": "SharewareOnSale",
         "Borde": "border-color: #00ff00;"
      },
      {
         "Nombre": "3300 Transparent People Stock Images Mega Bundle",
         "Informacion": "Este enorme paquete presenta m\u00e1s de 3300 im\u00e1genes de archivo de personas transparentes organizadas en m\u00e1s de 90 categor\u00edas diversas y \u00fanicas para ahorrar tiempo para su conveniencia. Eche un vistazo r\u00e1pido a las im\u00e1genes vers\u00e1tiles incluidas en este mega paquete:",
         "Desde": "",
         "Hasta": "2024/05/06 09:00",
         "URL": "https://sharewareonsale.com/s/free-3300-transparent-people-stock-images-mega-bundle-100-discount",
         "IMG": "https://cdn.sharewareonsale.com/wp-content/uploads/2023/10/transparent-mega-bundle.png?9187",
         "Distribuidora": "SharewareOnSale",
         "Borde": "border-color: #00ff00;"
      },
      {
         "Nombre": "EMOTION Projects Pro",
         "Informacion": "Experimente la diferencia que puede hacer una nueva atm\u00f3sfera de imagen con EMOTION Projects Professional. \u00a1Edita fotos de forma creativa como nunca antes!",
         "Desde": "",
         "Hasta": "2024/05/07 09:00",
         "URL": "https://sharewareonsale.com/s/free-emotion-projects-pro-100-discount",
         "IMG": "https://sharewareonsale.com/wp-content/uploads/2024/04/emotion_projects_pro.png",
         "Distribuidora": "SharewareOnSale",
         "Borde": "border-color: #00ff00;"
      },
      {
         "Nombre": "500 Professional Photoshop Actions Bundle",
         "Informacion": "\u00a1Presentamos las 500 incre\u00edbles acciones de Photoshop que te permitir\u00e1n crear fotograf\u00edas incre\u00edbles con un solo clic!",
         "Desde": "",
         "Hasta": "2024/05/07 09:00",
         "URL": "https://sharewareonsale.com/s/free-500-professional-photoshop-actions-bundle-100-discount",
         "IMG": "https://cdn.sharewareonsale.com/wp-content/uploads/2021/10/500-Professional-Photoshop-Actions-Bundle-200x133.jpg?7297",
         "Distribuidora": "SharewareOnSale",
         "Borde": "border-color: #00ff00;"
      },
      {
         "Nombre": "Life Quiz by ZeroUI",
         "Informacion": "Bienvenido a Life Quiz, este juego te invita a sumergirte en un mundo de diversos modos de prueba y cautivar la emoci\u00f3n invisible del mundo de las trivia.",
         "Desde": "",
         "Hasta": "2024/05/07 18:59",
         "URL": "https://zeroui.itch.io/life-quiz",
         "IMG": "https://img.itch.zone/aW1hZ2UvMjY2MjQ1MS8xNTg2NDc2MS5wbmc=/347x500/s4LniK.png",
         "Distribuidora": "Itch io",
         "Borde": "border-color: #00ff00;"
      },
      {
         "Nombre": "Packaging Items by ZeroUI",
         "Informacion": "Packaging Items es un juego de rompecabezas gratuito disponible en la plataforma Android.",
         "Desde": "",
         "Hasta": "2024/05/07 18:59",
         "URL": "https://zeroui.itch.io/packaging-items",
         "IMG": "https://img.itch.zone/aW1hZ2UvMjYzMjg0Ni8xNTY4Nzg4NC5wbmc=/347x500/%2F265RI.png",
         "Distribuidora": "Itch io",
         "Borde": "border-color: #00ff00;"
      },
      {
         "Nombre": "A Peaceful Camping by AL7USSAIN",
         "Informacion": "",
         "Desde": "",
         "Hasta": "2024/05/07 23:00",
         "URL": "https://al7ussain.itch.io/a-peacful-camping",
         "IMG": "https://img.itch.zone/aW1hZ2UvMjUzMjY0NC8xNTExNjc5OS5wbmc=/347x500/PHT4im.png",
         "Distribuidora": "Itch io",
         "Borde": "border-color: #00ff00;"
      },
      {
         "Nombre": "House Cleaner 2 by AL7USSAIN",
         "Informacion": "se trata de una empresa de limpieza y vas a las casas y las limpias pero la casa a la que entraste est\u00e1 alojada por un fantasma \u00bfpuede terminar bien esta noche?",
         "Desde": "",
         "Hasta": "2024/05/07 23:00",
         "URL": "https://al7ussain.itch.io/house-cleaner-2",
         "IMG": "https://img.itch.zone/aW1hZ2UvMjIyMzIyMy8xMzE2MDc1NC5wbmc=/347x500/Icf6je.png",
         "Distribuidora": "Itch io",
         "Borde": "border-color: #00ff00;"
      },
      {
         "Nombre": "House Cleaner by AL7USSAIN",
         "Informacion": "House Cleaner es un juego de terror en el que limpias la casa y la descubres y descubres que est\u00e1 encantada con un fantasma.",
         "Desde": "",
         "Hasta": "2024/05/07 23:00",
         "URL": "https://al7ussain.itch.io/housecleaner",
         "IMG": "https://img.itch.zone/aW1hZ2UvMTkyNDg2NC8xMTM1NzY5MC5qcGc=/347x500/JJ1S7y.jpg",
         "Distribuidora": "Itch io",
         "Borde": "border-color: #00ff00;"
      },
      {
         "Nombre": "Cat Quest II",
         "Informacion": "RPG de acci\u00f3n de mundo abierto ambientado en un mundo de gatos y perros. En Cat Quest II puedes jugar a solas o con un amigo, \u00a1siendo un perro o un gato! \u00a1Completa misiones en un mundo de magia, derrota a monstruos y consigue objetos en esta aventura gatuna!",
         "Desde": "2024/05/02",
         "Hasta": "2024/05/09 17:00",
         "URL": "https://store.epicgames.com/p/cat-quest-ii-9dbefc",
         "IMG": "https://cdn1.epicgames.com/spt-assets/fe812f94c42e44e986691a84c796952d/cat-quest-ii-cj318.jpg",
         "Distribuidora": "Epic Game",
         "Borde": "border-color: #ff9600;"
      },
      {
         "Nombre": "Orcs Must Die! 3",
         "Informacion": "Corta, quema, lanza, electrocuta, pulveriza y apalea hordas enormes de repugnantes orcos en este esperado sucesor de la galardonada serie Orcs Must Die!.",
         "Desde": "2024/05/02",
         "Hasta": "2024/05/09 17:00",
         "URL": "https://store.epicgames.com/p/combo-a7e03a",
         "IMG": "https://cdn1.epicgames.com/spt-assets/af503dd7e8b64218b69c22a9003de268/orcs-must-die-3-1puow.jpg",
         "Distribuidora": "Epic Game",
         "Borde": "border-color: #ff9600;"
      },
      {
         "Nombre": "SCAFFOLDEDGE by Snekjar",
         "Informacion": "Al liberar el cubo, el humilde tap\u00f3n lanza sus rayos de borde, armando paneles en cascada de creaci\u00f3n. La danza entre lo micro y lo macro cincela el lienzo de los universos, revelando y construyendo sus secretos, explorando capas de infinitos infinitos #gaming",
         "Desde": "",
         "Hasta": "2024/05/10 00:00",
         "URL": "https://snekjar.itch.io/scaffoldedge",
         "IMG": "https://img.itch.zone/aW1hZ2UvMjE4OTA4MC8xMzA4NDQ0MC5qcGc=/347x500/NWACZZ.jpg",
         "Distribuidora": "Itch io",
         "Borde": "border-color: #00ff00;"
      },
      {
         "Nombre": "coffee boy by bee tea",
         "Informacion": "En este encantador juego corto, juegas como el chico del caf\u00e9 reci\u00e9n contratado. \u00a1Depende de ti encontrar el True Coffee y entreg\u00e1rselo al Jefe! Podr\u00e1s hacer amigos extravagantes, explorar las misteriosas instalaciones, leer textos divertidos y... \u00bfencontrar al chico del caf\u00e9 desaparecido? De todos modos, no te preocupes por eso \u00faltimo y \u00a1conc\u00e9ntrate en LLEVARLE EL CAF\u00c9 AL JEFE!",
         "Desde": "",
         "Hasta": "2024/05/10 08:00",
         "URL": "https://bee-tea.itch.io/coffeeboy",
         "IMG": "https://img.itch.zone/aW1hZ2UvMTM4MzcwNy84MDg3NTc5LnBuZw==/347x500/m7t9P9.png",
         "Distribuidora": "Itch io",
         "Borde": "border-color: #00ff00;"
      },
      {
         "Nombre": "rainy day by bee tea",
         "Informacion": "\u00e2\u00a1 un juego corto sobre la lucha de una familia y su recuperaci\u00f3n de la depresi\u00f3n",
         "Desde": "",
         "Hasta": "2024/05/10 08:00",
         "URL": "https://bee-tea.itch.io/rainyday",
         "IMG": "https://img.itch.zone/aW1hZ2UvMTIzNDk4Mi83MjAwNTY2LnBuZw==/347x500/Qc0KWv.png",
         "Distribuidora": "Itch io",
         "Borde": "border-color: #00ff00;"
      },
      {
         "Nombre": "Because of Magic by gamesbyrd",
         "Informacion": "Criaturas oscuras de la Dimensi\u00f3n de la Oscuridad buscan destruir la Gran Fuente de Todo Poder. Si lo logran, el equilibrio se romper\u00e1 y el universo entero colapsar\u00e1.",
         "Desde": "",
         "Hasta": "2024/05/11 00:00",
         "URL": "https://gamesbyrd.itch.io/becauseofmagic",
         "IMG": "https://img.itch.zone/aW1hZ2UvMjU3ODgyMS8xNTM1OTcxNi5wbmc=/347x500/tB0rpJ.png",
         "Distribuidora": "Itch io",
         "Borde": "border-color: #00ff00;"
      },
      {
         "Nombre": "Blackness by gamesbyrd",
         "Informacion": "CONTROL S:",
         "Desde": "",
         "Hasta": "2024/05/11 00:00",
         "URL": "https://gamesbyrd.itch.io/blackness",
         "IMG": "https://img.itch.zone/aW1hZ2UvMjU4NjM2OC8xNTQwMzA4My5qcGc=/347x500/iv0EZ9.jpg",
         "Distribuidora": "Itch io",
         "Borde": "border-color: #00ff00;"
      },
      {
         "Nombre": "Cubes in Danger 2 by gamesbyrd",
         "Informacion": "CONTROL S:",
         "Desde": "",
         "Hasta": "2024/05/11 00:00",
         "URL": "https://gamesbyrd.itch.io/cubes-in-danger-2",
         "IMG": "https://img.itch.zone/aW1hZ2UvMjU4NzI2My8xNTQwNTA3MS5wbmc=/347x500/2sE%2BRY.png",
         "Distribuidora": "Itch io",
         "Borde": "border-color: #00ff00;"
      },
      {
         "Nombre": "Cubes in Danger 3 by gamesbyrd",
         "Informacion": "",
         "Desde": "",
         "Hasta": "2024/05/11 00:00",
         "URL": "https://gamesbyrd.itch.io/cubes-in-danger-3",
         "IMG": "https://img.itch.zone/aW1hZ2UvMjU4NzM1OC8xNTQwNTY4MS5wbmc=/347x500/T0Vthd.png",
         "Distribuidora": "Itch io",
         "Borde": "border-color: #00ff00;"
      },
      {
         "Nombre": "IncorpoScape by gamesbyrd",
         "Informacion": "COLOCA TABLAS EN EL AIRE Y SALTA SOBRE ELLAS, ASCENDIENDO CADA VEZ M\u00c1S ALTO EN UNA TORRE INFINITA.",
         "Desde": "",
         "Hasta": "2024/05/11 00:00",
         "URL": "https://gamesbyrd.itch.io/incorposcape",
         "IMG": "https://img.itch.zone/aW1hZ2UvMjU4NjQ0MS8xNTQxNzIxMy5wbmc=/347x500/1%2Fm5Bi.png",
         "Distribuidora": "Itch io",
         "Borde": "border-color: #00ff00;"
      },
      {
         "Nombre": "The Last Tree by gamesbyrd",
         "Informacion": "",
         "Desde": "",
         "Hasta": "2024/05/11 00:00",
         "URL": "https://gamesbyrd.itch.io/the-last-tree",
         "IMG": "https://img.itch.zone/aW1hZ2UvMjYxNzUxOC8xNTU5MjM2NC5wbmc=/347x500/ZzpRmP.png",
         "Distribuidora": "Itch io",
         "Borde": "border-color: #00ff00;"
      },
      {
         "Nombre": "The cursed cake! by Tuftuf-Games",
         "Informacion": "versi\u00f3n en ingl\u00e9s a continuaci\u00f3n.",
         "Desde": "",
         "Hasta": "2024/05/11 00:00",
         "URL": "https://tuftuf-games.itch.io/the-cursed-cake",
         "IMG": "https://img.itch.zone/aW1hZ2UvMjIzMDA5Mi8xMzIwMzAwMi5wbmc=/347x500/CscATS.png",
         "Distribuidora": "Itch io",
         "Borde": "border-color: #00ff00;"
      },
      {
         "Nombre": "PURE HDR",
         "Informacion": "PURE HDR es la herramienta para todos los profesionales de HDR que buscan inculcar detalles fascinantes y v\u00edvidos en sus trabajos fotogr\u00e1ficos mediante la utilizaci\u00f3n de espectros completos de luz y color. En forma de extensi\u00f3n de complemento, PURE HDR funciona con las \u00faltimas capacidades de edici\u00f3n HDR de 32 bits de las galardonadas colecciones de proyectos FRANZIS HDR directamente en Lightroom\u00ae y Photoshop\u00ae.",
         "Desde": "",
         "Hasta": "2024/05/11 09:00",
         "URL": "https://sharewareonsale.com/s/free-pure-hdr-100-discount",
         "IMG": "https://sharewareonsale.com/wp-content/uploads/2022/05/x30979-0_01_1280x1280_png_pagespeed_ic_dk_N3-wugc-200x287.png",
         "Distribuidora": "SharewareOnSale",
         "Borde": "border-color: #00ff00;"
      },
      {
         "Nombre": "Ashampoo Duplicate File Finder",
         "Informacion": "Casi todos los sistemas Windows contienen numerosos archivos duplicados. Ashampoo Duplicate Finder busca y elimina archivos redundantes y permite a los usuarios recuperar su espacio en disco. Para garantizar que sus aplicaciones sigan funcionando sin problemas, el programa mantiene un archivo maestro y reemplaza todas las copias redundantes con enlaces f\u00edsicos a ese archivo. Cuando una aplicaci\u00f3n intenta acceder a una copia eliminada, utilizar\u00e1 el archivo maestro. \u00a1Es un enfoque inteligente que evita por completo los problemas con los archivos y simplemente no es factible solo con la eliminaci\u00f3n manual de archivos! \u00bfPero de d\u00f3nde vienen los archivos duplicados? Pueden deberse a descargas repetidas o configuraciones de programas en las que cada uno proporciona su propia copia de los archivos de la biblioteca del sistema. Incluso el propio Windows tiende a crear archivos redundantes en unidades y ubicaciones de guardado. Ashampoo Duplicate File Finder escanea sistemas Windows a velocidades vertiginosas y presenta los resultados claramente ordenados por tipo de archivo, incluidos documentos, archivos de audio y video. Los usuarios pueden revisar coincidencias individuales y excluir permanentemente archivos para que no se eliminen, si es necesario. Pruebas exhaustivas han demostrado que los archivos duplicados pueden ocupar una cantidad significativa de espacio en disco y ofrecer poco o ning\u00fan beneficio aparte de la redundancia de archivos. Reemplazarlos con enlaces f\u00edsicos a un \u00fanico archivo maestro libera instant\u00e1neamente espacio en disco sin costo de rendimiento perceptible y con poco o ning\u00fan riesgo. Y Ashampoo Duplicate File Finder viene con un mecanismo de seguridad: \u00a1se crea una copia de seguridad antes de cada modificaci\u00f3n del sistema para que los usuarios puedan revertirla en cuesti\u00f3n de segundos!",
         "Desde": "",
         "Hasta": "2024/05/11 09:00",
         "URL": "https://sharewareonsale.com/s/free-ashampoo-duplicate-file-finder-100-discount",
         "IMG": "https://cdn.sharewareonsale.com/wp-content/uploads/2023/07/front1-1-1.png?7297",
         "Distribuidora": "SharewareOnSale",
         "Borde": "border-color: #00ff00;"
      },
      {
         "Nombre": "Baldi's Basics Songkran In Education And Learning X by SJ Logo transparent",
         "Informacion": "el juego original baldi basics en educaci\u00f3n y aprendizaje 1.3.2 el a\u00f1o pasado ahora actualizaci\u00f3n del juego a baldi basics songkran en educaci\u00f3n y aprendizaje 1.4.5 mod no descompilado, juego real que actualiza, publica el juego completado. \u00a1Gracias a mystman12 por no enviar ese mod descompilado ya enviarlo ya para actualizar el acceso al juego no informar mi cuenta y el juego por favor y ahora envi\u00e1rselo a usted!",
         "Desde": "",
         "Hasta": "2024/05/11 10:31",
         "URL": "https://sj-logo-transparent.itch.io/baldis-basics-songkran-in-education-and-learning-x",
         "IMG": "https://img.itch.zone/aW1hZ2UvMTUwODkzNy84Nzk1MDA0LmpwZw==/347x500/yIuU8%2B.jpg",
         "Distribuidora": "Itch io",
         "Borde": "border-color: #00ff00;"
      },
      {
         "Nombre": "Abdus Apartment by Mmado",
         "Informacion": "",
         "Desde": "",
         "Hasta": "2024/05/12 23:00",
         "URL": "https://mmado.itch.io/abdus-apartment",
         "IMG": "https://img.itch.zone/aW1hZ2UvMTk5ODc4Mi8xMTc1MzE3Mi5naWY=/347x500/0BFabo.gif",
         "Distribuidora": "Itch io",
         "Borde": "border-color: #00ff00;"
      },
      {
         "Nombre": "THE DRILLING by Voxelvoid",
         "Informacion": "THE DRILLING es un juego de terror psicol\u00f3gico de estilo retro sobre una expedici\u00f3n subterr\u00e1nea",
         "Desde": "",
         "Hasta": "2024/05/13 21:15",
         "URL": "https://voxelvoid.itch.io/the-drilling",
         "IMG": "https://img.itch.zone/aW1hZ2UvMjM0NTkyOC8xMzg5NzA5Ny5wbmc=/347x500/0wbdzt.png",
         "Distribuidora": "Itch io",
         "Borde": "border-color: #00ff00;"
      },
      {
         "Nombre": "Can't Sleep With The Lights Off by DavidelDEV",
         "Informacion": "",
         "Desde": "",
         "Hasta": "2024/05/13 23:00",
         "URL": "https://davideldev.itch.io/cant-sleep-with-the-lights-off",
         "IMG": "https://img.itch.zone/aW1hZ2UvMjY3ODY0Ny8xNTk2NDY2Mi5wbmc=/347x500/FcbLGH.png",
         "Distribuidora": "Itch io",
         "Borde": "border-color: #00ff00;"
      },
      {
         "Nombre": "ExiDourus by Green Woltec",
         "Informacion": "Te despiertas en mitad de la noche y escuchas un ruido. Mira lo que te espera en el juego de supervivencia de ExiDourus. \u00bfQu\u00e9 te espera? Habitaciones l\u00fagubres y oscuras y un monstruo que te persigue. Intenta encontrar la salida a tiempo.",
         "Desde": "",
         "Hasta": "2024/05/15 22:59",
         "URL": "https://greenwoltec.itch.io/exidourus",
         "IMG": "https://img.itch.zone/aW1hZ2UvMjYyOTM5Ny8xNTY2NzAxNy5wbmc=/347x500/F4n9u5.png",
         "Distribuidora": "Itch io",
         "Borde": "border-color: #00ff00;"
      },
      {
         "Nombre": "Horror Game: NEVREN by Green Woltec",
         "Informacion": "Este es un juego de terror medieval. Has escuchado los gritos de tu vecino y quieres ver si todo est\u00e1 bien con \u00e9l. Te das cuenta de que no est\u00e1 en casa y examinas la casa. Pero te das cuenta de que algo sobrenatural est\u00e1 pasando. Intenta encontrar todas las pistas e interruptores para seguir adelante.",
         "Desde": "",
         "Hasta": "2024/05/15 22:59",
         "URL": "https://greenwoltec.itch.io/horror-game-nevren",
         "IMG": "https://img.itch.zone/aW1hZ2UvMjE2NjA1NC8xMjc3ODAwNS5wbmc=/347x500/xJ03aK.png",
         "Distribuidora": "Itch io",
         "Borde": "border-color: #00ff00;"
      },
      {
         "Nombre": "TmeZombie Remake by Green Woltec",
         "Informacion": "Bienvenidos al remake de Tme Zombie. Ahora tengo los gr\u00e1ficos en HD y con incre\u00edbles 64 bits. As\u00ed como las animaciones de armas y con zombies aterradores. Para obtener m\u00e1s informaci\u00f3n, mire el avance.",
         "Desde": "",
         "Hasta": "2024/05/15 22:59",
         "URL": "https://greenwoltec.itch.io/tmezombie-remake",
         "IMG": "https://img.itch.zone/aW1hZ2UvMTg0ODUxNS8xMDg1MDAzNC5wbmc=/347x500/EOghGr.png",
         "Distribuidora": "Itch io",
         "Borde": "border-color: #00ff00;"
      },
      {
         "Nombre": "onlineTV 19",
         "Informacion": "M\u00e1s de 100 estaciones de TV de 13 pa\u00edses: \u00a1onlineTV 19 trae la televisi\u00f3n internacional a su PC, computadora port\u00e1til y dispositivo Android!",
         "Desde": "",
         "Hasta": "2024/05/18 09:00",
         "URL": "https://sharewareonsale.com/s/free-onlinetv-19-100-discount",
         "IMG": "https://cdn.sharewareonsale.com/wp-content/uploads/2023/04/otv18ohneandroid.png?9187",
         "Distribuidora": "SharewareOnSale",
         "Borde": "border-color: #00ff00;"
      },
      {
         "Nombre": "Infinity Clicker by Taco",
         "Informacion": "Empiezas con Nada, pero haces clic en Algo",
         "Desde": "",
         "Hasta": "2024/05/20 06:00",
         "URL": "https://taco2009.itch.io/everything-and-anything",
         "IMG": "https://img.itch.zone/aW1nLzE1NTI0MTMyLmdpZg==/347x500/K%2Ffm%2Fj.gif",
         "Distribuidora": "Itch io",
         "Borde": "border-color: #00ff00;"
      },
      {
         "Nombre": "CLIMB & SHOOT (VR Shooting Game for Oculus Quest ) by ULTRA FUN GAMES",
         "Informacion": "Este es un divertido parque de tiro y escalada con 32 armas ocultas diferentes de muchos tipos: pistolas modernas, pistolas de iluminaci\u00f3n, lanzacohetes, sables de iluminaci\u00f3n, katanas, martillos, martillos de iluminaci\u00f3n, etc.",
         "Desde": "",
         "Hasta": "2024/05/20 23:00",
         "URL": "https://ultra-fun-games.itch.io/climb-shoot",
         "IMG": "https://img.itch.zone/aW1hZ2UvMTIyODc2MC83MTkzNTMwLnBuZw==/347x500/vBQZ8C.png",
         "Distribuidora": "Itch io",
         "Borde": "border-color: #00ff00;"
      },
      {
         "Nombre": "FUN SHOOTING RANGE (VR Shooting Game for Oculus Quest ) by ULTRA FUN GAMES",
         "Informacion": "Este es un campo de tiro divertido con muchas armas de muchos tipos: pistolas modernas, pistolas de iluminaci\u00f3n, lanzacohetes, sables de iluminaci\u00f3n, katanas, martillos, martillos de iluminaci\u00f3n, etc.",
         "Desde": "",
         "Hasta": "2024/05/20 23:00",
         "URL": "https://ultra-fun-games.itch.io/fun-shooting-playground",
         "IMG": "https://img.itch.zone/aW1hZ2UvMTIyNTUzMS83MTQ2MDIzLnBuZw==/347x500/CbvXLL.png",
         "Distribuidora": "Itch io",
         "Borde": "border-color: #00ff00;"
      },
      {
         "Nombre": "ULTRA CLIMBING PLAYGROUNDS (VR  Platformer/Climbing Game for Oculus Quest) by ULTRA FUN GAMES",
         "Informacion": "\u00a1Este es un juego si quieres experimentar con escalada libre, tirolesa, plataformas y caminatas en planchas, pero en niveles que a\u00fan no has visto!",
         "Desde": "",
         "Hasta": "2024/05/20 23:00",
         "URL": "https://ultra-fun-games.itch.io/climbing-playgrounds",
         "IMG": "https://img.itch.zone/aW1hZ2UvMTA3MzU4Ny82MTU0NzgwLmpwZw==/347x500/u6WZin.jpg",
         "Distribuidora": "Itch io",
         "Borde": "border-color: #00ff00;"
      },
      {
         "Nombre": "Ultra Explorer: Jurassic Forest ( VR Dinosaurs Game for Oculus Quest) by ULTRA FUN GAMES",
         "Informacion": "UItra Fun Games presenta Ultra Explorer: \u00a1Bosque Jur\u00e1sico!",
         "Desde": "",
         "Hasta": "2024/05/20 23:00",
         "URL": "https://ultra-fun-games.itch.io/ultra-explorer-jurassic-forest",
         "IMG": "https://img.itch.zone/aW1hZ2UvMTAyMDk3MS81ODIwMDU2LmpwZw==/347x500/QA9sc7.jpg",
         "Distribuidora": "Itch io",
         "Borde": "border-color: #00ff00;"
      },
      {
         "Nombre": "Oceanox by oceanoxstudios",
         "Informacion": "\u00bfQu\u00e9 es Oceanox?",
         "Desde": "",
         "Hasta": "2024/05/21 16:00",
         "URL": "https://oceanoxstudios.itch.io/oceanox",
         "IMG": "https://img.itch.zone/aW1nLzE0MTM0ODU3LnBuZw==/347x500/giwCrH.png",
         "Distribuidora": "Itch io",
         "Borde": "border-color: #00ff00;"
      },
      {
         "Nombre": "CarCreatorTycoon by LightShadowGames",
         "Informacion": "CarCreatorTycoon es un juego de clics con carreras. Haz clic y compite para obtener la mejor puntuaci\u00f3n.",
         "Desde": "",
         "Hasta": "2024/05/23 08:00",
         "URL": "https://lightshadowgames.itch.io/carcreatortycoon",
         "IMG": "https://img.itch.zone/aW1hZ2UvMjQwMzQ0Ny8xNDIyODgzMi5wbmc=/347x500/mlC3s3.png",
         "Distribuidora": "Itch io",
         "Borde": "border-color: #00ff00;"
      },
      {
         "Nombre": "Sparkit 3-Month Free License Key Giveaway Full Version",
         "Informacion": "Saluda a Sparkit si est\u00e1s buscando una herramienta para capturar fotogramas espec\u00edficos y crear contenido promocional. Esta maravillosa herramienta te ayudar\u00e1 a capturar y combinar capturas de pantalla de videos para despertar la imaginaci\u00f3n y hacer realidad tus ideas. Si eres artista, escritor, dise\u00f1ador o simplemente alguien apasionado por la innovaci\u00f3n, esta herramienta tambi\u00e9n puede ayudarte a transformar videoclips comunes en im\u00e1genes ricas y editables que cuentan una historia o resaltan detalles espec\u00edficos.",
         "Desde": "",
         "Hasta": "2024/05/27 00:00",
         "URL": "https://giveaway.tickcoupon.com/sparkit-free-license-key-full-version/",
         "IMG": "https://giveaway.tickcoupon.com/wp-content/uploads/2024/04/sparkit-boxshot.png",
         "Distribuidora": "Tickcoupon Giveaway",
         "Borde": "border-color: #00ff00;"
      },
      {
         "Nombre": "Leawo Video Converter Free License Key 1 Year Giveaway",
         "Informacion": "\u00bfEst\u00e1 buscando un software completo de conversi\u00f3n de v\u00eddeo? Leawo Video Converter (para Mac o Windows) es la opci\u00f3n n\u00famero 1. Le permite realizar conversiones entre todos los formatos populares de video y audio: MP4 a AVI, MPEG a MOV, MKV a FLV, F4V a WebM, MOV a MP3, RMVB a AAC, MTS a M4A, RM a OGG, etc. Normalmente, su precio es $29.95. Pero ahora puedes obtener la clave gratuita de Leawo Video Converter.",
         "Desde": "",
         "Hasta": "2024/05/30 00:00",
         "URL": "https://giveaway.tickcoupon.com/leawo-video-converter-free-license-key/",
         "IMG": "https://giveaway.tickcoupon.com/wp-content/uploads/2023/05/leawo-video-converter-box.png",
         "Distribuidora": "Tickcoupon Giveaway",
         "Borde": "border-color: #00ff00;"
      },
      {
         "Nombre": "Office Cats by Ken's Studio",
         "Informacion": "Los gatos corren en tu escritorio ayud\u00e1ndote a relajarte y reducir el estr\u00e9s",
         "Desde": "",
         "Hasta": "2024/05/30 19:00",
         "URL": "https://ken-pham.itch.io/office-cats",
         "IMG": "https://img.itch.zone/aW1hZ2UvMjU5MTczOC8xNTQzMzcyOC5wbmc=/347x500/QZl%2Bgb.png",
         "Distribuidora": "Itch io",
         "Borde": "border-color: #00ff00;"
      },
      {
         "Nombre": "Sukuna by Ken's Studio",
         "Informacion": "\u00a1Prep\u00e1rate para desatar el caos en el emocionante juego de acci\u00f3n hack-and-slash basado en la popular serie de anime Jujutsu Kaisen! Como Sukuna, asumir\u00e1s el papel de un poderoso demonio y causar\u00e1s estragos entre tus enemigos. Con gr\u00e1ficos impresionantes y una jugabilidad trepidante, este juego seguramente te mantendr\u00e1 al borde de tu asiento. \u00a1\u00danete a la batalla y experimenta la emoci\u00f3n de liberar tu demonio interior!",
         "Desde": "",
         "Hasta": "2024/05/30 19:00",
         "URL": "https://ken-pham.itch.io/sukuna",
         "IMG": "https://img.itch.zone/aW1hZ2UvMjU2MDMzOS8xNTM4MjY1OS5qcGc=/347x500/osxAQT.jpg",
         "Distribuidora": "Itch io",
         "Borde": "border-color: #00ff00;"
      },
      {
         "Nombre": "One Spike by AL7USSAIN",
         "Informacion": "Es un juego dif\u00edcil en 2D con trampas dif\u00edciles.",
         "Desde": "",
         "Hasta": "2024/05/30 23:00",
         "URL": "https://al7ussain.itch.io/one-spike",
         "IMG": "https://img.itch.zone/aW1hZ2UvMjMxMjg0My8xMzcwNTA0OS5wbmc=/347x500/jTQk06.png",
         "Distribuidora": "Itch io",
         "Borde": "border-color: #00ff00;"
      },
      {
         "Nombre": "Here We Go Again by AL7USSAIN",
         "Informacion": "",
         "Desde": "",
         "Hasta": "2024/05/30 23:00",
         "URL": "https://al7ussain.itch.io/hear-we-go-again",
         "IMG": "https://img.itch.zone/aW1hZ2UvMjMwMDg4My8xMzYzNTM3OC5wbmc=/347x500/B9tR8c.png",
         "Distribuidora": "Itch io",
         "Borde": "border-color: #00ff00;"
      },
      {
         "Nombre": "Zombie Hunter by AL7USSAIN",
         "Informacion": "WDAS PARA MOVIMIENTO",
         "Desde": "",
         "Hasta": "2024/05/30 23:00",
         "URL": "https://al7ussain.itch.io/zombie-hunter",
         "IMG": "https://img.itch.zone/aW1hZ2UvMjI0MjMyNi8xMzI4NDEzNC5wbmc=/347x500/1PphEM.png",
         "Distribuidora": "Itch io",
         "Borde": "border-color: #00ff00;"
      },
      {
         "Nombre": "Simple Tasks by AL7USSAIN",
         "Informacion": "",
         "Desde": "",
         "Hasta": "2024/05/30 23:00",
         "URL": "https://al7ussain.itch.io/simple-tasks",
         "IMG": "https://img.itch.zone/aW1nLzEzMjQ3OTY0LnBuZw==/347x500/tqrJuo.png",
         "Distribuidora": "Itch io",
         "Borde": "border-color: #00ff00;"
      },
      {
         "Nombre": "Maze by AL7USSAIN",
         "Informacion": "Movimiento WASD",
         "Desde": "",
         "Hasta": "2024/05/30 23:00",
         "URL": "https://al7ussain.itch.io/maze",
         "IMG": "https://img.itch.zone/aW1nLzEzMjAyODQ1LnBuZw==/347x500/1A3FxW.png",
         "Distribuidora": "Itch io",
         "Borde": "border-color: #00ff00;"
      },
      {
         "Nombre": "Foxy Man by AL7USSAIN",
         "Informacion": "C\u00f3mo mover",
         "Desde": "",
         "Hasta": "2024/05/30 23:00",
         "URL": "https://al7ussain.itch.io/foxy-man",
         "IMG": "https://img.itch.zone/aW1hZ2UvMjIxNzUyMC8xMzExODc2OS5wbmc=/347x500/3xVBSw.png",
         "Distribuidora": "Itch io",
         "Borde": "border-color: #00ff00;"
      },
      {
         "Nombre": "STRIKE by AL7USSAIN",
         "Informacion": "",
         "Desde": "",
         "Hasta": "2024/05/30 23:00",
         "URL": "https://al7ussain.itch.io/strike",
         "IMG": "https://img.itch.zone/aW1hZ2UvMjIwNDM2MC8xMzAzMzA0Ny5qcGc=/347x500/fIRkaF.jpg",
         "Distribuidora": "Itch io",
         "Borde": "border-color: #00ff00;"
      },
      {
         "Nombre": "square run by AL7USSAIN",
         "Informacion": "",
         "Desde": "",
         "Hasta": "2024/05/30 23:00",
         "URL": "https://al7ussain.itch.io/square-run",
         "IMG": "https://img.itch.zone/aW1hZ2UvMjIwMjA3Ny8xMzAxODUzMC5wbmc=/347x500/ZMxkZd.png",
         "Distribuidora": "Itch io",
         "Borde": "border-color: #00ff00;"
      },
      {
         "Nombre": "Fish Runner by AL7USSAIN",
         "Informacion": "Fish Runner es un divertido juego 2d sin fin",
         "Desde": "",
         "Hasta": "2024/05/30 23:00",
         "URL": "https://al7ussain.itch.io/fish-runner",
         "IMG": "https://img.itch.zone/aW1hZ2UvMjE3NDU2Ny8xMjgzNTM0My5wbmc=/347x500/FOKU8J.png",
         "Distribuidora": "Itch io",
         "Borde": "border-color: #00ff00;"
      },
      {
         "Nombre": "Zombie Town_ Living In The City by Yuneek",
         "Informacion": "Un sencillo juego de zombies que hice con emparejamiento en l\u00ednea. Tiene un modo para un jugador bastante simple, todo lo que tienes que hacer es cargar un juego t\u00fa mismo y te dar\u00e1 un cron\u00f3metro e intentar\u00e1s sobrevivir el mayor tiempo posible.",
         "Desde": "",
         "Hasta": "2024/05/31 06:00",
         "URL": "https://yuneek.itch.io/zombie-townghost-town",
         "IMG": "https://img.itch.zone/aW1nLzE0Mzg5MDI0LnBuZw==/347x500/myGucj.png",
         "Distribuidora": "Itch io",
         "Borde": "border-color: #00ff00;"
      },
      {
         "Nombre": "The Wind Turbine by JEMCraftStudios",
         "Informacion": "Acceso temprano",
         "Desde": "",
         "Hasta": "2024/05/31 06:00",
         "URL": "https://jemcraftstudios.itch.io/the-wind-turbine",
         "IMG": "https://img.itch.zone/aW1nLzE1MzcyNzkzLnBuZw==/347x500/RZ%2BW3Z.png",
         "Distribuidora": "Itch io",
         "Borde": "border-color: #00ff00;"
      },
      {
         "Nombre": "Risky Jump Journey by Yuneek",
         "Informacion": "\u00a1Salta y esquiva las trampas y supera los 20 niveles para ganar! Pero si pierdes... reinicias desde el principio.",
         "Desde": "",
         "Hasta": "2024/05/31 06:00",
         "URL": "https://yuneek.itch.io/risky-jump-journey",
         "IMG": "https://img.itch.zone/aW1hZ2UvNzk1ODg3LzQ0NjAwNzgucG5n/347x500/uUCqRa.png",
         "Distribuidora": "Itch io",
         "Borde": "border-color: #00ff00;"
      },
      {
         "Nombre": "CTHULHU: Frozen Nightmare by VIRTUA WORLDS",
         "Informacion": "Cthulhu espera so\u00f1ando... hasta que unos extra\u00f1os cultistas del lejano norte lo despiertan. \u00a1Usa tu avi\u00f3n para devolver a Cthulhu a su sue\u00f1o helado o muere en el intento!",
         "Desde": "",
         "Hasta": "2024/05/31 09:00",
         "URL": "https://virtuaworlds.itch.io/cthulhu-frozen-nightmare",
         "IMG": "https://img.itch.zone/aW1hZ2UvNjY3NTk2LzM2MTYzMDcuZ2lm/347x500/dUHTIS.gif",
         "Distribuidora": "Itch io",
         "Borde": "border-color: #00ff00;"
      },
      {
         "Nombre": "REMAKO Visualizer by VIRTUA WORLDS",
         "Informacion": "REMAKO Visualizer es un visualizador de m\u00fasica interactivo en tiempo real que presenta m\u00fasica de \"REMAKO (Final Fantasy 7)\" de Mercurius FM y Stux. yo. Esta demostraci\u00f3n t\u00e9cnica utiliza trazado de rayos (en hardware compatible) desarrollado en Unreal Engine 4.24.",
         "Desde": "",
         "Hasta": "2024/05/31 09:00",
         "URL": "https://virtuaworlds.itch.io/remako-visualizer",
         "IMG": "https://img.itch.zone/aW1hZ2UvNjUyNDEwLzM1MDE1OTUuZ2lm/347x500/lcZcae.gif",
         "Distribuidora": "Itch io",
         "Borde": "border-color: #00ff00;"
      },
      {
         "Nombre": "COLUMNS by VIRTUA WORLDS",
         "Informacion": "COLUMNS, una experiencia art\u00edstica Vaporwave VR (y no VR)",
         "Desde": "",
         "Hasta": "2024/05/31 09:00",
         "URL": "https://virtuaworlds.itch.io/columns",
         "IMG": "https://img.itch.zone/aW1hZ2UvMjUzNDQwLzEyMTM0NzMuanBn/347x500/IcltuV.jpg",
         "Distribuidora": "Itch io",
         "Borde": "border-color: #00ff00;"
      },
      {
         "Nombre": "Z invasion by KS GAMES",
         "Informacion": "-------------------------------------------------- -------------------",
         "Desde": "",
         "Hasta": "2024/05/31 12:00",
         "URL": "https://gamerevolutionx.itch.io/zinvasion2",
         "IMG": "https://img.itch.zone/aW1hZ2UvMjM3ODI5OS8xNDIxMDQ4MS5qcGc=/347x500/JkYtJ%2B.jpg",
         "Distribuidora": "Itch io",
         "Borde": "border-color: #00ff00;"
      },
      {
         "Nombre": "Circuit 7 by Funky Tiger Highsaturn",
         "Informacion": "3 2 1 \u00a1\u00a1\u00a1INDIE 700 WORLD TOURMINI LOOP TRUCO CONTRARRELOJ",
         "Desde": "",
         "Hasta": "2024/07/01 07:00",
         "URL": "https://qjzsezhi.itch.io/circuit-7",
         "IMG": "https://img.itch.zone/aW1hZ2UvNjY0NjA5Lzg1NTU3MDcuZ2lm/347x500/Xmxgkx.gif",
         "Distribuidora": "Itch io",
         "Borde": "border-color: #00ff00;"
      },
      {
         "Nombre": "Geograph by Funky Tiger Highsaturn",
         "Informacion": "infinitas formaciones para relajarse y dejarse perplejo",
         "Desde": "",
         "Hasta": "2024/07/01 07:00",
         "URL": "https://qjzsezhi.itch.io/geograph",
         "IMG": "https://img.itch.zone/aW1hZ2UvOTg2MTUvOTIwMzI5LmdpZg==/347x500/89EXBO.gif",
         "Distribuidora": "Itch io",
         "Borde": "border-color: #00ff00;"
      },
      {
         "Nombre": "Iota by Funky Tiger Highsaturn",
         "Informacion": "mascota de escritorio virtual",
         "Desde": "",
         "Hasta": "2024/07/01 07:00",
         "URL": "https://qjzsezhi.itch.io/iota",
         "IMG": "https://img.itch.zone/aW1nLzI5MjE4NjIucG5n/347x500/ouoxq0.png",
         "Distribuidora": "Itch io",
         "Borde": "border-color: #00ff00;"
      },
      {
         "Nombre": "Key by Funky Tiger Highsaturn",
         "Informacion": "[+\u00e2\u00a2\u00e2\u00a2] Proyecto 24solo",
         "Desde": "",
         "Hasta": "2024/07/01 07:00",
         "URL": "https://qjzsezhi.itch.io/key",
         "IMG": "https://img.itch.zone/aW1hZ2UvMzc0MTU3LzE4NzY0MjQucG5n/347x500/fUhihI.png",
         "Distribuidora": "Itch io",
         "Borde": "border-color: #00ff00;"
      },
      {
         "Nombre": "Techna \u00e2\u009a\u00ac Alpha by Roomah Gaming",
         "Informacion": "Este proyecto prototipo comenz\u00f3 el 25 de agosto de 2021 y se envi\u00f3 a #summerslowjams y #sunofes game jam. Aunque por no tener el mejor estado de \u00e1nimo, esto es lo que tengo para presentar.",
         "Desde": "",
         "Hasta": "2024/09/08 18:00",
         "URL": "https://roomahgaming.itch.io/techna",
         "IMG": "https://img.itch.zone/aW1hZ2UvMTE3NDg0MC82ODcyMTMzLnBuZw==/347x500/zsIjb1.png",
         "Distribuidora": "Itch io",
         "Borde": "border-color: #00ff00;"
      },
      {
         "Nombre": "Bones in the Boneyard: Halloween Falling Skulls Game by John D. Moore",
         "Informacion": "Hay muchos huesos en el cementerio. A medida que caen de la pantalla, organiza las calaveras en l\u00edneas de tres para eliminarlas y alinea esqueletos completos para liberarlas.",
         "Desde": "",
         "Hasta": "2024/10/31 08:00",
         "URL": "https://jdmgames.itch.io/bones-in-the-boneyard",
         "IMG": "https://img.itch.zone/aW1hZ2UvMTc3MTM2OS8xMDQxMzcyNy5wbmc=/347x500/sGD27W.png",
         "Distribuidora": "Itch io",
         "Borde": "border-color: #00ff00;"
      },
      {
         "Nombre": "Dr. Creepinscare's Pumpkin Patch Match by John D. Moore",
         "Informacion": "\u00a1El Dr. Creepinscare est\u00e1 aqu\u00ed para invitarte a poner a prueba tu ingenio y reflejos en su diab\u00f3lico huerto de calabazas! Divi\u00e9rtete espeluznantemente colocando las calabazas que caen en arreglos especiales para despejar el campo. El genio loco del Dr. Creepinscare ha ideado que todas las calabazas tengan caras talladas de manera similar. \u00a1Estar alerta!",
         "Desde": "",
         "Hasta": "2024/10/31 08:00",
         "URL": "https://jdmgames.itch.io/pumpkin-patch-match",
         "IMG": "https://img.itch.zone/aW1hZ2UvMTgzNjUwLzg1ODY2My5wbmc=/347x500/f%2Fd9MK.png",
         "Distribuidora": "Itch io",
         "Borde": "border-color: #00ff00;"
      },
      {
         "Nombre": "Monster Hug by John D. Moore",
         "Informacion": "Bienvenidos a MONSTER HUG.",
         "Desde": "",
         "Hasta": "2024/10/31 08:00",
         "URL": "https://jdmgames.itch.io/monster-hug",
         "IMG": "https://img.itch.zone/aW1hZ2UvMzE0NzIwLzE1NDgwNTIucG5n/347x500/c7ocxL.png",
         "Distribuidora": "Itch io",
         "Borde": "border-color: #00ff00;"
      },
      {
         "Nombre": "Village Vampire Feast by John D. Moore",
         "Informacion": "Una actualizaci\u00f3n de 2018 de un juego que cre\u00e9 en 2012.",
         "Desde": "",
         "Hasta": "2024/10/31 08:00",
         "URL": "https://jdmgames.itch.io/village-vampire-feast",
         "IMG": "https://img.itch.zone/aW1hZ2UvMzE2Mjg4LzE1NTcyMTMucG5n/347x500/caO9Uj.png",
         "Distribuidora": "Itch io",
         "Borde": "border-color: #00ff00;"
      },
      {
         "Nombre": "Bunny Hill Horror by Krunchy Fried Games",
         "Informacion": "Actualizaci\u00f3n: El cap\u00edtulo final: Bunny Hill Horror: Bunny Boiler, \u00a1ahora en itch.io!",
         "Desde": "",
         "Hasta": "2025/01/01 01:59",
         "URL": "https://krunchyfriedgames.itch.io/bunny-hill-horror",
         "IMG": "https://img.itch.zone/aW1hZ2UvNTAxOTIyLzI1OTc2ODEucG5n/347x500/uATBvN.png",
         "Distribuidora": "Itch io",
         "Borde": "border-color: #00ff00;"
      },
      {
         "Nombre": "Bunny Hill Horror: Bunny Boiler by Krunchy Fried Games",
         "Informacion": "Oswald Mandias es un hombre con una misi\u00f3n: arrastrar al pa\u00eds pataleando y gritando de regreso a los d\u00edas de gloria de anta\u00f1o, donde un caballero pod\u00eda confiar en los valores probados por el tiempo de la caballerosidad, la crianza y la clase. Armado con zombis feroces, una reserva de productos farmac\u00e9uticos muy cuestionables y una voluntad de hierro, te ha reclutado para hacer realidad sus planes.",
         "Desde": "",
         "Hasta": "2025/01/01 01:59",
         "URL": "https://krunchyfriedgames.itch.io/bunny-hill-horror-bunny-boiler",
         "IMG": "https://img.itch.zone/aW1hZ2UvNzkwNzU0LzQ0Mjc2NDQuanBn/347x500/B16Bli.jpg",
         "Distribuidora": "Itch io",
         "Borde": "border-color: #00ff00;"
      },
      {
         "Nombre": "Witches and Bandits and Swords (Oh My) by Krunchy Fried Games",
         "Informacion": "Witches and Bandits and Swords (Oh My) es un juego de novela gr\u00e1fica de elecci\u00f3n de aventuras solo para mouse en el que debes explorar bosques peligrosos, salvar a tus amigos de una conspiraci\u00f3n pirata y evitar a un b\u00e1rbaro particularmente extra\u00f1o que quiere hacerte cosas desagradables. entra\u00f1as blandas.",
         "Desde": "",
         "Hasta": "2025/01/01 01:59",
         "URL": "https://krunchyfriedgames.itch.io/witches-and-bandits-and-swords-oh-my",
         "IMG": "https://img.itch.zone/aW1hZ2UvMTg4NTc3Lzg4NDQ4MS5qcGc=/347x500/2Oaqw3.jpg",
         "Distribuidora": "Itch io",
         "Borde": "border-color: #00ff00;"
      },
      {
         "Nombre": "Redwood Lake Incident by ToMar Dev",
         "Informacion": "Juego corto sobre unas vacaciones en la caba\u00f1a. El juego contiene di\u00e1logos y jumpscares. Este juego est\u00e1 inspirado en Fears to Fathom.",
         "Desde": "",
         "Hasta": "2028/03/28 00:00",
         "URL": "https://tomar-dev.itch.io/redwood-lake-incident",
         "IMG": "https://img.itch.zone/aW1hZ2UvMjIzMTk0MC8xMzI3MDQ3My5wbmc=/347x500/HLaHZX.png",
         "Distribuidora": "Itch io",
         "Borde": "border-color: #00ff00;"
      },
      {
         "Nombre": "Jack VS The Uberwaffe [REWORK 0.1] by Nevada Vacho",
         "Informacion": "\u00a1Juegas como Jack!",
         "Desde": "",
         "Hasta": "2029/07/15 00:00",
         "URL": "https://nevadavetacheese.itch.io/jackvs",
         "IMG": "https://img.itch.zone/aW1hZ2UvOTI2NjQ0LzUyNDExNDMucG5n/347x500/Gdkl5B.png",
         "Distribuidora": "Itch io",
         "Borde": "border-color: #00ff00;"
      },
      {
         "Nombre": "Katakombs [ON HOLD] by Nevada Vacho",
         "Informacion": "\u00bfCorre y salta?",
         "Desde": "",
         "Hasta": "2029/07/15 00:00",
         "URL": "https://nevadavetacheese.itch.io/katakombs",
         "IMG": "https://img.itch.zone/aW1hZ2UvMTEzNjIwMy83MTMxMzQ2LnBuZw==/347x500/6fMc0j.png",
         "Distribuidora": "Itch io",
         "Borde": "border-color: #00ff00;"
      },
      {
         "Nombre": "Onions (Android) [Test] by Nevada Vacho",
         "Informacion": "\u00a1Eres Smash-Guy! Solo quiere algunas cebollas para su hamburguesa vegana de berenjena (marca pendiente), \u00a1pero las perdi\u00f3 todas! Ay\u00fadalo a recuperarlos, \u00a1pero cuidado! Deadly Chompers lo persiguen, tratando de evitar que Smash-Guy recoja las cebollas.",
         "Desde": "",
         "Hasta": "2029/07/15 00:00",
         "URL": "https://nevadavetacheese.itch.io/onions-apk",
         "IMG": "https://img.itch.zone/aW1hZ2UvMTExMjg5Ni82NDM3NjI4LmpwZw==/347x500/pVXMf7.jpg",
         "Distribuidora": "Itch io",
         "Borde": "border-color: #00ff00;"
      },
      {
         "Nombre": "I Get This Call Every Day by David S Gallant",
         "Informacion": "Exactamente lo que dice en la caja: una experiencia ligeramente filtrada extra\u00edda de mi (ahora anterior) trabajo diario en un centro de atenci\u00f3n al cliente, hecha interactiva en un formato de apuntar y hacer clic. Pierde cort\u00e9smente, o pierde espectacularmente; la decisi\u00f3n es tuya.",
         "Desde": "",
         "Hasta": "2057/03/16 00:00",
         "URL": "https://davidsgallant.itch.io/i-get-this-call-every-day",
         "IMG": "https://img.itch.zone/aW1hZ2UvMzQyLzMxNzU0My5wbmc=/347x500/PyFxVy.png",
         "Distribuidora": "Itch io",
         "Borde": "border-color: #00ff00;"
      },
      {
         "Nombre": "Greak: Memories of Azur",
         "Informacion": "Greak: Memories of Azur es un juego para un jugador de desplazamiento lateral con animaciones dibujadas a mano. Tomar\u00e1s el papel de tres hermanos: Greak, Adara y Raydel para guiarlos a trav\u00e9s de las tierras de Azur. Alterna el control entre ellos y usa sus habilidades \u00fanicas para escapar de la invasi\u00f3n Urlag....",
         "Desde": "",
         "Hasta": "2758/11/11 07:00",
         "URL": "https://www.gog.com/en/game/greak_memories_of_azur",
         "IMG": "https://images.gog-statics.com/4d2508cf24589d577bb7b19ae728a0d75914e57519394255e48c1353bcd7adaa.jpg",
         "Distribuidora": "GOG",
         "Borde": "border-color: #00ff00;"
      },
      {
         "Nombre": "Worms Revolution Gold Edition",
         "Informacion": "Incluye: Worms Revolution, Worms Revolution - Customization Pack, Worms Revolution - Mars Pack, Worms Revolution: Funfair DLC, Worms Revolution: Medieval Tales DLCWorms\u2122 Revolution es otra entrega de la cl\u00e1sica serie de estrategia por turnos que llega a la PC, \u00a0con emocionantes nuevas caracter\u00edsticas y...",
         "Desde": "",
         "Hasta": "2769/10/24 07:00",
         "URL": "https://www.gog.com/en/game/worms_revolution",
         "IMG": "https://images.gog-statics.com/f3f88804947ca5f684f2b7547c6ae2f35fde5aaa71cdfdc24dec27e9e192d76c.jpg",
         "Distribuidora": "GOG",
         "Borde": "border-color: #00ff00;"
      },
      {
         "Nombre": "Daymare: 1998",
         "Informacion": "DAYMARE: 1998 es un horror de supervivencia en tercera persona con mec\u00e1nicas de supervivencia extremas y enemigos dif\u00edciles de matar. Requiere un enfoque estrat\u00e9gico para el combate y los acertijos, y ofrece un punto de vista de varios personajes sobre la historia, revelando una historia profunda y oscura. La escena est\u00e1 ambientada con una investigaci\u00f3n secreta...",
         "Desde": "",
         "Hasta": "2778/01/10 07:00",
         "URL": "https://www.gog.com/en/game/daymare_1998",
         "IMG": "https://images.gog-statics.com/2e45a6a84c14e124fe2260a1b9d096740df546314ecc6055a7d78983b6967a67.jpg",
         "Distribuidora": "GOG",
         "Borde": "border-color: #00ff00;"
      },
      {
         "Nombre": "Haven Park",
         "Informacion": "`Me estoy haciendo mayor, querida, y ya no puedo cuidar el parque... \u00bfMe ayudar\u00e1s a devolverle la vida a este lugar?` S\u00e9 Flint, que est\u00e1 haciendo todo lo posible para mantener el parque de su abuela en funcionamiento y convertirlo en un lugar para que disfruten los campistas. Aprende la wi del camper...",
         "Desde": "",
         "Hasta": "2835/07/10 07:00",
         "URL": "https://www.gog.com/en/game/haven_park",
         "IMG": "https://images.gog-statics.com/0c9dc9e333dc626b528af27505690a879439a1c729d1e7a69a53c57ccb8366a6.jpg",
         "Distribuidora": "GOG",
         "Borde": "border-color: #00ff00;"
      },
      {
         "Nombre": "CDPR Goodie Pack",
         "Informacion": "El paquete contiene carteles, fondos de pantalla digitales, artes conceptuales y m\u00e1s de los juegos de The Witcher y Cyberpunk 2077. Para descargar los art\u00edculos, ve a tu Biblioteca en GOG.",
         "Desde": "",
         "Hasta": "2852/12/22 07:00",
         "URL": "https://www.gog.com/en/game/cdpr_goodie_pack",
         "IMG": "https://images.gog-statics.com/ffe4b876306351db5baf567922f0f5840ff89c42c879ce371a7e53ad604368c0.jpg",
         "Distribuidora": "GOG",
         "Borde": "border-color: #00ff00;"
      },
      {
         "Nombre": "CHUCHEL & Botanicula - Goodie Pack",
         "Informacion": "CHUCHEL & Botanicula - Goodie Pack incluye:CHUCHEL Soundtrack + Art BookBotanicula Soundtrack + Art Book",
         "Desde": "",
         "Hasta": "2901/03/26 07:00",
         "URL": "https://www.gog.com/en/game/chuchel_botanicula_goodie_pack",
         "IMG": "https://images.gog-statics.com/c30d5cc7f392f8f774dae4f75525f0a57a54b2d74f630d479bb012583639a72a.jpg",
         "Distribuidora": "GOG",
         "Borde": "border-color: #00ff00;"
      },
      {
         "Nombre": "Alien Breed Trilogy",
         "Informacion": "Experimenta lo \u00faltimo en acci\u00f3n de ciencia ficci\u00f3n con Alien Breed\u2122 Trilogy: tres t\u00edtulos de arcade de disparos en una fant\u00e1stica colecci\u00f3n, juntos por primera vez. La trilog\u00eda Alien Breed\u2122 resucita una franquicia muy reverenciada con una narrativa \u00e9pica, enjambres de enemigos alien\u00edgenas inteligentes,...",
         "Desde": "",
         "Hasta": "2903/12/21 07:00",
         "URL": "https://www.gog.com/en/game/alien_breed_trilogy",
         "IMG": "https://images.gog-statics.com/7afa8bdeb6b3df9be397fd48af4444e110b973a6b602c628a6b3a8b8a206f77f.jpg",
         "Distribuidora": "GOG",
         "Borde": "border-color: #00ff00;"
      },
      {
         "Nombre": "Biing!: Sex, Intrigue and Scalpels",
         "Informacion": "Aviso de contenido para adultos: Biing!: Sex, Intrigue and Scalpels contiene lenguaje expl\u00edcito, fuertes temas sexuales, desnudez y est\u00e1 destinado a audiencias maduras. La secuela: \u00a1Biing! 2 se incluye con el juego como obsequio adicional. Disponible solo en alem\u00e1n. Chiflado, gr\u00e1ficamente brillante, extremadamente divertido y...",
         "Desde": "",
         "Hasta": "2912/03/08 07:00",
         "URL": "https://www.gog.com/en/game/biing_sex_intrigue_and_scalpels",
         "IMG": "https://images.gog-statics.com/7f24b74f699678450a1750d71cce31bdbe56d9a0403e9512637edb010207747d.jpg",
         "Distribuidora": "GOG",
         "Borde": "border-color: #00ff00;"
      },
      {
         "Nombre": "Figment",
         "Informacion": "Figment 2: Creed Valley, \u00a1a la venta el 9 de marzo! Una aventura musical de acci\u00f3n ambientada en los recovecos de la mente humana... Bienvenido al mundo de Figment. Un mundo extra\u00f1o y surrealista; un lugar lleno de nuestros pensamientos, impulsos y recuerdos m\u00e1s profundos, poblado por las muchas voces que escuchamos en nuestras cabezas. Esta m...",
         "Desde": "",
         "Hasta": "2959/01/26 07:00",
         "URL": "https://www.gog.com/en/game/figment",
         "IMG": "https://images.gog-statics.com/c8d0c9882d6d6da599d0a423d1e660269b9c63503a60d6eb6d33f87488b2ade8.jpg",
         "Distribuidora": "GOG",
         "Borde": "border-color: #00ff00;"
      },
      {
         "Nombre": "Lorelai",
         "Informacion": "Lorelai nunca olvidar\u00e1 ese d\u00eda. Lo poco que ten\u00eda se lo quitaron. Todo su mundo se desintegr\u00f3. En realidad nunca tuvo una oportunidad, pero Lorelai se neg\u00f3 a darse por vencida. ella luchar\u00e1 Y ni siquiera la muerte le impedir\u00e1 recuperarlo todo. Lorelai, de Harvester Games, es la contundente...",
         "Desde": "",
         "Hasta": "2997/01/21 07:00",
         "URL": "https://www.gog.com/en/game/lorelai",
         "IMG": "https://images.gog-statics.com/7617a137a072c7596d06f2bbf31a7744050be0e32735e7e7b25c31bdf1dd4434.jpg",
         "Distribuidora": "GOG",
         "Borde": "border-color: #00ff00;"
      },
      {
         "Nombre": "Backbone: Prologue",
         "Informacion": "Backbone: Prologue is the first act of a noir roleplaying detective adventure. You are raccoon private eye Howard Lotor, a second-class citizen of dystopian Vancouver, BC inhabited by animals. Interrogate a diverse cast of characters, collect evidence, and choose which leads to follow.",
         "Desde": "",
         "Hasta": "2999/02/10 19:00",
         "URL": "https://www.humblebundle.com/store/backbone-prologue",
         "IMG": "https://hb.imgix.net/199751202b253069287b845c2380fff0eef5d62a.jpg?auto=compress,format&fit=crop&h=353&w=616&s=8ee7384524e09308706c4fbd7ba10b25",
         "Distribuidora": "Humble Bundle",
         "Borde": "border-color: #00ff00;"
      },
      {
         "Nombre": "Crying Suns Demo",
         "Informacion": "Crying Suns es un rogue-lite de exploraci\u00f3n t\u00e1ctica en el que encarnas a un gran almirante que explora su imperio ca\u00eddo. Descubre la verdad sobre el Imperio y sobre ti mismo en una historia inspirada por cl\u00e1sicos como Fundaci\u00f3n y Dune.",
         "Desde": "",
         "Hasta": "3000/01/01 09:00",
         "URL": "https://www.humblebundle.com/store/crying-suns-demo",
         "IMG": "https://i.ytimg.com/vi/cmwFRlxMhW0/maxresdefault.jpg",
         "Distribuidora": "Humble Bundle",
         "Borde": "border-color: #00ff00;"
      },
      {
         "Nombre": "Neurodeck: Psychological Deckbuilder",
         "Informacion": "Neurodeck: la demostraci\u00f3n de Psychological Deckbuilder est\u00e1 disponible aqu\u00ed. Caracter\u00edsticas Construcci\u00f3n de mazos a medida que avanzas en el juego (como Slay The Spire) Medita y elige rasgos de personalidad que alteran profundamente tu juego Explora un laberinto subconsciente, lleno de cartas y mejoras que te...",
         "Desde": "",
         "Hasta": "3007/11/24 15:00",
         "URL": "https://www.gog.com/en/game/neurodeck_psychological_deckbuilder",
         "IMG": "https://images.gog-statics.com/5f8058ce032742ef9f10f3208e42cc58a2b3717ac6e6b6bad9b79bf1d812e9de.jpg",
         "Distribuidora": "GOG",
         "Borde": "border-color: #00ff00;"
      },
      {
         "Nombre": "Alwa's Awakening",
         "Informacion": "En Alwa's Awakening, juegas como Zoe, una hero\u00edna enviada desde otro mundo para traer la paz a la tierra de Alwa. Equipada solo con un bast\u00f3n m\u00e1gico, se despierta en una tierra lejana y debe partir para ayudar a la gente. Atraviesa mazmorras peligrosas, conoce personajes interesantes y divertidos y explora el mundo en...",
         "Desde": "",
         "Hasta": "3016/02/10 15:00",
         "URL": "https://www.gog.com/en/game/alwas_awakening",
         "IMG": "https://images.gog-statics.com/6c5a7589529bafd7a51b77a4874687a166a09fa53c90a05dfe4d052df3013b5a.jpg",
         "Distribuidora": "GOG",
         "Borde": "border-color: #00ff00;"
      },
      {
         "Nombre": "Deep Sky Derelicts",
         "Informacion": "En un sombr\u00edo futuro dist\u00f3pico, donde la humanidad se ha dispersado por la galaxia y la sociedad humana se ha dividido en dos clases distintas, eres un pobre paria ap\u00e1trida obligado a vivir de los restos de estaciones alien\u00edgenas abandonadas y naves en el espacio exterior, pero sue\u00f1as con convirti\u00e9ndose en una ciudad privilegiada...",
         "Desde": "",
         "Hasta": "3027/01/23 15:00",
         "URL": "https://www.gog.com/en/game/deep_sky_derelicts",
         "IMG": "https://images.gog-statics.com/460e4b7f2d73d6dbe4c3993e76a28b1dc3401a2e028966e9f99c41b810b83eb3.jpg",
         "Distribuidora": "GOG",
         "Borde": "border-color: #00ff00;"
      },
      {
         "Nombre": "Under The Moon",
         "Informacion": "\u00a1\u00danete a Ali Kemal en su fant\u00e1stico viaje por el camino del amor verdadero! Under the Moon es una aventura independiente: un juego de acertijos. Si eres un entusiasta de los acertijos, te divertir\u00e1s mucho mientras resuelves acertijos en el juego mientras experimentas los gr\u00e1ficos estilizados, las bandas sonoras ambientales (que son exclusiv...",
         "Desde": "",
         "Hasta": "3103/09/22 15:00",
         "URL": "https://www.gog.com/en/game/under_the_moon",
         "IMG": "https://images.gog-statics.com/776d4de419cc2db73b92050204686ba76855ee3dd1259fecca62c3b14dba11d3.jpg",
         "Distribuidora": "GOG",
         "Borde": "border-color: #00ff00;"
      },
      {
         "Nombre": "Fiendish Freddy's Big Top o' Fun",
         "Informacion": "\u00a1Haz clic aqu\u00ed para descubrir toda la colecci\u00f3n de Throwback Entertainment! Muy bien, ni\u00f1os y ni\u00f1as. Te espera un gran placer con Fiendish Freddy's Big Top O' Fun. No tenemos uno, ni dos, sino seis, cu\u00e9ntalos hasta seis, estrafalarios juegos de emoci\u00f3n circense. S\u00ed, amigos, un verdadero deporte-o-rama. Pronto estar\u00e1s...",
         "Desde": "",
         "Hasta": "3161/03/21 15:00",
         "URL": "https://www.gog.com/en/game/fiendish_freddys_big_top_o_fun",
         "IMG": "https://images.gog-statics.com/56cab01491201c7401c02fe9816fc4f6157f4f190fd3fcba5e6d0c1dbb3021af.jpg",
         "Distribuidora": "GOG",
         "Borde": "border-color: #00ff00;"
      },
      {
         "Nombre": "System Shock Goodie Pack",
         "Informacion": "Sum\u00e9rgete m\u00e1s profundamente en el sombr\u00edo mundo de System Shock con este Goodie Pack especial, que contiene varias artes y activos de la franquicia Incluye: Im\u00e1genes de Pixel Art Im\u00e1genes de alta resoluci\u00f3n TriOptimum New Employee Technical Manual Renders de pistola de rayos Sparq Im\u00e1genes conceptuales de juguetes de System Shock Videos...",
         "Desde": "",
         "Hasta": "3191/07/25 23:00",
         "URL": "https://www.gog.com/en/game/system_shock_goodie_pack",
         "IMG": "https://images.gog-statics.com/ef914a96f398788ece592f152e051c37c211d9f8533543f8a0ee7eebe1b376eb.jpg",
         "Distribuidora": "GOG",
         "Borde": "border-color: #00ff00;"
      },
      {
         "Nombre": "Amnesia: A Machine For Pigs",
         "Informacion": "\u00a1Los cerdos se est\u00e1n levantando! En 2010, Frictional Games aterroriz\u00f3 al mundo con el horror de culto Amnesia: A Dark Descent. Ahora te traen una nueva pesadilla. Creado en colaboraci\u00f3n con The Chinese Room, el estudio detr\u00e1s de Dear Esther, Amnesia: A Machine for Pigs es un viaje intenso y aterrador en...",
         "Desde": "",
         "Hasta": "3209/10/25 15:00",
         "URL": "https://www.gog.com/en/game/amnesia_a_machine_for_pigs",
         "IMG": "https://images.gog-statics.com/b6a69dfb11bb12ba5f9c75d9c3be6f3801c2ba3a4beefeab58fefb3b32f51996.jpg",
         "Distribuidora": "GOG",
         "Borde": "border-color: #00ff00;"
      },
      {
         "Nombre": "Cyberpunk 2077 & Phantom Liberty Goodies Collection",
         "Informacion": "\u00a1Hola, chooms! Antes de emprender una misi\u00f3n imposible de espionaje y supervivencia en Phantom Liberty, la expansi\u00f3n del thriller de esp\u00edas para Cyberpunk 2077 ambientada en un distrito completamente nuevo de Night City, puedes obtener Cyberpunk 2077 y Phantom Liberty Goodies Collection gratis en GOG ahora, antes...",
         "Desde": "",
         "Hasta": "3224/10/04 23:00",
         "URL": "https://www.gog.com/en/game/cyberpunk_2077_phantom_liberty_goodies_collection",
         "IMG": "https://images.gog-statics.com/ade8204326fb8812dc7f68484408bfa5aaaef1fc5a8097e98ef83fcf146accbf.jpg",
         "Distribuidora": "GOG",
         "Borde": "border-color: #00ff00;"
      },
      {
         "Nombre": "Sigma Theory: Global Cold War",
         "Informacion": "HISTORIA De los creadores del premiado juego de ciencia ficci\u00f3n Out There... En un futuro cercano, un descubrimiento cient\u00edfico que cambia el paradigma se cierne sobre el mundo, prometiendo nuevas tecnolog\u00edas radicales. Las superpotencias del mundo se dan cuenta de que podr\u00edan tener el poder de destruir el sistema financiero mundial, aniquilar...",
         "Desde": "",
         "Hasta": "3237/11/17 15:00",
         "URL": "https://www.gog.com/en/game/sigma_theory_global_cold_war",
         "IMG": "https://images.gog-statics.com/21283146b993f480f8fc73dc1e84dc612b1fb945c276c9d474b6763c5b670949.jpg",
         "Distribuidora": "GOG",
         "Borde": "border-color: #00ff00;"
      },
      {
         "Nombre": "Hero of the Kingdom II",
         "Informacion": "Navega hasta las islas m\u00e1s lejanas para salvar a tu hermana y derrotar a los piratas. T\u00fa y tu hermana finalmente hab\u00e9is encontrado un refugio seguro en un peque\u00f1o pueblo de pescadores. Pero poco despu\u00e9s surgieron m\u00e1s problemas. La amenaza de una tripulaci\u00f3n imparable de piratas extendi\u00f3 su sombra por todo el reino. Tu querida hermana...",
         "Desde": "",
         "Hasta": "3437/09/30 17:00",
         "URL": "https://www.gog.com/en/game/hero_of_the_kingdom_ii",
         "IMG": "https://images.gog-statics.com/961a6f6832b80f6db89c149336335e824da6f0a50981920915755c8109151c1e.jpg",
         "Distribuidora": "GOG",
         "Borde": "border-color: #00ff00;"
      },
      {
         "Nombre": "King's Bounty: The Legend",
         "Informacion": "Convi\u00e9rtete en un h\u00e9roe en un mundo de fantas\u00eda de caballeros intr\u00e9pidos, magos malvados, reyes sabios y hermosas princesas. Explora la tierra, dirige ej\u00e9rcitos y completa misiones para que tu rey obtenga grandes recompensas... O sufre derrotas devastadoras. El juego se divide en dos secciones principales: modo aventura y ta...",
         "Desde": "",
         "Hasta": "3448/09/12 17:00",
         "URL": "https://www.gog.com/en/game/kings_bounty_the_legend",
         "IMG": "https://images.gog-statics.com/f43343ed27913f5749f5d517db907638bc0ff3461cffbb52ce8c1b910342e697.jpg",
         "Distribuidora": "GOG",
         "Borde": "border-color: #00ff00;"
      },
      {
         "Nombre": "Ghost Master",
         "Informacion": "`Ejercita` tus demonios. Pon a prueba a tus poltergeists y pon a tus fantasmas en marcha. Divi\u00e9rtete en este inquietante mundo inspirado en pel\u00edculas de terror cl\u00e1sicas como `Hellraiser` o `Ghost Ship`. Te conviertes en el Maestro Fantasma en una mezcla \u00fanica de estrategia, aventura y simulaci\u00f3n macabra de brujas....",
         "Desde": "",
         "Hasta": "3456/11/29 16:00",
         "URL": "https://www.gog.com/en/game/ghost_master",
         "IMG": "https://images.gog-statics.com/65b84154cbdf62ea4ea42c8cabd0ce021bc67977e6bee9203244dba9a1f1d3d1.jpg",
         "Distribuidora": "GOG",
         "Borde": "border-color: #00ff00;"
      },
      {
         "Nombre": "Requiem: Avenging Angel",
         "Informacion": "Requiem: Avenging Angel es un juego de acci\u00f3n en primera persona en 3D de proporciones b\u00edblicas ambientado en un mundo sitiado. Una guerra santa hace estragos en la Tierra entre los Soldados Elegidos del Cielo y los \u00c1ngeles Ca\u00eddos del Infierno. Eres Malachi, un \u00e1ngel elegido, enviado a la Tierra para salvar la Creaci\u00f3n de la ira de los Ca\u00eddos. Maldita seas...",
         "Desde": "",
         "Hasta": "3467/11/12 16:00",
         "URL": "https://www.gog.com/en/game/requiem_avenging_angel",
         "IMG": "https://images.gog-statics.com/b87f0e05c48ab853637ab9a486560b3f8e1d3bd56a4e944d1e29528cde80cbfe.jpg",
         "Distribuidora": "GOG",
         "Borde": "border-color: #00ff00;"
      },
      {
         "Nombre": "The Night of the Rabbit",
         "Informacion": "Pi\u00e9rdete en una historia de magia y maravillas, donde todo es posible y donde nada es lo que parece: \u00fanete al joven Jerry y sigue a un peculiar conejo blanco hasta el maravilloso reino de Mousewood, una tierra donde las criaturas pueden hablar y donde abunda el misterio. Es aqu\u00ed donde Jerry sue\u00f1a de ser...",
         "Desde": "",
         "Hasta": "3506/03/13 16:00",
         "URL": "https://www.gog.com/en/game/the_night_of_the_rabbit",
         "IMG": "https://images.gog-statics.com/f56d3261eac9291076d63afea4f246957f23a80c8d257813d2b17bb0e6fcf286.jpg",
         "Distribuidora": "GOG",
         "Borde": "border-color: #00ff00;"
      },
      {
         "Nombre": "Tr\u00fcberbrook",
         "Informacion": "\u00bbTr\u00fcberbrook\u00ab es un emocionante juego de aventuras de ciencia ficci\u00f3n y misterio. \u00a1Disfruta de unas vacaciones de aventura en un universo paralelo de los a\u00f1os 60! Un juego de aventuras y misterio de ciencia ficci\u00f3n con escenarios hechos a mano. Imag\u00ednese de vacaciones en Europa a finales de los a\u00f1os sesenta. Ahora, imag\u00ednese como un joven cient\u00edfico estadounidense...",
         "Desde": "",
         "Hasta": "3525/05/12 17:00",
         "URL": "https://www.gog.com/en/game/truberbrook",
         "IMG": "https://images.gog-statics.com/903e3abd1f5b7e521ee732a5c7c6d35390ffbe9d17f22e059276693bc608fdb9.jpg",
         "Distribuidora": "GOG",
         "Borde": "border-color: #00ff00;"
      },
      {
         "Nombre": "Blacksad: Under the Skin",
         "Informacion": "\u00a1Un oscuro esc\u00e1ndalo de corrupci\u00f3n en el coraz\u00f3n del inframundo de la ciudad de Nueva York para el carism\u00e1tico detective John Blacksad! A\u00f1os 50, Nueva York: Joe Dunn, propietario de un club de boxeo, es encontrado muerto. Mientras tanto, la estrella en ascenso Bobby Yale, que debe tomar el ring para la pelea m\u00e1s importante de su carrera, ha...",
         "Desde": "",
         "Hasta": "3602/01/08 16:00",
         "URL": "https://www.gog.com/en/game/blacksad_under_the_skin",
         "IMG": "https://images.gog-statics.com/f912ae90cebb7c071cf8eca1664c1c657c908d304a148b911f140f299df4e546.jpg",
         "Distribuidora": "GOG",
         "Borde": "border-color: #00ff00;"
      },
      {
         "Nombre": "The Whisperer",
         "Informacion": "Investiga un puesto comercial abandonado, explora sus alrededores y resuelve el terrible misterio que encierra. The Whisperer (Le Murmureur) es un juego de point & click basado en una historia corta ambientado en el Bajo Canad\u00e1 a principios del siglo XIX. Bajo Canad\u00e1, 1814. Un puesto comercial en un valle remoto...",
         "Desde": "",
         "Hasta": "3607/08/12 09:00",
         "URL": "https://www.gog.com/en/game/the_whisperer",
         "IMG": "https://images.gog-statics.com/7a9268e5b5afe8c5821bb2cd46c2930137ca316e7b67507fa3d5247e7df7b799.jpg",
         "Distribuidora": "GOG",
         "Borde": "border-color: #00ff00;"
      },
      {
         "Nombre": "Styx: Shards of Darkness",
         "Informacion": "\u00a1Styx regresa en una nueva aventura sigilosa! Contratado para una misi\u00f3n cr\u00edtica, explora y domina enormes entornos abiertos como Styx. Asesina o esquiva a enemigos (humanos, elfos y enanos), pero tambi\u00e9n a criaturas colosales y mucho m\u00e1s temibles. Experimenta con la nueva gama de habilidades y armas letales...",
         "Desde": "",
         "Hasta": "3670/08/01 09:00",
         "URL": "https://www.gog.com/en/game/styx_shards_of_darkness",
         "IMG": "https://images.gog-statics.com/11b4528bbb6454703c0a0ac95e711acce476f0b98cccd71d1fa744d9a4c671f3.jpg",
         "Distribuidora": "GOG",
         "Borde": "border-color: #00ff00;"
      },
      {
         "Nombre": "Rawcember Goodie Pack",
         "Informacion": "\u00a1Sum\u00e9rgete en un pa\u00eds de las maravillas visual con este paquete de regalos especial! Descubre fondos de pantalla exclusivos y arte conceptual de tus juegos favoritos de Raw Fury. Cinco jugadores afortunados tendr\u00e1n la oportunidad de recibir un paquete de regalos exclusivo, completo con una llave oculta dentro de uno de los activos. Esta llave...",
         "Desde": "",
         "Hasta": "3722/08/09 09:00",
         "URL": "https://www.gog.com/en/game/rawcember_goodie_pack",
         "IMG": "https://images.gog-statics.com/dadcb9f0417bc0581388a5b793464eac5835c5ec02289e1bedf1f21cfac6de3c.jpg",
         "Distribuidora": "GOG",
         "Borde": "border-color: #00ff00;"
      },
      {
         "Nombre": "Legend of Keepers: Career of a Dungeon Manager",
         "Informacion": "El pr\u00f3logo gratuito de Legend of Keepers: Career of a Dungeon Manager est\u00e1 disponible aqu\u00edBolet\u00edn informativo\u00a1En esta combinaci\u00f3n original de Dungeon Management y Roguelite, liderar\u00e1s tu carrera como Dungeon Manager!Caracter\u00edsticas \u00danete a Dungeons Company y asciende en la escala corporativa Aplasta al llamado `h\u00e9roe ...",
         "Desde": "",
         "Hasta": "3730/10/26 09:00",
         "URL": "https://www.gog.com/en/game/legend_of_keepers_career_of_a_dungeon_master",
         "IMG": "https://images.gog-statics.com/1dd0787114be3b04a5a04f1eeead76cdbfd2ee032799730c09160add8b903293.jpg",
         "Distribuidora": "GOG",
         "Borde": "border-color: #00ff00;"
      },
      {
         "Nombre": "Lost Ruins",
         "Informacion": "Lost Ruins es un juego de acci\u00f3n de supervivencia de desplazamiento lateral en 2D, en el que juegas como una joven que ha despertado en un lugar extra\u00f1o y extra\u00f1o sin sus recuerdos. Explora un mundo oscuro y peligroso, lucha contra horribles monstruos y derroca a jefes incre\u00edbles. Una joven se despierta en una mazmorra con poca luz y...",
         "Desde": "",
         "Hasta": "3744/07/04 09:00",
         "URL": "https://www.gog.com/en/game/lost_ruins",
         "IMG": "https://images.gog-statics.com/1cd6b7cec9cb3fed89e0b59c585ce6f6550af601d844bbf45d8d765aa2c7ae2a.jpg",
         "Distribuidora": "GOG",
         "Borde": "border-color: #00ff00;"
      },
      {
         "Nombre": "Caveblazers",
         "Informacion": "Caveblazers es un roguelike de plataformas centrado en la acci\u00f3n ambientado en un mundo de fantas\u00eda. Cada juego es \u00fanico, con niveles generados procedimentalmente para explorar y una enorme cantidad de elementos, armas y equipos para descubrir. El juego se desarrolla en una cueva recientemente descubierta, que se dice que tiene un `poder inimaginable`. Y...",
         "Desde": "",
         "Hasta": "3755/06/17 09:00",
         "URL": "https://www.gog.com/en/game/caveblazers",
         "IMG": "https://images.gog-statics.com/ee37e0bb054cc9a65bc3a8f62efd4336b08aac05e8bbaafebc2f39499a015333.jpg",
         "Distribuidora": "GOG",
         "Borde": "border-color: #00ff00;"
      },
      {
         "Nombre": "Lacuna \u2013 A Sci-Fi Noir Adventure",
         "Informacion": "La versi\u00f3n demo gratuita de Lacuna \u2013 A Sci-Fi Noir Adventure est\u00e1 disponible en GOG.COM. Puedes descargarlo aqu\u00edOtro cigarrillo cae al abismo. El sol est\u00e1 saliendo lentamente, brillando en el mar de edificios de abajo. Miro las estrellas por \u00faltima vez antes de que desaparezcan. No prueban...",
         "Desde": "",
         "Hasta": "3766/05/30 09:00",
         "URL": "https://www.gog.com/en/game/lacuna_a_scifi_noir_adventure",
         "IMG": "https://images.gog-statics.com/2d11a18cae6d1b130c9af66b5f83baab54f198be694e8d05976543c21d54d487.jpg",
         "Distribuidora": "GOG",
         "Borde": "border-color: #00ff00;"
      },
      {
         "Nombre": "South of the Circle",
         "Informacion": "South of the Circle es una experiencia narrativa emocional con una profunda historia cinematogr\u00e1fica de m\u00faltiples capas. La trama principal plantea preguntas sobre las consecuencias de las elecciones de vida, de seguir una carrera o el amor verdadero, maniobrando entre el ahora y el pasado. Juegas como Peter, un acad\u00e9mico de Cambridge que se estrella...",
         "Desde": "",
         "Hasta": "3774/08/16 09:00",
         "URL": "https://www.gog.com/en/game/south_of_the_circle",
         "IMG": "https://images.gog-statics.com/d3df28b2c184355b3dfd838225ab8eff89b4006d7ae90ac79e7160aa2e5c8b53.jpg",
         "Distribuidora": "GOG",
         "Borde": "border-color: #00ff00;"
      },
      {
         "Nombre": "Mordheim: City of the Damned",
         "Informacion": "Descubre los sombr\u00edos y oscuros universos de Warhammer donde solo hay guerra. Desde Warhammer 40,000 hasta Warhammer Fantasy y m\u00e1s: desc\u00fabrelo todo en la p\u00e1gina de la franquicia GOG Warhammer. La versi\u00f3n en GOG no incluye funciones en l\u00ednea. Como muestra de disculpa, agregamos el DLC `PAQUETE DE DLC HIRED SWORDS...",
         "Desde": "",
         "Hasta": "3848/07/19 09:00",
         "URL": "https://www.gog.com/en/game/mordheim_city_of_the_damned",
         "IMG": "https://images.gog-statics.com/883e6d09daaf73b4ed7fa623273204c4af18d8a408ae31b556920cd6c0459ed0.jpg",
         "Distribuidora": "GOG",
         "Borde": "border-color: #00ff00;"
      },
      {
         "Nombre": "The Beast Inside",
         "Informacion": "The Beast Inside es una versi\u00f3n \u00fanica y apasionante del thriller y el horror de supervivencia. El juego combina una intrigante aventura basada en una historia con una desconcertante experiencia de terror de supervivencia. Sum\u00e9rgete en una historia de secretos enterrados hace mucho tiempo, tragedias personales y locura. Juega como dos protagonistas que viven en diferentes c...",
         "Desde": "",
         "Hasta": "3864/12/22 08:00",
         "URL": "https://www.gog.com/en/game/the_beast_inside",
         "IMG": "https://images.gog-statics.com/9d7844741c2e98d156d9c0b8b2b7b90e21a9c743fd962b4c00ea53b023dc221b.jpg",
         "Distribuidora": "GOG",
         "Borde": "border-color: #00ff00;"
      },
      {
         "Nombre": "FlatOut",
         "Informacion": "Conductores arrojados por la pista, vallas destrozadas, coches destrozados, paredes de neum\u00e1ticos explotando, \u00a1y eso es s\u00f3lo la primera curva! Usa todos los trucos, atajos y saltos mientras luchas contra 7 rivales por el campeonato. FlatOut ofrece una emocionante combinaci\u00f3n de carreras de alto octanaje, actos de derby de demolici\u00f3n aplastantes...",
         "Desde": "",
         "Hasta": "3903/04/23 09:00",
         "URL": "https://www.gog.com/en/game/flatout",
         "IMG": "https://images.gog-statics.com/ff7b111c6ba2299cda2f49c3fffd68ea2d9d4e5a69964c6221a2b619278caee8.jpg",
         "Distribuidora": "GOG",
         "Borde": "border-color: #00ff00;"
      },
      {
         "Nombre": "Book of Demons",
         "Informacion": "Book of Demons es un h\u00edbrido de construcci\u00f3n de mazos Hack & Slash en el que T\u00da decides la duraci\u00f3n de las misiones. Empu\u00f1a cartas m\u00e1gicas en lugar de armas y mata a los ej\u00e9rcitos de la oscuridad en las mazmorras debajo de la Catedral Vieja. \u00a1Salva el aterrorizado Paperverse de las garras del mism\u00edsimo Archidemonio! Procedimiento...",
         "Desde": "",
         "Hasta": "4004/08/10 09:00",
         "URL": "https://www.gog.com/en/game/book_of_demons",
         "IMG": "https://images.gog-statics.com/d9d03ff8ba239fc9bb49308ada8c734aee945b35426496d255157ab3ce37f581.jpg",
         "Distribuidora": "GOG",
         "Borde": "border-color: #00ff00;"
      },
      {
         "Nombre": "Hammerting",
         "Informacion": "Hammerting es un simulador de colonia minera enana vertical con elementos de juego de rol. Dirige un clan de coloridos enanos, establece una operaci\u00f3n minera \u00e9pica, crea espadas legendarias y profundiza en busca de mayor gloria, riquezas... y peligro. Con un conflicto en la superficie, los enanos se comprometen a profundizar...",
         "Desde": "",
         "Hasta": "4023/08/29 17:00",
         "URL": "https://www.gog.com/en/game/hammerting",
         "IMG": "https://images.gog-statics.com/4f3b88d25e923df172eda894002a38369dbd358a6eacc9effe8f719d8f83bd8c.jpg",
         "Distribuidora": "GOG",
         "Borde": "border-color: #00ff00;"
      }
   ]
}