{
   "date_update": "08 Dec 2022 17:05 UTC",
   "values": [
      {
         "Nombre": "Vovsoft SEO Checker License Key for Free 2022",
         "Informacion": "Vovsoft SEO Checker es un analizador de sitios web y una herramienta de auditor\u00eda SEO que le permite probar la optimizaci\u00f3n del motor de b\u00fasqueda de su sitio web. Con \u00e9l, puede mejorar la clasificaci\u00f3n y el estado del SEO de un sitio web. Adem\u00e1s, SEO Checker le proporciona listas completas de mapas de sitios, enlaces, backlinks internos, encabezados H1 y H2.",
         "Desde": "",
         "Hasta": "2022/12/08 15:00",
         "URL": "https://giveaway.tickcoupon.com/vovsoft-seo-checker-free-key/",
         "IMG": "https://y8p7i4q3.stackpathcdn.com/wp-content/uploads/2022/04/vovsoft-seo-checker-giveaway-free-license-key.png",
         "Distribuidora": "Tickcoupon Giveaway",
         "Borde": "border-image: linear-gradient(to right, red 75%, yellow 75%) 1;"
      },
      {
         "Nombre": "Evil Dead: The Game",
         "Informacion": "\u00a1M\u00e9tete en la piel de Ash Williams o de sus amigos de la emblem\u00e1tica franquicia Evil Dead y trabajad juntos en un juego con lo mejor del cooperativo y de la acci\u00f3n multijugador JcJ!",
         "Desde": "2022/12/01",
         "Hasta": "2022/12/08 17:00",
         "URL": "https://store.epicgames.com/p/evil-dead-the-game",
         "IMG": "https://cdn1.epicgames.com/offer/95e09a8c24c44684bca1a6f25aea920c/EGS_EvilDeadTheGame_SaberInteractiveInc_S1_2560x1440-fde136bc32f2b93006b9df0bc421fec0_2560x1440-fde136bc32f2b93006b9df0bc421fec0",
         "Distribuidora": "Epic Game",
         "Borde": "border-image: linear-gradient(to right, red 67%, yellow 67%) 1;"
      },
      {
         "Nombre": "Fort Triumph",
         "Informacion": "Un juego de estrategia que combina el combate por turnos de la saga XCOM con la exploraci\u00f3n de mundos de HOMM. Construye pueblos, encuentra artefactos, mejora a tus h\u00e9roes y modifica el entorno t\u00e1ctico usando el sistema de f\u00edsica del juego.",
         "Desde": "2022/12/01",
         "Hasta": "2022/12/08 17:00",
         "URL": "https://store.epicgames.com/p/fort-triumph",
         "IMG": "https://cdn1.epicgames.com/salesEvent/salesEvent/EGS_FortTriumph_CookieByteEntertainment_S1_2560x1440-a0b5e1aeb62c1ee5550d97886ab475a3",
         "Distribuidora": "Epic Game",
         "Borde": "border-image: linear-gradient(to right, red 67%, yellow 67%) 1;"
      },
      {
         "Nombre": "RPG in a Box",
         "Informacion": "\u00a1Haz realidad tus historias e ideas! RPG in a Box es una herramienta de creaci\u00f3n accesible para desarrollar juegos y otras experiencias interactivas de forma f\u00e1cil y sencilla.",
         "Desde": "2022/12/01",
         "Hasta": "2022/12/08 17:00",
         "URL": "https://store.epicgames.com/p/rpg-in-a-box",
         "IMG": "https://cdn1.epicgames.com/offer/0e76e53e157d416ab598342ed3a9dd5a/EGS_RPGinaBox_JustinArnold_S1_2560x1440-fef2661fad4d06cee988aa2a2c3383c7",
         "Distribuidora": "Epic Game",
         "Borde": "border-image: linear-gradient(to right, red 67%, yellow 67%) 1;"
      },
      {
         "Nombre": "Batch Video CompreXor",
         "Informacion": "Batch Video CompreXor es la herramienta perfecta para reducir sus archivos de video hasta en un 95% del archivo de video original. Batch Video CompreXor reduce los archivos de video al reducir la calidad del video y la calidad del audio en un porcentaje que usted defina, para que pueda convertir sus videos en el tama\u00f1o que desee. Batch Video CompreXor funciona para MP4, MOV, MPG, WMV, QT, AVI, MP3, OGG, 3GP, FLAC, FLV y m\u00e1s.",
         "Desde": "",
         "Hasta": "2022/12/09 07:00",
         "URL": "https://sharewareonsale.com/s/free-batch-video-comprexor-100-discount",
         "IMG": "https://cdn.sharewareonsale.com/wp-content/uploads/2021/06/Batch_Video_CompreXor.png?1357",
         "Distribuidora": "SharewareOnSale",
         "Borde": "border-image: linear-gradient(to right, red 9%, yellow 9%) 1;"
      },
      {
         "Nombre": "KCleaner PRO",
         "Informacion": "\u00a1El limpiador de disco duro m\u00e1s eficiente!",
         "Desde": "",
         "Hasta": "2022/12/09 07:00",
         "URL": "https://sharewareonsale.com/s/kcleaner-giveaway-coupon-sale",
         "IMG": "https://cdn.sharewareonsale.com/wp-content/uploads/2016/05/KCleaner_screen-200x148.png?1357",
         "Distribuidora": "SharewareOnSale",
         "Borde": "border-image: linear-gradient(to right, red 9%, yellow 9%) 1;"
      },
      {
         "Nombre": "Ara and the Empty Universe by Basim Aziz",
         "Informacion": "\u00bfQu\u00e9 hace uno cuando todos desaparecen? \u00bfC\u00f3mo lo maneja?",
         "Desde": "",
         "Hasta": "2022/12/09 07:00",
         "URL": "https://basim-aziz.itch.io/ara-and-the-empty-universe",
         "IMG": "https://img.itch.zone/aW1hZ2UvMTAxMjk1OC81ODMyMjA1LnBuZw==/347x500/Csgn88.png",
         "Distribuidora": "Itch io",
         "Borde": "border-image: linear-gradient(to right, red 9%, yellow 9%) 1;"
      },
      {
         "Nombre": "Get Genie Timeline Home Free",
         "Informacion": "\u00a1Configuraci\u00f3n \u00fanica, protecci\u00f3n de por vida!",
         "Desde": "",
         "Hasta": "2022/12/09 09:00",
         "URL": "https://www.bitsdujour.com/software/get-genie-timeline-home-free/in=today-100-percent",
         "IMG": "https://bitsdujourblob.blob.core.windows.net/software/screenshot/get-genie-timeline-home-free-80jfq.png",
         "Distribuidora": "BitsDuJour",
         "Borde": "border-image: linear-gradient(to right, red 0%, yellow 0%) 1;"
      },
      {
         "Nombre": "KCleaner PRO License Key for Free Full Version",
         "Informacion": "KCleaner Pro es un software de limpieza de archivos poderoso y seguro que est\u00e1 dise\u00f1ado para ser el limpiador de disco duro m\u00e1s eficiente. Este software rastrea cada byte in\u00fatil para brindarle todos los recursos que pueda necesitar para sus documentos, m\u00fasica, im\u00e1genes, pel\u00edculas, etc. Por lo tanto, despu\u00e9s de mucho tiempo de usar la computadora, debe actualizarla para recuperar la capacidad de almacenamiento del disco duro. y aumentar el rendimiento de la PC.",
         "Desde": "",
         "Hasta": "2022/12/09 14:00",
         "URL": "https://giveaway.tickcoupon.com/kcleaner-pro-free-license-key/",
         "IMG": "https://y8p7i4q3.stackpathcdn.com/wp-content/uploads/2021/01/KCleaner-PRO-Giveaway.png",
         "Distribuidora": "Tickcoupon Giveaway",
         "Borde": "border-color: #00ff00;"
      },
      {
         "Nombre": "Allavsoft Video Downloader Registration Code Free",
         "Informacion": "Allavsoft es un software de descarga para Windows, admite la descarga de pel\u00edculas, videos musicales, listas de reproducci\u00f3n, videos deportivos, conferencias y m\u00e1s desde sitios web gratuitos para compartir videos como Facebook, Dailymotion, eHow y m\u00e1s de 100 sitios para compartir videos. Tambi\u00e9n ayuda a extraer y descargar audio de videos musicales o pel\u00edculas en l\u00ednea.",
         "Desde": "",
         "Hasta": "2022/12/09 15:00",
         "URL": "https://giveaway.tickcoupon.com/allavsoft-free-license-key-lifetime/",
         "IMG": "https://y8p7i4q3.stackpathcdn.com/wp-content/uploads/2021/12/allavsoft-for-windows-giveaway-screenshot.png",
         "Distribuidora": "Tickcoupon Giveaway",
         "Borde": "border-color: #00ff00;"
      },
      {
         "Nombre": "PDF Eraser Pro Giveaway License Key for Lifetime 2022",
         "Informacion": "PDFZilla PDF Eraser Pro lo ayuda a eliminar/borrar texto e im\u00e1genes de documentos PDF y guardarlos en un nuevo archivo PDF. Con \u00e9l, puede eliminar texto e im\u00e1genes de PDF incluso si el color de fondo del PDF NO es blanco. Adem\u00e1s, tambi\u00e9n lo ayudar\u00e1 a agregar su propio texto e im\u00e1genes en el PDF.",
         "Desde": "",
         "Hasta": "2022/12/10 00:00",
         "URL": "https://giveaway.tickcoupon.com/pdfzilla-pdf-eraser-pro-free-key/",
         "IMG": "https://y8p7i4q3.stackpathcdn.com/wp-content/uploads/2020/06/pdf-eraser-pro-screenshot-1.png",
         "Distribuidora": "Tickcoupon Giveaway",
         "Borde": "border-color: #00ff00;"
      },
      {
         "Nombre": "Tenorshare 4uKey Password Manager 1-Month License Key Free",
         "Informacion": "Olvid\u00f3 las contrase\u00f1as de inicio de sesi\u00f3n del sitio web guardadas en Safari; por lo tanto, est\u00e1 buscando el software de b\u00fasqueda de contrase\u00f1as de iOS que puede ayudarlo a recuperar sitios web almacenados y contrase\u00f1as de inicio de sesi\u00f3n de aplicaciones; probemos Tenorshare 4uKey Password Manager. Esta herramienta ofrece una excelente funci\u00f3n para encontrar contrase\u00f1as Wi-Fi guardadas en iPhone/iPad desde PC/Mac, as\u00ed como recuperar sitios web almacenados y contrase\u00f1as de inicio de sesi\u00f3n de aplicaciones.",
         "Desde": "",
         "Hasta": "2022/12/10 00:00",
         "URL": "https://giveaway.tickcoupon.com/tenorshare-4ukey-password-manager-free-key/",
         "IMG": "https://y8p7i4q3.stackpathcdn.com/wp-content/uploads/2022/11/tenorshare-4ukey-password-manager-license-key-free.png",
         "Distribuidora": "Tickcoupon Giveaway",
         "Borde": "border-color: #00ff00;"
      },
      {
         "Nombre": "WinX HD Video Converter Deluxe License Key Free 2022",
         "Informacion": "WinX HD Video Converter Deluxe, un software de video todo en uno como convertidor de video Ultra HD, creador de presentaciones de diapositivas y editor de video, le brinda el m\u00e1ximo control sobre los archivos de video con resoluci\u00f3n SD, HD y 4K. Con m\u00e1s de 320 c\u00f3decs de video y 50 c\u00f3decs de audio, posee la poderosa capacidad de satisfacer las necesidades de conversi\u00f3n de video r\u00e1pidas y de alta calidad sin la ayuda de ninguna herramienta de terceros.",
         "Desde": "",
         "Hasta": "2022/12/10 00:00",
         "URL": "https://giveaway.tickcoupon.com/winx-hd-video-converter-deluxe-free-key/",
         "IMG": "https://y8p7i4q3.stackpathcdn.com/wp-content/uploads/2022/08/winx-hd-video-converter-deluxe-license-key-free.png",
         "Distribuidora": "Tickcoupon Giveaway",
         "Borde": "border-color: #00ff00;"
      },
      {
         "Nombre": "Useless Demon Lord by Firecat1311",
         "Informacion": "Lucille es una mujer soltera desempleada que vive sola en su apartamento, con sentimientos de ansiedad e insuficiencia... pero luego, sin previo aviso y debido a una extra\u00f1a confusi\u00f3n m\u00e1gica, \u00a1es convocada para ser el nuevo Demon Lord en otro mundo!",
         "Desde": "",
         "Hasta": "2022/12/10 20:00",
         "URL": "https://firecat1311.itch.io/useless-demon-lord",
         "IMG": "https://img.itch.zone/aW1hZ2UvMTQyMzE3My84NTQ3NDIzLnBuZw==/347x500/orGmaU.png",
         "Distribuidora": "Itch io",
         "Borde": "border-color: #00ff00;"
      },
      {
         "Nombre": "Ball Down Hill by KasperV",
         "Informacion": "Meta:",
         "Desde": "",
         "Hasta": "2022/12/11 00:00",
         "URL": "https://kasperv.itch.io/ball-down-hill",
         "IMG": "https://img.itch.zone/aW1hZ2UvMTU4MTA5Ny85MjM2ODk2LnBuZw==/347x500/wjOoCN.png",
         "Distribuidora": "Itch io",
         "Borde": "border-color: #00ff00;"
      },
      {
         "Nombre": "Sky Lab Defender by KasperV",
         "Informacion": "Defensor del laboratorio del cielo",
         "Desde": "",
         "Hasta": "2022/12/11 00:00",
         "URL": "https://kasperv.itch.io/skylabdefender",
         "IMG": "https://img.itch.zone/aW1hZ2UvMzIyMDczLzE3MTkzOTEucG5n/347x500/pwKYLh.png",
         "Distribuidora": "Itch io",
         "Borde": "border-color: #00ff00;"
      },
      {
         "Nombre": "The Simple Life by KasperV",
         "Informacion": "La vida simple",
         "Desde": "",
         "Hasta": "2022/12/11 00:00",
         "URL": "https://kasperv.itch.io/the-simple-life",
         "IMG": "https://img.itch.zone/aW1hZ2UvMTU1MTY4Ny85MDU0MDU2LnBuZw==/347x500/ThLrWi.png",
         "Distribuidora": "Itch io",
         "Borde": "border-color: #00ff00;"
      },
      {
         "Nombre": "Vovsoft Blur Multiple Images License Key for Free",
         "Informacion": "Disponible para Windows, Vovsoft Blur Multiple Images se jacta de ser el poderoso de la industria para agregar un efecto de desenfoque a muchas im\u00e1genes. Es el software de desenfoque de im\u00e1genes actualmente disponible y, como mencionamos, puede ayudar a agregar un efecto de desenfoque a una gran cantidad de archivos de imagen en una operaci\u00f3n r\u00e1pida.",
         "Desde": "",
         "Hasta": "2022/12/11 00:00",
         "URL": "https://giveaway.tickcoupon.com/vovsoft-blur-multiple-images-free-license-code/",
         "IMG": "https://y8p7i4q3.stackpathcdn.com/wp-content/uploads/2022/12/vovsoft-blur-multiple-images-free-license-giveaway.png",
         "Distribuidora": "Tickcoupon Giveaway",
         "Borde": "border-color: #00ff00;"
      },
      {
         "Nombre": "Pixel Galaxy by H967",
         "Informacion": "Una civilizaci\u00f3n pr\u00f3spera (que consiste solo en p\u00edxeles verdes) ha encontrado la v\u00eda l\u00e1ctea. \u00a1Eres el \u00fanico capaz de derrotar a estos p\u00edxeles y recuperar nuestra galaxia antes de que sea destruida!",
         "Desde": "",
         "Hasta": "2022/12/11 05:00",
         "URL": "https://h967.itch.io/pixel-galaxy",
         "IMG": "https://img.itch.zone/aW1hZ2UvMTQ2ODcyNy85MDE1NDU3LnBuZw==/347x500/MpUbCr.png",
         "Distribuidora": "Itch io",
         "Borde": "border-color: #00ff00;"
      },
      {
         "Nombre": "Keep It In The Light by King OB Games",
         "Informacion": "Keep It In The Light es un juego de terror simple pero espeluznante. Tienes un objetivo, salir de esta ciudad. Empiezas en una puerta con 3 cerraduras. Encuentra las 3 llaves ubicadas al azar alrededor del mapa mientras algo te persigue. Recuerda mantenerlo en la luz o te atrapar\u00e1... Mantenlo en la luz demasiado tiempo... puedes enojarlo.",
         "Desde": "",
         "Hasta": "2022/12/11 06:00",
         "URL": "https://king0fballoons.itch.io/keep-it-in-the-light",
         "IMG": "https://img.itch.zone/aW1hZ2UvMTUzMDE4Ni84OTg1MzQ2LmpwZw==/347x500/eQl7rP.jpg",
         "Distribuidora": "Itch io",
         "Borde": "border-color: #00ff00;"
      },
      {
         "Nombre": "Ant Download Manager PRO",
         "Informacion": "Ant Download Manager (AntDM) es una herramienta que le permite aumentar repetidamente la velocidad de descarga de archivos debido a m\u00faltiples flujos de descarga, reanudar, programar descargas, capturar y descargar flujos de audio y video.",
         "Desde": "",
         "Hasta": "2022/12/11 07:00",
         "URL": "https://sharewareonsale.com/s/ant-download-manager-giveaway-coupon-sale",
         "IMG": "https://cdn.sharewareonsale.com/wp-content/uploads/2016/11/antbox-150x200.png?1357",
         "Distribuidora": "SharewareOnSale",
         "Borde": "border-color: #00ff00;"
      },
      {
         "Nombre": "Audials Radio 2023",
         "Informacion": "La grabadora de radio por Internet con 100 000 radios evoca legalmente una gran cantidad de archivos MP3 gratuitos en el disco duro",
         "Desde": "",
         "Hasta": "2022/12/11 07:00",
         "URL": "https://sharewareonsale.com/s/free-audials-radio-2023-100-discount",
         "IMG": "https://cdn.sharewareonsale.com/wp-content/uploads/2022/11/ara_seBoxShot@medium.png?1357",
         "Distribuidora": "SharewareOnSale",
         "Borde": "border-color: #00ff00;"
      },
      {
         "Nombre": "Ant Download Manager Pro Giveaway Full Version Download",
         "Informacion": "Ant Download Manager es un administrador de descargas de Internet para cualquier archivo que lo ayude a descargar y administrar videos. Con este software, puede descargar los archivos de audio y extraer pistas de audio de archivos de video, luego convertirlos al popular formato MP3 y agregarles la informaci\u00f3n b\u00e1sica que los acompa\u00f1a.",
         "Desde": "",
         "Hasta": "2022/12/11 15:00",
         "URL": "https://giveaway.tickcoupon.com/ant-download-manager-pro-free-key/",
         "IMG": "https://y8p7i4q3.stackpathcdn.com/wp-content/uploads/2021/05/Ant-Download-Manager-Pro-Giveaway.png",
         "Distribuidora": "Tickcoupon Giveaway",
         "Borde": "border-color: #00ff00;"
      },
      {
         "Nombre": "CLASSIC GAME by HORSES' MUSIC-DOGS",
         "Informacion": "CLASSIC GAME es un juego de aventuras ASCII iniciado en 2011 y lanzado en 2017.",
         "Desde": "",
         "Hasta": "2022/12/11 19:00",
         "URL": "https://iamqqqqqqq.itch.io/classicgame",
         "IMG": "https://img.itch.zone/aW1hZ2UvMTQ4NTAxLzMzMTU3OTkucG5n/347x500/i3A4Ds.png",
         "Distribuidora": "Itch io",
         "Borde": "border-color: #00ff00;"
      },
      {
         "Nombre": "HOME GAME 2 by HORSES' MUSIC-DOGS",
         "Informacion": "HOME GAME 2 trata sobre el ERMITA\u00d1O que vive solo.",
         "Desde": "",
         "Hasta": "2022/12/11 19:00",
         "URL": "https://iamqqqqqqq.itch.io/homegame2",
         "IMG": "https://img.itch.zone/aW1hZ2UvNTU3ODczLzI5MjUxNTQucG5n/347x500/br1YI9.png",
         "Distribuidora": "Itch io",
         "Borde": "border-color: #00ff00;"
      },
      {
         "Nombre": "HOME GAME by HORSES' MUSIC-DOGS",
         "Informacion": "JUEGO EN CASA se trata del ERMITA\u00d1O en casa.",
         "Desde": "",
         "Hasta": "2022/12/11 19:00",
         "URL": "https://iamqqqqqqq.itch.io/homegame",
         "IMG": "https://img.itch.zone/aW1hZ2UvMjc3MDIyLzEzNDQ2NzgucG5n/347x500/3WPFFe.png",
         "Distribuidora": "Itch io",
         "Borde": "border-color: #00ff00;"
      },
      {
         "Nombre": "WinX MediaTrans License Key Full Version Download 2022",
         "Informacion": "WinX MediaTrans le permite transferir f\u00e1cilmente datos desde dispositivos iPhone, iPad a computadoras y viceversa. Con esta transferencia, administrar\u00e1 f\u00e1cilmente los archivos en su dispositivo y tambi\u00e9n puede liberar espacio para que su iPhone guarde nuevos datos importantes.",
         "Desde": "",
         "Hasta": "2022/12/12 00:00",
         "URL": "https://giveaway.tickcoupon.com/giveaway-key-for-winx-mediatrans/",
         "IMG": "https://y8p7i4q3.stackpathcdn.com/wp-content/uploads/2019/10/WinX-MediaTrans-Screenshot.png",
         "Distribuidora": "Tickcoupon Giveaway",
         "Borde": "border-color: #00ff00;"
      },
      {
         "Nombre": "500 Realistic Professional Photo Overlays",
         "Informacion": "M\u00e1s de 500 superposiciones de fotos realistas es la colecci\u00f3n m\u00e1s grande y diversa de superposiciones en 2022 para verdaderos profesionales. Ahorre un tiempo precioso y domine sus habilidades con m\u00e1s de 500 superposiciones de fotos realistas. Agregue vibraciones suaves y frescas a sus dise\u00f1os.",
         "Desde": "",
         "Hasta": "2022/12/12 07:00",
         "URL": "https://sharewareonsale.com/s/free-500-realistic-professional-photo-overlays-100-discount",
         "IMG": "https://cdn.sharewareonsale.com/wp-content/uploads/2022/11/500-Professional-Photo-Overlays-Bundle-Image-scaled.jpg?1357",
         "Distribuidora": "SharewareOnSale",
         "Borde": "border-color: #00ff00;"
      },
      {
         "Nombre": "Sticky Password Premium",
         "Informacion": "Sticky Password\u00a0es el administrador de contrase\u00f1as galardonado con funciones como inicio de sesi\u00f3n autom\u00e1tico, llenado autom\u00e1tico de formularios, generador de contrase\u00f1as y uso compartido seguro de contrase\u00f1as, y protege sus datos con el cifrado AES-256 est\u00e1ndar de la industria junto con su contrase\u00f1a maestra o autenticaci\u00f3n biom\u00e9trica (por ejemplo, huella digital ).",
         "Desde": "",
         "Hasta": "2022/12/12 07:00",
         "URL": "https://sharewareonsale.com/s/sticky-password-sale",
         "IMG": "https://cdn.sharewareonsale.com/wp-content/uploads/2016/09/Sticky-Password-Premium-2017-200x147.png?1357",
         "Distribuidora": "SharewareOnSale",
         "Borde": "border-color: #00ff00;"
      },
      {
         "Nombre": "The backrooms by Notmessyouself",
         "Informacion": "Versi\u00f3n alfa 1.1",
         "Desde": "",
         "Hasta": "2022/12/13 01:00",
         "URL": "https://notmessyouself.itch.io/the-backrooms",
         "IMG": "https://img.itch.zone/aW1nLzk2OTQ3MTUuanBn/347x500/a0MQdE.jpg",
         "Distribuidora": "Itch io",
         "Borde": "border-color: #00ff00;"
      },
      {
         "Nombre": "5 in 1 Retro Games by Notmessyouself",
         "Informacion": "Este proyecto est\u00e1 patrocinado por\u00a0Windows365",
         "Desde": "",
         "Hasta": "2022/12/13 01:00",
         "URL": "https://notmessyouself.itch.io/5-in-1-retro-games",
         "IMG": "https://img.itch.zone/aW1hZ2UvODg1MDQyLzQ5ODgyOTAucG5n/347x500/u5rJql.png",
         "Distribuidora": "Itch io",
         "Borde": "border-color: #00ff00;"
      },
      {
         "Nombre": "1943 by Notmessyouself",
         "Informacion": "Este proyecto est\u00e1 patrocinado por\u00a0Windows365.dk",
         "Desde": "",
         "Hasta": "2022/12/13 01:00",
         "URL": "https://notmessyouself.itch.io/1943",
         "IMG": "https://img.itch.zone/aW1nLzUwNjA1MTAucG5n/347x500/klTaxH.png",
         "Distribuidora": "Itch io",
         "Borde": "border-color: #00ff00;"
      },
      {
         "Nombre": "Baldi's Basics Songkran In Education And Learning X by SJ Logo transparent",
         "Informacion": "el juego original baldi basics en educaci\u00f3n y aprendizaje 1.3.2 el a\u00f1o pasado ahora actualizaci\u00f3n del juego a baldi basics songkran en educaci\u00f3n y aprendizaje 1.4.5 no descompilado mod it juego real que actualiza publicar juego completado! gracias a mystman12 por no enviar ese mod descompilado para enviarlo ya para actualizar el acceso al juego, no informar mi cuenta y el juego, \u00a1y ahora enviarlo a usted!",
         "Desde": "",
         "Hasta": "2022/12/14 20:00",
         "URL": "https://sj-logo-transparent.itch.io/baldis-basics-songkran-in-education-and-learning-x",
         "IMG": "https://img.itch.zone/aW1hZ2UvMTUwODkzNy84Nzk1MDA0LmpwZw==/347x500/yIuU8%2B.jpg",
         "Distribuidora": "Itch io",
         "Borde": "border-color: #00ff00;"
      },
      {
         "Nombre": "Leawo DVD Copy License Key Free Download Full",
         "Informacion": "El software Leawo DVD Copy es el software profesional para copiar y realizar copias de seguridad a alta velocidad. Los usuarios pueden copiar datos de DVD de DVD a DVD, de disco a carpeta y de disco a imagen ISO. Adem\u00e1s, es posible copiar pel\u00edculas HD a un DVD muy simple. Leawo DVD Copy est\u00e1 respaldado con tecnolog\u00eda avanzada de copia y copia de DVD, y admite la copia de DVD con una calidad constante. Tiene tres modos de copia diferentes, que incluyen Pel\u00edcula completa, Pel\u00edcula principal, Modo personalizado.",
         "Desde": "",
         "Hasta": "2022/12/15 00:00",
         "URL": "https://giveaway.tickcoupon.com/leawo-dvd-copy-giveaway/",
         "IMG": "https://y8p7i4q3.stackpathcdn.com/wp-content/uploads/2020/08/leawo-dvd-copy-screenhsot-giveaway.png",
         "Distribuidora": "Tickcoupon Giveaway",
         "Borde": "border-color: #00ff00;"
      },
      {
         "Nombre": "StreamFab YouTube Downloader Pro",
         "Informacion": "StreamFab YouTube Downloader Pro permite a los usuarios descargar videos de YouTube a la PC en formatos MP4, MKV y MP3",
         "Desde": "",
         "Hasta": "2022/12/15 07:00",
         "URL": "https://sharewareonsale.com/s/free-streamfab-youtube-downloader-pro-100-discount",
         "IMG": "https://cdn.sharewareonsale.com/wp-content/uploads/2021/11/62001-200x200.png?1357",
         "Distribuidora": "SharewareOnSale",
         "Borde": "border-color: #00ff00;"
      },
      {
         "Nombre": "Saints Row IV: Re-Elected",
         "Informacion": "\u00a1Ahora t\u00fa eres el presidente! Los Saints han pasado del \u00e1tico a la Casa Blanca, pero la Tierra ha sido invadida y te toca a ti salvarla con un arsenal de superpoderes y extra\u00f1as armas en el juego de mundo abierto m\u00e1s alocado de la historia.",
         "Desde": "2022/12/08",
         "Hasta": "2022/12/15 17:00",
         "URL": "https://store.epicgames.com/p/saints-row-iv-re-elected",
         "IMG": "https://cdn1.epicgames.com/offer/151e56468b5049628653dedab7c88007/EGS_SaintsRowIVReElected_DeepSilverVolition_S1_2560x1440-77ce5721cb572e6ce6f37537edcb4fb1",
         "Distribuidora": "Epic Game",
         "Borde": "border-color: #00ff00;"
      },
      {
         "Nombre": "Wildcat Gun Machine",
         "Informacion": "Wildcat Gun Machine es un juego de exploraci\u00f3n de mazmorras e infierno de balas en el que te enfrentar\u00e1s a hordas de repugnantes bestias con una amplia variedad de armas, robots gigantes y gatitos la mar de monos.",
         "Desde": "2022/12/08",
         "Hasta": "2022/12/15 17:00",
         "URL": "https://store.epicgames.com/p/wildcat-gun-machine-c66c4e",
         "IMG": "https://cdn1.epicgames.com/spt-assets/d92266115f8d4d5680562d993435daa5/wildcat-gun-machine-offer-rle9l.jpg",
         "Distribuidora": "Epic Game",
         "Borde": "border-color: #00ff00;"
      },
      {
         "Nombre": "BadGuy's Escape to Comodo - ZAM by BuilderManX",
         "Informacion": "Es un lugar de aventuras. BadGuy's Escape to Comodo es un juego en el que exploras un enorme mundo abierto y asumes el papel de un hombre que huye. Puede explorar una gran variedad de terrenos, incluidos desiertos, monta\u00f1as, ciudades y pueblos generados por procedimientos. Para ayudarte en tu b\u00fasqueda, Escape to Comodo incluye una variedad de armas, accesorios para la cabeza y ropa para ayudar a mejorar la experiencia de juego de rol. Los jugadores tambi\u00e9n pueden construir su propia historia, elegir entre cientos de opciones y personalizar su personaje con diferentes atuendos, equipos y sombreros. Cuando te aventuras en una misi\u00f3n, puedes elegir conducir, explorar o caminar a trav\u00e9s de una tierra casi infinita.",
         "Desde": "",
         "Hasta": "2022/12/16 07:00",
         "URL": "https://buildermanx.itch.io/badguys-escape-to-comodo-zam",
         "IMG": "https://img.itch.zone/aW1hZ2UvMTM5NjE1OS84MTQ2ODM4LnBuZw==/347x500/wxXDQW.png",
         "Distribuidora": "Itch io",
         "Borde": "border-color: #00ff00;"
      },
      {
         "Nombre": "BadGuy's Melee by BuilderManX",
         "Informacion": "Es un lugar de aventuras BadGuy's Escape to Comodo es un juego en el que exploras una isla metropolitana de misterio, asumes el papel de un villano con superpoderes que busca el camino de regreso a Comodo. Puede explorar una gran variedad de paisajes urbanos, incluidos oc\u00e9anos, monta\u00f1as, ciudades y pueblos generados por procedimientos. Para ayudarte en tu b\u00fasqueda, Escape to Comodo incluye una variedad de superpoderes y autos para ayudar a mejorar la experiencia de juego de roles. Los jugadores tambi\u00e9n pueden construir su propia historia, elegir entre cientos de opciones y personalizar su personaje con diferentes estilos de movimiento. Cuando te aventuras en una misi\u00f3n, puedes elegir conducir, explorar o caminar a trav\u00e9s de una tierra casi infinita.",
         "Desde": "",
         "Hasta": "2022/12/16 07:00",
         "URL": "https://buildermanx.itch.io/badguys-escape-to-comodo-melee",
         "IMG": "https://img.itch.zone/aW1hZ2UvMTM5NjI1Ny84MTQ2NTk4LnBuZw==/347x500/%2BHrJA2.png",
         "Distribuidora": "Itch io",
         "Borde": "border-color: #00ff00;"
      },
      {
         "Nombre": "Intergalactic Space Patrol V1.6 *UPDATED* by BuilderManX",
         "Informacion": "Esta es la patrulla de la nave estelar ISP Venture nuestra misi\u00f3n de 5 minutos es ser una entretenida parodia de la ciencia ficci\u00f3n y el control corporativo moderno de TODO. Ven y disfruta de este juego de aventuras h\u00edbridas de simulaci\u00f3n espacial mientras criticamos las partes m\u00e1s rid\u00edculas del g\u00e9nero que amamos.",
         "Desde": "",
         "Hasta": "2022/12/16 07:00",
         "URL": "https://buildermanx.itch.io/intergalactic-space-patrol",
         "IMG": "https://img.itch.zone/aW1hZ2UvMTU1Njc5Ny85MDg0MTc3LnBuZw==/347x500/SC9uFe.png",
         "Distribuidora": "Itch io",
         "Borde": "border-color: #00ff00;"
      },
      {
         "Nombre": "Lands of Zam: Prelude by BuilderManX",
         "Informacion": "Navega por el desierto procesal retro de los 90 de ZAM con este controlador infinito gratuito. Vista previa de lo que vendr\u00e1 con los juegos futuros en serie",
         "Desde": "",
         "Hasta": "2022/12/16 07:00",
         "URL": "https://buildermanx.itch.io/lands-of-zam-prelude",
         "IMG": "https://img.itch.zone/aW1hZ2UvMTQxMDIzMC84MjE1Njk5LnBuZw==/347x500/2MOe4n.png",
         "Distribuidora": "Itch io",
         "Borde": "border-color: #00ff00;"
      },
      {
         "Nombre": "Spook Smashers! by BuilderManX",
         "Informacion": "\u00a1Caza fantasmas en una parodia de caza de fantasmas ecto procesal!",
         "Desde": "",
         "Hasta": "2022/12/16 07:00",
         "URL": "https://buildermanx.itch.io/spooksmashers",
         "IMG": "https://img.itch.zone/aW1hZ2UvMTM5NjYyMi85Nzc2OTc1LnBuZw==/347x500/Y1UiIE.png",
         "Distribuidora": "Itch io",
         "Borde": "border-color: #00ff00;"
      },
      {
         "Nombre": "The Door! 2 by Nitish Thombre",
         "Informacion": "Este juego hecho para Speed \u200b\u200brun -_-",
         "Desde": "",
         "Hasta": "2022/12/16 10:00",
         "URL": "https://nitish-thombre.itch.io/the-door-2",
         "IMG": "https://img.itch.zone/aW1hZ2UvMTM2Njg0NS83OTU2Nzc0LnBuZw==/347x500/E42hh0.png",
         "Distribuidora": "Itch io",
         "Borde": "border-color: #00ff00;"
      },
      {
         "Nombre": "The Door! 3 by Nitish Thombre",
         "Informacion": "\u00a1Este es un juego m\u00e1s dif\u00edcil que The Door! 2 \u00a1porque es La Puerta! 3",
         "Desde": "",
         "Hasta": "2022/12/16 10:00",
         "URL": "https://nitish-thombre.itch.io/the-door-3",
         "IMG": "https://img.itch.zone/aW1hZ2UvMTQ1NTUxMC84NTA0MzUxLnBuZw==/347x500/BXLApA.png",
         "Distribuidora": "Itch io",
         "Borde": "border-color: #00ff00;"
      },
      {
         "Nombre": "The Door! by Nitish Thombre",
         "Informacion": "\u00a1Este juego est\u00e1 hecho para ser el juego m\u00e1s dif\u00edcil del mundo!",
         "Desde": "",
         "Hasta": "2022/12/16 10:00",
         "URL": "https://nitish-thombre.itch.io/the-door",
         "IMG": "https://img.itch.zone/aW1hZ2UvMTM0NDU2NS83ODI1MzY2LnBuZw==/347x500/YjQvSI.png",
         "Distribuidora": "Itch io",
         "Borde": "border-color: #00ff00;"
      },
      {
         "Nombre": "Escape the Void by asbux",
         "Informacion": "Escape the void es un p\u00edcaro de acci\u00f3n en 2D en el que luchas contra oleadas de enemigos y jefes y usas sus almas verdes para abrir cofres y obtener elementos poderosos que te hacen fuerte y tal vez solo tal vez escapar del vac\u00edo.",
         "Desde": "",
         "Hasta": "2022/12/19 22:00",
         "URL": "https://asbux.itch.io/escape-the-void",
         "IMG": "https://img.itch.zone/aW1hZ2UvMTY1NDc3Mi8xMDEzODQzNi5naWY=/347x500/IWs4zH.gif",
         "Distribuidora": "Itch io",
         "Borde": "border-color: #00ff00;"
      },
      {
         "Nombre": "Alien Infiltration by 17-09Studio",
         "Informacion": "\u00a1\u00a1Disponible ahora!!",
         "Desde": "",
         "Hasta": "2022/12/20 05:00",
         "URL": "https://17-09studio.itch.io/alien-infiltration",
         "IMG": "https://img.itch.zone/aW1hZ2UvMTMyMzg1NC83Njk4NTA2LmpwZw==/347x500/5VUAUL.jpg",
         "Distribuidora": "Itch io",
         "Borde": "border-color: #00ff00;"
      },
      {
         "Nombre": "Dark Bot (new update) by 17-09Studio",
         "Informacion": "",
         "Desde": "",
         "Hasta": "2022/12/20 05:00",
         "URL": "https://17-09studio.itch.io/dark-bot",
         "IMG": "https://img.itch.zone/aW1hZ2UvMTA2NTYwOS82MzY4NjAzLmpwZw==/347x500/DgacI%2B.jpg",
         "Distribuidora": "Itch io",
         "Borde": "border-color: #00ff00;"
      },
      {
         "Nombre": "factory box(new update) by 17-09Studio",
         "Informacion": "17/09 Estudio",
         "Desde": "",
         "Hasta": "2022/12/20 05:00",
         "URL": "https://17-09studio.itch.io/factory-box",
         "IMG": "https://img.itch.zone/aW1hZ2UvODEzNzQ5LzQ1NjMzMzMuanBn/347x500/Gwkfh8.jpg",
         "Distribuidora": "Itch io",
         "Borde": "border-color: #00ff00;"
      },
      {
         "Nombre": "House Thief by 17-09Studio",
         "Informacion": "Un juego en el que deber\u00e1s demostrar tus habilidades para que no te descubran mientras entras a robar, \u00bfpodr\u00edas ser el mejor ladr\u00f3n del mundo?",
         "Desde": "",
         "Hasta": "2022/12/20 05:00",
         "URL": "https://17-09studio.itch.io/house-thief",
         "IMG": "https://img.itch.zone/aW1hZ2UvOTU2Mjg0LzU0MjIwMjIuanBn/347x500/nnTfmW.jpg",
         "Distribuidora": "Itch io",
         "Borde": "border-color: #00ff00;"
      },
      {
         "Nombre": "Mouse Maze Escape by 17-09Studio",
         "Informacion": "",
         "Desde": "",
         "Hasta": "2022/12/20 05:00",
         "URL": "https://17-09studio.itch.io/mouse-maze-escape",
         "IMG": "https://img.itch.zone/aW1hZ2UvMTAyNzMwMC81ODU5NjM0LmdpZg==/347x500/RcwPxu.gif",
         "Distribuidora": "Itch io",
         "Borde": "border-color: #00ff00;"
      },
      {
         "Nombre": "Pop Caps!!! by 17-09Studio",
         "Informacion": "",
         "Desde": "",
         "Hasta": "2022/12/20 05:00",
         "URL": "https://17-09studio.itch.io/pop-caps",
         "IMG": "https://img.itch.zone/aW1hZ2UvOTE0OTU5LzUxNzI1NzMuanBn/347x500/a%2Btvwk.jpg",
         "Distribuidora": "Itch io",
         "Borde": "border-color: #00ff00;"
      },
      {
         "Nombre": "PREVENT RIOT by 17-09Studio",
         "Informacion": "Disponible ahora",
         "Desde": "",
         "Hasta": "2022/12/20 05:00",
         "URL": "https://17-09studio.itch.io/prevent-riot",
         "IMG": "https://img.itch.zone/aW1hZ2UvMTEyNjY1NC82NTIyNzE2LmpwZw==/347x500/OM3h25.jpg",
         "Distribuidora": "Itch io",
         "Borde": "border-color: #00ff00;"
      },
      {
         "Nombre": "without oxygen by 17-09Studio",
         "Informacion": "Juego de plataformas, de la vieja escuela,",
         "Desde": "",
         "Hasta": "2022/12/20 05:00",
         "URL": "https://17-09studio.itch.io/without-oxygen",
         "IMG": "https://img.itch.zone/aW1hZ2UvMTQ5MTIzMC84NjkzODY3LnBuZw==/347x500/PpqGBb.png",
         "Distribuidora": "Itch io",
         "Borde": "border-color: #00ff00;"
      },
      {
         "Nombre": "Counter Aim:  Brutal Offensive by Dankoff, CounterAim series",
         "Informacion": "",
         "Desde": "",
         "Hasta": "2022/12/23 23:00",
         "URL": "https://dankoff.itch.io/counter-aim",
         "IMG": "https://img.itch.zone/aW1hZ2UvOTQ3MTI0LzUzNjkwNTQucG5n/347x500/v3Rqk%2F.png",
         "Distribuidora": "Itch io",
         "Borde": "border-color: #00ff00;"
      },
      {
         "Nombre": "Counter Aim: New Operation by Dankoff, CounterAim series",
         "Informacion": "",
         "Desde": "",
         "Hasta": "2022/12/23 23:00",
         "URL": "https://dankoff.itch.io/counter-aim-2",
         "IMG": "https://img.itch.zone/aW1hZ2UvMTA5OTk1Ni82MzQ4NjE0LnBuZw==/347x500/Uuqc%2BB.png",
         "Distribuidora": "Itch io",
         "Borde": "border-color: #00ff00;"
      },
      {
         "Nombre": "Cubes And More Cubes (Logic game) by Dankoff",
         "Informacion": "",
         "Desde": "",
         "Hasta": "2022/12/23 23:00",
         "URL": "https://dankoff.itch.io/cubes-and-more-cubes",
         "IMG": "https://img.itch.zone/aW1hZ2UvMTI1ODUwOC83MzMzNzkxLnBuZw==/347x500/Yb8bH7.png",
         "Distribuidora": "Itch io",
         "Borde": "border-color: #00ff00;"
      },
      {
         "Nombre": "Track racing battle simulator by Dankoff",
         "Informacion": "",
         "Desde": "",
         "Hasta": "2022/12/23 23:00",
         "URL": "https://dankoff.itch.io/track-racing-battle-simulator",
         "IMG": "https://img.itch.zone/aW1hZ2UvMTUxNTUyOS84ODM4NjczLnBuZw==/347x500/NrApEw.png",
         "Distribuidora": "Itch io",
         "Borde": "border-color: #00ff00;"
      },
      {
         "Nombre": "Call Centre Simulator by Catch All",
         "Informacion": "Est\u00e1 trabajando en un centro de llamadas y tiene que hablar literalmente con un cliente furioso. Escuche sus inquietudes a trav\u00e9s de sus auriculares y hable en voz alta para responderle. Se mostrar\u00e1n dos opciones de respuesta en la pantalla, diga una de ellas en voz alta para seleccionarla.",
         "Desde": "",
         "Hasta": "2022/12/24 16:00",
         "URL": "https://catchall.itch.io/call-centre-simulator",
         "IMG": "https://img.itch.zone/aW1hZ2UvMTQ5OTQ5LzY4NjcwNy5wbmc=/347x500/3fhRoi.png",
         "Distribuidora": "Itch io",
         "Borde": "border-color: #00ff00;"
      },
      {
         "Nombre": "Glidey - Minimalist brain teasing puzzles by Aboubakrsbt",
         "Informacion": "Glidey es un juego de rompecabezas alucinante con desaf\u00edos l\u00f3gicos que te molestar\u00e1n. Glidey es un rompecabezas minimalista con un juego simple pero adictivo junto con una banda sonora relajante y efectos de sonido que seguramente te ayudar\u00e1n a relajarte y concentrarte. El objetivo de este juego de rompecabezas est\u00e1 guiando una peque\u00f1a bola llamada Glidey hacia la puerta simplemente girando algunos objetos y obst\u00e1culos en el camino PERO no es tan f\u00e1cil... cada objeto y obst\u00e1culo tiene su propia habilidad \u00fanica... que crear\u00e1 un rompecabezas desafiante a veces dif\u00edcil pero definitivamente agradable. .As\u00ed que simplemente toque para rotar el objeto creando un camino para Glidey hacia la puerta o, de lo contrario, se alejar\u00e1 del objetivo y perder\u00e1 el juego y comenzar\u00e1 el nivel nuevamente.Con 75 niveles hechos a mano que contienen obst\u00e1culos, bloques, portales junto con m\u00fasica relajante y sin distracciones, Glidey definitivamente te brindar\u00e1 una experiencia inolvidable. A veces, debes pensar muchos pasos antes de lanzar la pelota, por lo que necesitar\u00e1s un buen tiempo. mory por eso tambi\u00e9n! Entonces, para completar todos los niveles, deber\u00e1 desarrollar una estrategia, tener un pensamiento l\u00f3gico y una buena memoria. Glidey le dar\u00e1 acertijos, acertijos l\u00f3gicos alucinantes que desafiar\u00e1n su mente y le dar\u00e1n satisfacci\u00f3n una vez que complete cada uno. \u00a1\u00a1nivel!!",
         "Desde": "",
         "Hasta": "2022/12/29 01:00",
         "URL": "https://aboubakrsbt.itch.io/glidey",
         "IMG": "https://img.itch.zone/aW1hZ2UvNjkxMzkyLzM4MTIyODYucG5n/347x500/rMhMf4.png",
         "Distribuidora": "Itch io",
         "Borde": "border-color: #00ff00;"
      },
      {
         "Nombre": "vika - sandbox and platformer by delibaltov",
         "Informacion": "\u00a1Ya hemos lanzado vika 0.0.1! \u00a1Estamos un mes adelantados a lo previsto! \u00bfInteresante?",
         "Desde": "",
         "Hasta": "2022/12/30 23:00",
         "URL": "https://delibaltov.itch.io/vika",
         "IMG": "https://img.itch.zone/aW1hZ2UvMTc3MTk2My8xMDQ1OTUzNS5wbmc=/347x500/efufpU.png",
         "Distribuidora": "Itch io",
         "Borde": "border-color: #00ff00;"
      },
      {
         "Nombre": "Banknotes Memory Puzzle by unaux_25917242",
         "Informacion": "Juego de memoria de escritorio. Descubra billetes similares en 22 im\u00e1genes. Obtenga la puntuaci\u00f3n m\u00e1xima en el mejor momento.",
         "Desde": "",
         "Hasta": "2022/12/31 00:00",
         "URL": "https://unaux-25917242.itch.io/banknotes-memory-puzzle",
         "IMG": "https://img.itch.zone/aW1hZ2UvMjIzMDY5LzEwNTI5NjQuanBn/347x500/fRgDJK.jpg",
         "Distribuidora": "Itch io",
         "Borde": "border-color: #00ff00;"
      },
      {
         "Nombre": "simple frogger zx spectrum by unaux_25917242",
         "Informacion": "clon de rana",
         "Desde": "",
         "Hasta": "2022/12/31 00:00",
         "URL": "https://unaux-25917242.itch.io/simple-frogger-zx-spectrum",
         "IMG": "https://img.itch.zone/aW1hZ2UvMTE1NTE1NS82NzEyMTg1LmpwZw==/347x500/dYUYbj.jpg",
         "Distribuidora": "Itch io",
         "Borde": "border-color: #00ff00;"
      },
      {
         "Nombre": "The Dark Retributionist by al3cs71",
         "Informacion": "\u00a1Te despiertas de tu sue\u00f1o eterno en busca de venganza!",
         "Desde": "",
         "Hasta": "2022/12/31 00:00",
         "URL": "https://al3cs71.itch.io/the-dark-retributionist",
         "IMG": "https://img.itch.zone/aW1hZ2UvOTExNTI5LzczMzY2OTMucG5n/347x500/TKX6Mc.png",
         "Distribuidora": "Itch io",
         "Borde": "border-color: #00ff00;"
      },
      {
         "Nombre": "Virtual Pet Caterpillar 1.0 by unaux_25917242",
         "Informacion": "Oruga de mascota virtual: el ciclo de vida de 17 niveles de las orugas, agregue comida, sue\u00f1o y diversi\u00f3n para evolucionar al final del d\u00eda (~ 1,5 h), muy poco o demasiado afecta la felicidad general, obtenga nuevas acciones con subir de nivel.",
         "Desde": "",
         "Hasta": "2022/12/31 00:00",
         "URL": "https://unaux-25917242.itch.io/virtual-pet-caterpillar-10",
         "IMG": "https://img.itch.zone/aW1hZ2UvMjIxMTAwLzEyMzI4NTAuanBn/347x500/uxXYqe.jpg",
         "Distribuidora": "Itch io",
         "Borde": "border-color: #00ff00;"
      },
      {
         "Nombre": "Bones in the Boneyard by John D. Moore",
         "Informacion": "Hay muchos huesos en el cementerio. A medida que caen de la pantalla, coloca las calaveras en filas de tres para despejarlas y alinea los esqueletos completos para liberarlas.",
         "Desde": "",
         "Hasta": "2022/12/31 07:00",
         "URL": "https://jdmgames.itch.io/bones-in-the-boneyard",
         "IMG": "https://img.itch.zone/aW1hZ2UvMTc3MTM2OS8xMDQxMzcyNy5wbmc=/347x500/sGD27W.png",
         "Distribuidora": "Itch io",
         "Borde": "border-color: #00ff00;"
      },
      {
         "Nombre": "Dr. Creepinscare's Pumpkin Patch Match by John D. Moore",
         "Informacion": "\u00a1El Dr. Creepinscare est\u00e1 aqu\u00ed para invitarte a poner a prueba tu ingenio y tus reflejos en su diab\u00f3lico huerto de calabazas! Divi\u00e9rtete espeluznantemente colocando las calabazas que caen en arreglos especiales para despejar el campo. Sin embargo, el genio loco del Dr. Creepinscare ha ideado que todas las calabazas tienen caras talladas de manera similar. \u00a1Estar alerta!",
         "Desde": "",
         "Hasta": "2022/12/31 07:00",
         "URL": "https://jdmgames.itch.io/pumpkin-patch-match",
         "IMG": "https://img.itch.zone/aW1hZ2UvMTgzNjUwLzg1ODY2My5wbmc=/347x500/f%2Fd9MK.png",
         "Distribuidora": "Itch io",
         "Borde": "border-color: #00ff00;"
      },
      {
         "Nombre": "ExpandoScape by John D. Moore",
         "Informacion": "Manipula el tama\u00f1o de los bloques de engranajes verdes para llegar a objetivos aparentemente inalcanzables en este exclusivo juego de plataformas y rompecabezas.",
         "Desde": "",
         "Hasta": "2022/12/31 07:00",
         "URL": "https://jdmgames.itch.io/expandoscape",
         "IMG": "https://img.itch.zone/aW1hZ2UvNDQ2NjcvMTIzNTI5NC5wbmc=/347x500/vr0Y2q.png",
         "Distribuidora": "Itch io",
         "Borde": "border-color: #00ff00;"
      },
      {
         "Nombre": "Fairy Penguin Parade by John D. Moore",
         "Informacion": "El ping\u00fcino hada (tambi\u00e9n conocido como el ping\u00fcino peque\u00f1o) es el ping\u00fcino m\u00e1s peque\u00f1o del mundo.",
         "Desde": "",
         "Hasta": "2022/12/31 07:00",
         "URL": "https://jdmgames.itch.io/fairy-penguin-parade",
         "IMG": "https://img.itch.zone/aW1hZ2UvNTU2MTMzLzI5MTQwMDIucG5n/347x500/admHFl.png",
         "Distribuidora": "Itch io",
         "Borde": "border-color: #00ff00;"
      },
      {
         "Nombre": "Invasion Versus by John D. Moore",
         "Informacion": "Invasi\u00f3n contra",
         "Desde": "",
         "Hasta": "2022/12/31 07:00",
         "URL": "https://jdmgames.itch.io/invasion-versus",
         "IMG": "https://img.itch.zone/aW1hZ2UvMjg5Nzg1LzE0MjgyODAuZ2lm/347x500/oY%2B1Wq.gif",
         "Distribuidora": "Itch io",
         "Borde": "border-color: #00ff00;"
      },
      {
         "Nombre": "Koi Puncher MMXVIII by John D. Moore",
         "Informacion": "ERES UN GOLPEADOR DE KOI.",
         "Desde": "",
         "Hasta": "2022/12/31 07:00",
         "URL": "https://jdmgames.itch.io/koi-puncher-mmxviii",
         "IMG": "https://img.itch.zone/aW1hZ2UvMjQzNDgzLzExNzE5MDkucG5n/347x500/6S%2BFZO.png",
         "Distribuidora": "Itch io",
         "Borde": "border-color: #00ff00;"
      },
      {
         "Nombre": "Liz & Laz: The Control Cubes by John D. Moore",
         "Informacion": "Cuando un extra\u00f1o accidente desestabiliza el estabilizador, los cubos de control desaparecen y Liz y Laz deben trabajar juntos para asegurarlos. Laz se transporta a un paisaje peligroso y conf\u00eda en las instrucciones de Liz para mantenerlo a salvo.",
         "Desde": "",
         "Hasta": "2022/12/31 07:00",
         "URL": "https://jdmgames.itch.io/liz-laz-1",
         "IMG": "https://img.itch.zone/aW1hZ2UvMjY0NjY2LzEyODE1NzEucG5n/347x500/%2F%2B8Iv%2B.png",
         "Distribuidora": "Itch io",
         "Borde": "border-color: #00ff00;"
      },
      {
         "Nombre": "Monster Hug by John D. Moore",
         "Informacion": "Bienvenido a ABRAZO DE MONSTRUO.",
         "Desde": "",
         "Hasta": "2022/12/31 07:00",
         "URL": "https://jdmgames.itch.io/monster-hug",
         "IMG": "https://img.itch.zone/aW1hZ2UvMzE0NzIwLzE1NDgwNTIucG5n/347x500/c7ocxL.png",
         "Distribuidora": "Itch io",
         "Borde": "border-color: #00ff00;"
      },
      {
         "Nombre": "Orbital Paladin Melchior Y by John D. Moore",
         "Informacion": "Es el a\u00f1o 231 de la Era Fronteriza.",
         "Desde": "",
         "Hasta": "2022/12/31 07:00",
         "URL": "https://jdmgames.itch.io/orbital-paladin-melchior-y",
         "IMG": "https://img.itch.zone/aW1hZ2UvMzY3NDEzLzE4NjA0MzQuZ2lm/347x500/EtyL%2Fl.gif",
         "Distribuidora": "Itch io",
         "Borde": "border-color: #00ff00;"
      },
      {
         "Nombre": "Shadow Wrangler by John D. Moore",
         "Informacion": "Tus sombras se han separado de ti y debes guiarlas hacia la salida. Puedes moverte a voluntad, pero las sombras deben recibir \u00f3rdenes. Recoge cuadros de comando (girar, saltar, explotar) y soltarlos donde quieras que act\u00faen las sombras.",
         "Desde": "",
         "Hasta": "2022/12/31 07:00",
         "URL": "https://jdmgames.itch.io/shadow-wrangler",
         "IMG": "https://img.itch.zone/aW1hZ2UvMjExMDEvODM0ODgucG5n/347x500/VGlC5B.png",
         "Distribuidora": "Itch io",
         "Borde": "border-color: #00ff00;"
      },
      {
         "Nombre": "Temple of the Wumpus by John D. Moore",
         "Informacion": "Bienvenido, Peregrino",
         "Desde": "",
         "Hasta": "2022/12/31 07:00",
         "URL": "https://jdmgames.itch.io/temple-of-the-wumpus",
         "IMG": "https://img.itch.zone/aW1hZ2UvMjc0NTMwLzEzMjkxNjIucG5n/347x500/mkT%2Fhs.png",
         "Distribuidora": "Itch io",
         "Borde": "border-color: #00ff00;"
      },
      {
         "Nombre": "Ungrateful Birds by John D. Moore",
         "Informacion": "\u00a1Alguien ha secuestrado a los p\u00e1jaros y los ha puesto en jaulas en el bosque! \u00a1Por favor, gu\u00e1rdalos! Sin embargo, estos p\u00e1jaros NO SER\u00c1N AGRADECIDOS.",
         "Desde": "",
         "Hasta": "2022/12/31 07:00",
         "URL": "https://jdmgames.itch.io/ungrateful-birds",
         "IMG": "https://img.itch.zone/aW1hZ2UvMTQ4ODY5LzY4MTkyOC5wbmc=/347x500/K%2FCmVs.png",
         "Distribuidora": "Itch io",
         "Borde": "border-color: #00ff00;"
      },
      {
         "Nombre": "Village Vampire Feast by John D. Moore",
         "Informacion": "Una actualizaci\u00f3n de 2018 de un juego que hice en 2012.",
         "Desde": "",
         "Hasta": "2022/12/31 07:00",
         "URL": "https://jdmgames.itch.io/village-vampire-feast",
         "IMG": "https://img.itch.zone/aW1hZ2UvMzE2Mjg4LzE1NTcyMTMucG5n/347x500/caO9Uj.png",
         "Distribuidora": "Itch io",
         "Borde": "border-color: #00ff00;"
      },
      {
         "Nombre": "ART SQOOL by Glanderco",
         "Informacion": "BIENVENIDO A",
         "Desde": "",
         "Hasta": "2022/12/31 07:00",
         "URL": "https://glander.itch.io/art-sqool",
         "IMG": "https://img.itch.zone/aW1hZ2UvMzA1NjI3LzE1MDM0NjIuanBn/347x500/L40ew5.jpg",
         "Distribuidora": "Itch io",
         "Borde": "border-color: #00ff00;"
      },
      {
         "Nombre": "Linda & Joan Prologue: \u00e2\u0080\u009cFour Months Earlier\u00e2\u0080\u009d by False Vacuum Games",
         "Informacion": "** Preseleccionado para el\u00a0Premio de Escritura de Nuevos Medios 2021 **\u00e2Se sostiene por s\u00ed solo, el juego equivalente a un poema.\u00e2 \u2014Los Angeles Times",
         "Desde": "",
         "Hasta": "2022/12/31 10:00",
         "URL": "https://falsevacuum.itch.io/linda-joan-prologue",
         "IMG": "https://img.itch.zone/aW1hZ2UvNjE0MjY2LzM3MzE1NTIuanBn/347x500/LRuXyS.jpg",
         "Distribuidora": "Itch io",
         "Borde": "border-color: #00ff00;"
      },
      {
         "Nombre": "The CAMMEN Project by TheAZh Games",
         "Informacion": "\"Controle a S.I.G.H.T-12. \u00a1Considere esta su\u00a0advertencia! Aunque ha sido seleccionado para unirse al Proyecto C.A.M.M.E.N, su seguridad NO est\u00e1 garantizada. En caso de falla de su parte, su acceso al programa ser\u00e1 revocado independientemente de su supervivencia, cambio. \"",
         "Desde": "",
         "Hasta": "2022/12/31 22:59",
         "URL": "https://theult.itch.io/cammen",
         "IMG": "https://img.itch.zone/aW1hZ2UvMTcxMDAyNC8xMDA3NDIxNi5wbmc=/347x500/HCdOkJ.png",
         "Distribuidora": "Itch io",
         "Borde": "border-color: #00ff00;"
      },
      {
         "Nombre": "a short love story by Happy Doggo",
         "Informacion": "\u00a1Esta historia es sobre la cosa m\u00e1s incre\u00edble del mundo! \u00a1sobre el amor!",
         "Desde": "",
         "Hasta": "2022/12/31 23:00",
         "URL": "https://happydoggostudio.itch.io/a-short-love-story",
         "IMG": "https://img.itch.zone/aW1hZ2UvMTY4ODkwNC8xMDAzNjQ1NS5qcGc=/347x500/WwCHXk.jpg",
         "Distribuidora": "Itch io",
         "Borde": "border-color: #00ff00;"
      },
      {
         "Nombre": "Ecoman by Happy Doggo",
         "Informacion": "Ecoman es un juego corto creado durante Eco Jam que se llev\u00f3 a cabo en el Garaje del Museo de Arte Contempor\u00e1neo del 23 al 24 de noviembre.",
         "Desde": "",
         "Hasta": "2022/12/31 23:00",
         "URL": "https://happydoggostudio.itch.io/ecoman",
         "IMG": "https://img.itch.zone/aW1hZ2UvNTI0MzE4LzI3MjMxNzgucG5n/347x500/OdtNbk.png",
         "Distribuidora": "Itch io",
         "Borde": "border-color: #00ff00;"
      },
      {
         "Nombre": "Flower Parade by Happy Doggo",
         "Informacion": "\u00a1Eres una supermujer valiente en el camino para salvar a la humanidad del apocalipsis!",
         "Desde": "",
         "Hasta": "2022/12/31 23:00",
         "URL": "https://happydoggostudio.itch.io/flower-parade",
         "IMG": "https://img.itch.zone/aW1hZ2UvODg5MDUzLzUwNDk1NjcuanBlZw==/347x500/plg4zp.jpeg",
         "Distribuidora": "Itch io",
         "Borde": "border-color: #00ff00;"
      },
      {
         "Nombre": "I need to pee by Happy Doggo",
         "Informacion": "Un juego de aventuras sobre la superaci\u00f3n de dificultades.",
         "Desde": "",
         "Hasta": "2022/12/31 23:00",
         "URL": "https://happydoggostudio.itch.io/i-need-to-pee",
         "IMG": "https://img.itch.zone/aW1hZ2UvODY4NTMwLzQ4ODQwNzMuanBlZw==/347x500/S0x8Q2.jpeg",
         "Distribuidora": "Itch io",
         "Borde": "border-color: #00ff00;"
      },
      {
         "Nombre": "Mend Game by Happy Doggo",
         "Informacion": "FECHA DE LANZAMIENTO: 16 DE MARZO!!",
         "Desde": "",
         "Hasta": "2022/12/31 23:00",
         "URL": "https://happydoggostudio.itch.io/mend-game",
         "IMG": "https://img.itch.zone/aW1hZ2UvNTYwMzI4LzMxMDU1NDIuanBn/347x500/Zg4tWZ.jpg",
         "Distribuidora": "Itch io",
         "Borde": "border-color: #00ff00;"
      },
      {
         "Nombre": "Soul Of Hero by Alpi Games",
         "Informacion": "Juego de rol de plataforma Soul of Hero",
         "Desde": "",
         "Hasta": "2022/12/31 23:00",
         "URL": "https://alpigames.itch.io/soulofhero",
         "IMG": "https://img.itch.zone/aW1hZ2UvNTU5MjE0LzMzNjYxNDAucG5n/347x500/r4Es7A.png",
         "Distribuidora": "Itch io",
         "Borde": "border-color: #00ff00;"
      },
      {
         "Nombre": "ProjectXnow  [\u00f0\u009f\u0087\u00ac\u00f0\u009f\u0087\u00a7/\u00f0\u009f\u0087\u00ab\u00f0\u009f\u0087\u00b7] (Online) by Pinou007",
         "Informacion": "\u00f0\u00ab\u00f0 \u00b7 En una vida donde un virus ha infectado a todos, los humanos que no est\u00e1n infectados, decidimos instalarnos en las alcantarillas y el subsuelo, los Humanos, comenzamos a desarrollar las alcantarillas y el subsuelo Te revelas en una casa de un cient\u00edfico que quiere usarte y decides salir de su casa y encontrarse en las alcantarillas",
         "Desde": "",
         "Hasta": "2022/12/31 23:59",
         "URL": "https://pinou007.itch.io/projectxnow",
         "IMG": "https://img.itch.zone/aW1hZ2UvMTM2MzY5NC84MDcwMjQ5LnBuZw==/347x500/JOvejr.png",
         "Distribuidora": "Itch io",
         "Borde": "border-color: #00ff00;"
      },
      {
         "Nombre": "Radio Player (Ancien Version) by Pinou007",
         "Informacion": "Escucha tu radio favorita est\u00e9s donde est\u00e9s gracias a radio player 2020 Versi\u00f3n antigua",
         "Desde": "",
         "Hasta": "2022/12/31 23:59",
         "URL": "https://pinou007.itch.io/radio-player",
         "IMG": "https://img.itch.zone/aW1hZ2UvMTcyMjk4Ny8xMDE0ODQ2Ny5wbmc=/347x500/%2Fi%2BmeP.png",
         "Distribuidora": "Itch io",
         "Borde": "border-color: #00ff00;"
      },
      {
         "Nombre": "thisPaper by Pinou007",
         "Informacion": "Suspendido temporalmente thisPaper es un juego donde tienes que recuperar 10Paper este juego es realmente simple el juego se hizo en 12 horas un reto personal que comenc\u00e9 los otros juegos que ser\u00e1n de mejor calidadMapa DisponibleOtros mapas estar\u00e1n disponibles",
         "Desde": "",
         "Hasta": "2023/01/01 01:00",
         "URL": "https://pinou007.itch.io/paper",
         "IMG": "https://img.itch.zone/aW1hZ2UvMTM3MTMwMS83OTg3NDY2LnBuZw==/347x500/dRFdzZ.png",
         "Distribuidora": "Itch io",
         "Borde": "border-color: #00ff00;"
      },
      {
         "Nombre": "Bunny Hill Horror by Krunchy Fried Games",
         "Informacion": "Actualizaci\u00f3n: El cap\u00edtulo final - Bunny Hill Horror: Bunny Boiler, \u00a1ahora en itch.io!",
         "Desde": "",
         "Hasta": "2023/01/01 01:59",
         "URL": "https://krunchyfriedgames.itch.io/bunny-hill-horror",
         "IMG": "https://img.itch.zone/aW1hZ2UvNTAxOTIyLzI1OTc2ODEucG5n/347x500/uATBvN.png",
         "Distribuidora": "Itch io",
         "Borde": "border-color: #00ff00;"
      },
      {
         "Nombre": "Bunny Hill Horror: Bunny Boiler by Krunchy Fried Games",
         "Informacion": "Oswald Mandias es un hombre con una misi\u00f3n: arrastrar al pa\u00eds pateando y gritando de regreso a los d\u00edas de gloria de anta\u00f1o, donde un caballero pod\u00eda confiar en los valores probados por el tiempo de la caballerosidad, la educaci\u00f3n y la clase. Armado con zombis viciosos, una reserva de productos farmac\u00e9uticos muy cuestionables y una voluntad de hierro, te ha reclutado para que hagas realidad sus planes.",
         "Desde": "",
         "Hasta": "2023/01/01 01:59",
         "URL": "https://krunchyfriedgames.itch.io/bunny-hill-horror-bunny-boiler",
         "IMG": "https://img.itch.zone/aW1hZ2UvNzkwNzU0LzQ0Mjc2NDQuanBn/347x500/B16Bli.jpg",
         "Distribuidora": "Itch io",
         "Borde": "border-color: #00ff00;"
      },
      {
         "Nombre": "Witches and Bandits and Swords (Oh My) by Krunchy Fried Games",
         "Informacion": "Witches and Bandits and Swords (Oh My) es un juego de novelas gr\u00e1ficas de elecci\u00f3n de aventuras solo para mouse en el que debes explorar bosques peligrosos, salvar a tus amigos de una conspiraci\u00f3n pirata y evitar a un b\u00e1rbaro particularmente extra\u00f1o que quiere hacer cosas desagradables para tu entra\u00f1as blandas.",
         "Desde": "",
         "Hasta": "2023/01/01 01:59",
         "URL": "https://krunchyfriedgames.itch.io/witches-and-bandits-and-swords-oh-my",
         "IMG": "https://img.itch.zone/aW1hZ2UvMTg4NTc3Lzg4NDQ4MS5qcGc=/347x500/2Oaqw3.jpg",
         "Distribuidora": "Itch io",
         "Borde": "border-color: #00ff00;"
      },
      {
         "Nombre": "Tales from the Aerosphere by Ethan H. Reynolds",
         "Informacion": "\u00bfQui\u00e9n ser\u00e1s en esta ciudad entre las nubes?",
         "Desde": "",
         "Hasta": "2023/01/01 06:00",
         "URL": "https://ethanhreynolds.itch.io/tales-from-the-aerosphere",
         "IMG": "https://img.itch.zone/aW1hZ2UvMTMyNzM1Ny83NzE5MTAzLnBuZw==/347x500/ocLqT0.png",
         "Distribuidora": "Itch io",
         "Borde": "border-color: #00ff00;"
      },
      {
         "Nombre": "Chimera Crusader: Defender of Dominicus by MansterSoft",
         "Informacion": "El rey Dominicus ordena a su principal palad\u00edn que mate a la terrible quimera. Pero va a tomar un poco de molienda. Tendr\u00e1n que acumular fuerza matando todo lo dem\u00e1s en su camino. Es lo m\u00ednimo que puede conseguir un juego de rol.",
         "Desde": "",
         "Hasta": "2023/01/01 08:00",
         "URL": "https://manstersoft.itch.io/chimera-crusader",
         "IMG": "https://img.itch.zone/aW1hZ2UvNjA1MDgvNDE4MjQ3Ni5naWY=/347x500/xm0l%2FS.gif",
         "Distribuidora": "Itch io",
         "Borde": "border-color: #00ff00;"
      },
      {
         "Nombre": "Oatboy vs. Slime Mold by MansterSoft",
         "Informacion": "Oatboy vs. Slime Mold es un intento de hacer un juego de acci\u00f3n de ritmo r\u00e1pido con un concepto \u00fanico y un juego original que encajar\u00eda con los juegos Arcade de finales de los 70 y principios de los 80.",
         "Desde": "",
         "Hasta": "2023/01/01 08:00",
         "URL": "https://manstersoft.itch.io/oatboy-vs-slime-mold",
         "IMG": "https://img.itch.zone/aW1hZ2UvNjkzNDYvOTEzMDg0LmdpZg==/347x500/UqdR%2Fz.gif",
         "Distribuidora": "Itch io",
         "Borde": "border-color: #00ff00;"
      },
      {
         "Nombre": "Run-N-Jump-N-Jump-N-Run by MansterSoft",
         "Informacion": "Esta descarga incluye tanto \"Run-N-Jump-N-Jump-N-Run\" como \"Capybara Capriole\".",
         "Desde": "",
         "Hasta": "2023/01/01 08:00",
         "URL": "https://manstersoft.itch.io/run-n-jump",
         "IMG": "https://img.itch.zone/aW1hZ2UvMTcyMTkwLzgwMTIxNy5wbmc=/347x500/a4QLL9.png",
         "Distribuidora": "Itch io",
         "Borde": "border-color: #00ff00;"
      },
      {
         "Nombre": "The MansterSoft 3-in-1 Fun-Pak by MansterSoft",
         "Informacion": "MansterSoft presenta: \u00a1El Fun-Pak 3 en 1 de MansterSoft!",
         "Desde": "",
         "Hasta": "2023/01/01 08:00",
         "URL": "https://manstersoft.itch.io/fun-pak",
         "IMG": "https://img.itch.zone/aW1hZ2UvNjkyMDUvMzE1NDQ2LnBuZw==/347x500/c5kQuc.png",
         "Distribuidora": "Itch io",
         "Borde": "border-color: #00ff00;"
      },
      {
         "Nombre": "The Mini-Game 3-in-1 Fun-Pak by MansterSoft",
         "Informacion": "MansterSoft se enorgullece en presentar:\u00a0\u00a1El minijuego 3 en 1 Fun-Pak!",
         "Desde": "",
         "Hasta": "2023/01/01 08:00",
         "URL": "https://manstersoft.itch.io/the-mini-game-3-in-1-fun-pak",
         "IMG": "https://img.itch.zone/aW1hZ2UvNzE5NzMxLzM5ODk5NDAucG5n/347x500/Rh2Xea.png",
         "Distribuidora": "Itch io",
         "Borde": "border-color: #00ff00;"
      },
      {
         "Nombre": "The Mr. Dude 4-in-1 Poopy-Pak by MansterSoft",
         "Informacion": "MansterSoft presenta con orgullo: \u00a1El Poopy-Pak 4 en 1 de Mr. Dude!",
         "Desde": "",
         "Hasta": "2023/01/01 08:00",
         "URL": "https://manstersoft.itch.io/poopy-pak",
         "IMG": "https://img.itch.zone/aW1hZ2UvMTMwODAxLzYwMDYxNi5wbmc=/347x500/EfrurF.png",
         "Distribuidora": "Itch io",
         "Borde": "border-color: #00ff00;"
      },
      {
         "Nombre": "Remain Commie by Gravity Games Studios",
         "Informacion": "\u00a1Un juego de disparos de arriba hacia abajo de estilo arcade donde el jugador debe defenderse de las oleadas de comunistas!",
         "Desde": "",
         "Hasta": "2023/01/01 08:59",
         "URL": "https://gravity-games-studios.itch.io/remain-commie",
         "IMG": "https://img.itch.zone/aW1hZ2UvMTU2MDEyMi8xMDYyMTkzMy5wbmc=/347x500/4iOfpF.png",
         "Distribuidora": "Itch io",
         "Borde": "border-color: #00ff00;"
      },
      {
         "Nombre": "Choose the cat by Raph88",
         "Informacion": "El gato es lo mejor, as\u00ed que elige siempre al gato.",
         "Desde": "",
         "Hasta": "2023/01/01 16:15",
         "URL": "https://raph88.itch.io/choose-the-cat",
         "IMG": "https://img.itch.zone/aW1hZ2UvNjEzODA3LzMyNjU3ODcucG5n/347x500/V3flSz.png",
         "Distribuidora": "Itch io",
         "Borde": "border-color: #00ff00;"
      },
      {
         "Nombre": "Trapped with A Demon by SharPiii",
         "Informacion": "El clima empeora durante tu campamento en solitario en el bosque.",
         "Desde": "",
         "Hasta": "2023/01/05 20:00",
         "URL": "https://sharpiii.itch.io/trapped-with-demon",
         "IMG": "https://img.itch.zone/aW1hZ2UvMTcxODg5MS8xMDEyNjg3Ny5wbmc=/347x500/joFnMh.png",
         "Distribuidora": "Itch io",
         "Borde": "border-color: #00ff00;"
      },
      {
         "Nombre": "Cyber Cars Punk Racing 2 by AYN Games",
         "Informacion": "JUEGOS AYN",
         "Desde": "",
         "Hasta": "2023/01/30 23:00",
         "URL": "https://ayngames.itch.io/cyber-cars-punk-racing-2",
         "IMG": "https://img.itch.zone/aW1hZ2UvMTMxNzYxMy83NjYyMDIzLnBuZw==/347x500/Rcc%2Fk%2B.png",
         "Distribuidora": "Itch io",
         "Borde": "border-color: #00ff00;"
      },
      {
         "Nombre": "Free Run by Durant dev",
         "Informacion": "cr\u00e9dito a dani's 3d game karlson por inspiraci\u00f3n",
         "Desde": "",
         "Hasta": "2023/02/17 00:00",
         "URL": "https://durant.itch.io/freerun",
         "IMG": "https://img.itch.zone/aW1hZ2UvMTU2MzYwNi85MTM1MzE3LnBuZw==/347x500/lxidEU.png",
         "Distribuidora": "Itch io",
         "Borde": "border-color: #00ff00;"
      },
      {
         "Nombre": "Incredible Zig Zag by Durant dev",
         "Informacion": "",
         "Desde": "",
         "Hasta": "2023/02/17 00:00",
         "URL": "https://durant.itch.io/incredible-zig-zag",
         "IMG": "https://img.itch.zone/aW1nLzk3NjYwNzAucG5n/347x500/QrFqa2.png",
         "Distribuidora": "Itch io",
         "Borde": "border-color: #00ff00;"
      },
      {
         "Nombre": "Ultimate Minesweeper by Durant dev",
         "Informacion": "",
         "Desde": "",
         "Hasta": "2023/02/17 00:00",
         "URL": "https://durant.itch.io/minesweeper-petal",
         "IMG": "https://img.itch.zone/aW1hZ2UvMTU1Mzk1NC85MDY2NzE2LnBuZw==/347x500/upqTfw.png",
         "Distribuidora": "Itch io",
         "Borde": "border-color: #00ff00;"
      },
      {
         "Nombre": "2D ZooM 1.5 by Durant dev",
         "Informacion": "",
         "Desde": "",
         "Hasta": "2023/05/25 00:00",
         "URL": "https://durant.itch.io/2d-zoom-15",
         "IMG": "https://img.itch.zone/aW1nLzcwMTc4NjEucG5n/347x500/k4dacp.png",
         "Distribuidora": "Itch io",
         "Borde": "border-color: #00ff00;"
      },
      {
         "Nombre": "2D ZooM by Durant dev",
         "Informacion": "",
         "Desde": "",
         "Hasta": "2023/05/25 00:00",
         "URL": "https://durant.itch.io/2d-zoom",
         "IMG": "https://img.itch.zone/aW1nLzY5NjYxOTkucG5n/347x500/VGJm1S.png",
         "Distribuidora": "Itch io",
         "Borde": "border-color: #00ff00;"
      },
      {
         "Nombre": "Not A RICK roll by ZevKev",
         "Informacion": "Totalmente no es un rick roll",
         "Desde": "",
         "Hasta": "2023/06/30 00:00",
         "URL": "https://zevkev.itch.io/not-a-rick-roll",
         "IMG": "https://img.itch.zone/aW1nLzUzMjAwNzQucG5n/347x500/ppnYpk.png",
         "Distribuidora": "Itch io",
         "Borde": "border-color: #00ff00;"
      },
      {
         "Nombre": "OffBike (pre-release) by ZevKev",
         "Informacion": "OFFBIKE\u00a0 \u00a0\u00a0 es un simulador de motos, \u00a1que todav\u00eda est\u00e1 en desarrollo!",
         "Desde": "",
         "Hasta": "2023/06/30 00:00",
         "URL": "https://zevkev.itch.io/offbike",
         "IMG": "https://img.itch.zone/aW1hZ2UvODY1NzIwLzQ4NjUyOTMuanBn/347x500/DiqeW2.jpg",
         "Distribuidora": "Itch io",
         "Borde": "border-color: #00ff00;"
      },
      {
         "Nombre": "Goose Simulator by Donquae Alfred, Attack On Juice",
         "Informacion": "\u00e2\u00a0\u00ef\u00b8\u00danete a Discord para obtener ayuda y noticias sobre nuevas actualizaciones y funciones\u00a0\u00e2\u00a0\u00ef\u00b8",
         "Desde": "",
         "Hasta": "2042/11/01 04:00",
         "URL": "https://donquae-alfred.itch.io/goosesimulator",
         "IMG": "https://img.itch.zone/aW1hZ2UvMTQ3MTM4Ni84ODMyOTA0LnBuZw==/347x500/y%2BmMSW.png",
         "Distribuidora": "Itch io",
         "Borde": "border-color: #00ff00;"
      },
      {
         "Nombre": "I Get This Call Every Day by David S Gallant",
         "Informacion": "Exactamente lo que dice en la caja: una experiencia ligeramente filtrada extra\u00edda de mi (ahora anterior) trabajo diario en un centro de atenci\u00f3n al cliente, hecha interactiva en un formato de apuntar y hacer clic. Pierde cort\u00e9smente, o pierde espectacularmente; la decisi\u00f3n es tuya.",
         "Desde": "",
         "Hasta": "2057/03/16 00:00",
         "URL": "https://davidsgallant.itch.io/i-get-this-call-every-day",
         "IMG": "https://img.itch.zone/aW1hZ2UvMzQyLzMxNzU0My5wbmc=/347x500/PyFxVy.png",
         "Distribuidora": "Itch io",
         "Borde": "border-color: #00ff00;"
      },
      {
         "Nombre": "Iris and the Giant",
         "Informacion": "Iris and the Giant es una fusi\u00f3n de los g\u00e9neros roguelike, RPG y CCG. Juegas como Iris y descubrir\u00e1s su psique y sus ansiedades. Construye tu mazo Con cada encuentro, desbloquea nuevas cartas y gana puntos para impulsar a Iris. \u00a1Cada intento te hace m\u00e1s fuerte y te permite llegar m\u00e1s lejos! Una po\u00e9tica, melan...",
         "Desde": "",
         "Hasta": "2066/01/20 15:00",
         "URL": "https://www.gog.com/en/game/iris_and_the_giant_deckbuilding_roguelike",
         "IMG": "https://images.gog-statics.com/1aaa1c61a8d6c77c40353bc74b3f0286c4dd61d6641a7028d5db84df053bcfdd.jpg",
         "Distribuidora": "GOG",
         "Borde": "border-color: #00ff00;"
      },
      {
         "Nombre": "POSTAL 2",
         "Informacion": "\u00a1El que lo reinici\u00f3 todo! \u00a1The Dude aparece en su primer d\u00eda de trabajo en RWS y se produce la hilaridad! \u00a1Lucha contra los polic\u00edas! \u00a1Rabia contra el Hombre! \u00a1Acaba con los talibanes! \u00a1Compra leche! \u00a1Consigue un aut\u00f3grafo de Gary Coleman! Olv\u00eddate de lo que sabes sobre los juegos de disparos en primera persona. Camine durante una semana entera en el zapato del Postal Dude...",
         "Desde": "",
         "Hasta": "2080/09/17 19:00",
         "URL": "https://www.gog.com/en/game/postal_2",
         "IMG": "https://images.gog-statics.com/d852a13d79875678614aee8b5f534cd391eafcc51d443053d42b8210f1cb1d2a.jpg",
         "Distribuidora": "GOG",
         "Borde": "border-color: #00ff00;"
      },
      {
         "Nombre": "The Witcher Goodies Collection",
         "Informacion": "Tenemos un verdadero placer para todos los jugadores: The Witcher Goodies Collection disponible de forma gratuita. Incluye artes, libros, bandas sonoras, creaci\u00f3n de videos, conciertos de Video Game Show, fondos de pantalla y muchos m\u00e1s obsequios de todos los juegos de The Witcher reunidos. Reclama este sorteo \u00fanico antes de que finalice...",
         "Desde": "",
         "Hasta": "2162/11/28 15:00",
         "URL": "https://www.gog.com/en/game/the_witcher_goodies_collection",
         "IMG": "https://images.gog-statics.com/a344e6ee3a17af9e6529dd22deda462aa0c5cc7a856d3a4f8cb84e15d31a3a76.jpg",
         "Distribuidora": "GOG",
         "Borde": "border-color: #00ff00;"
      },
      {
         "Nombre": "Sanitarium",
         "Informacion": "Imagina un mundo creado a partir de la locura: ni\u00f1os deformes, dioses antiguos, fantasmas de tu pasado en la casa dentro de un reflejo de agua. Eres un paciente de asilo y acabas de sobrevivir a un accidente automovil\u00edstico; el problema es que no puedes recordar nada. Las visiones revelan respuestas a algunas preguntas, pero c...",
         "Desde": "",
         "Hasta": "2208/06/05 15:00",
         "URL": "https://www.gog.com/en/game/sanitarium",
         "IMG": "https://images.gog-statics.com/098fae4f00b2c7d0d727fc55f997c80740e2ef2ed5df44cadc30f814da6af16b.jpg",
         "Distribuidora": "GOG",
         "Borde": "border-color: #00ff00;"
      },
      {
         "Nombre": "Venetica - Gold Edition",
         "Informacion": "\u00a1Abr\u00f3chate el cintur\u00f3n y explora nuestro centro de ofertas de verano! Ambientada en el fant\u00e1stico mundo de la antigua Venecia, la joven Scarlett es v\u00edctima de un terrible misterio, que comienza con el asesinato de su compa\u00f1ero a manos de una alianza secreta de poderosos nigromantes. As\u00ed el destino toma su curso inevitable y amenaza con l...",
         "Desde": "",
         "Hasta": "2219/05/19 15:00",
         "URL": "https://www.gog.com/en/game/venetica",
         "IMG": "https://images.gog-statics.com/39ee0faef6dc014d96dffa267c11ebb940e71f7df1120a4e4ab5123ab0ee30cf.jpg",
         "Distribuidora": "GOG",
         "Borde": "border-color: #00ff00;"
      },
      {
         "Nombre": "Shantae and the Pirate's Curse",
         "Informacion": "\u00a1Abr\u00f3chate el cintur\u00f3n y explora nuestro centro de ofertas de verano! Emb\u00e1rcate en una nueva aventura con Shantae, la genio de la danza del vientre que mueve el cabello. Despu\u00e9s de perder su magia, Shantae se une al infame pirata Risky Boots para salvar a Sequin Land de una maldici\u00f3n. Como pirata, Shantae obtiene nuevas armas para avanzar...",
         "Desde": "",
         "Hasta": "2227/08/05 15:00",
         "URL": "https://www.gog.com/en/game/shantae_and_the_pirates_curse",
         "IMG": "https://images.gog-statics.com/646dc0d893924086747e4498835f0f30f1c10576fecd2d38262396ea65762cbb.jpg",
         "Distribuidora": "GOG",
         "Borde": "border-color: #00ff00;"
      },
      {
         "Nombre": "BEAUTIFUL DESOLATION",
         "Informacion": "\u00a1Abr\u00f3chate el cintur\u00f3n y explora nuestro centro de ofertas de verano! La demo de BEAUTIFUL DESOLATION est\u00e1 disponible aqu\u00edTHE BROTHERHOOD ha creado un homenaje a los juegos de aventuras de tu infancia. BEAUTIFUL DESOLATION es una aventura isom\u00e9trica en 2D ambientada en un futuro lejano. Explora un paisaje postapocal\u00edptico, resuelve pu...",
         "Desde": "",
         "Hasta": "2241/04/13 15:00",
         "URL": "https://www.gog.com/en/game/beautiful_desolation",
         "IMG": "https://images.gog-statics.com/94f51548505272104e98243e46b1c8872e6bc165a0412b9bde56128320517363.jpg",
         "Distribuidora": "GOG",
         "Borde": "border-color: #00ff00;"
      },
      {
         "Nombre": "Flashback\u2122",
         "Informacion": "\u00a1Abr\u00f3chate el cintur\u00f3n y explora nuestro centro de ofertas de verano! \u00a1FLASHBACK\u2122, el exitoso juego de acci\u00f3n y aventuras con m\u00e1s de 2,2 millones de unidades vendidas, ha vuelto! 2142. Tras huir de una nave espacial pero despojado de todo recuerdo, el joven cient\u00edfico Conrad B. Hart despierta en Tit\u00e1n, una luna colonizada del planeta Saturno. Su enemigo...",
         "Desde": "",
         "Hasta": "2249/06/30 15:00",
         "URL": "https://www.gog.com/en/game/flashback",
         "IMG": "https://images.gog-statics.com/cfbb26f44012638c90b9649bda0359292cca1e04dd889b862614c232384eacfa.jpg",
         "Distribuidora": "GOG",
         "Borde": "border-color: #00ff00;"
      },
      {
         "Nombre": "VirtuaVerse",
         "Informacion": "\u00a1Abr\u00f3chate el cintur\u00f3n y explora nuestro centro de ofertas de verano! La versi\u00f3n de demostraci\u00f3n de VirtuaVerse est\u00e1 disponible aqu\u00ed \u00a1Ahora con el MODO HISTORIA! Jugar el MODO HISTORIA ser\u00eda una excelente opci\u00f3n para todas aquellas personas que no quieren lidiar con rompecabezas complicados. No te perder\u00e1s gran parte de la historia, pero al mismo tiempo la mayor\u00eda...",
         "Desde": "",
         "Hasta": "2260/06/12 15:00",
         "URL": "https://www.gog.com/en/game/virtuaverse",
         "IMG": "https://images.gog-statics.com/9cc3b38ecefc0bd7ea8cd5cb939ac402a0d9aeee88c951979cdec8b07cb5be71.jpg",
         "Distribuidora": "GOG",
         "Borde": "border-color: #00ff00;"
      },
      {
         "Nombre": "CDPR Goodies Collection",
         "Informacion": "Consigue los obsequios hasta el 11 de agosto de 2022 a la 1 p. de los juegos de The Witcher y Cyb...",
         "Desde": "",
         "Hasta": "2383/08/27 15:00",
         "URL": "https://www.gog.com/en/game/cdpr_goodies_collection",
         "IMG": "https://images.gog-statics.com/b5ed51ac37daf9c5d0540adbaf09cdc6d0ab360eae68edb8a31befdee74cb10e.jpg",
         "Distribuidora": "GOG",
         "Borde": "border-color: #00ff00;"
      },
      {
         "Nombre": "STASIS",
         "Informacion": "STASIS es un juego de aventura de terror de ciencia ficci\u00f3n de apuntar y hacer clic que se juega desde una perspectiva isom\u00e9trica \u00fanica. STASIS entrelaza una narrativa espantosa con un juego de aventuras retro. Combine elementos, interact\u00fae con computadoras y resuelva acertijos mientras experimenta la atm\u00f3sfera arenosa. En un futuro lejano, ab...",
         "Desde": "",
         "Hasta": "2421/12/25 15:00",
         "URL": "https://www.gog.com/en/game/stasis",
         "IMG": "https://images.gog-statics.com/2470f1b7f6a94b35303ee395e859a00954790bea38049423c06f201979166852.jpg",
         "Distribuidora": "GOG",
         "Borde": "border-color: #00ff00;"
      },
      {
         "Nombre": "Dex",
         "Informacion": "\u00a1Guau! \u00a1Consulta las ofertas de GOGalicious dentro de The GOG Sale! La versi\u00f3n de demostraci\u00f3n de Dex est\u00e1 disponible aqu\u00ed Incluye el DLC Extra Outfits. \u00a1Explora, lucha, habla y piratea tu camino a trav\u00e9s de un rico mundo cyberpunk en este juego de rol de acci\u00f3n en 2D! llegando a la organizaci\u00f3n, atravesar\u00e1s la...",
         "Desde": "",
         "Hasta": "2432/12/07 15:00",
         "URL": "https://www.gog.com/en/game/dex",
         "IMG": "https://images.gog-statics.com/e9029c481d84815c77706610f11af8af6bdb64f793124bd02b70a8da2871d90f.jpg",
         "Distribuidora": "GOG",
         "Borde": "border-color: #00ff00;"
      },
      {
         "Nombre": "Lovecraft's Untold Stories",
         "Informacion": "\u00a1Guau! \u00a1Consulta las ofertas de GOGalicious dentro de The GOG Sale! Lovecraft's Untold Stories es un roguelite de acci\u00f3n con elementos de RPG. Exploras niveles generados aleatoriamente basados \u200b\u200ben H.P. Historias de Lovecraft, lucha contra cultistas y todo tipo de monstruos de los Mitos, mejora tus armas y equipo, resuelve acertijos...",
         "Desde": "",
         "Hasta": "2438/05/30 15:00",
         "URL": "https://www.gog.com/en/game/lovecrafts_untold_stories",
         "IMG": "https://images.gog-statics.com/6c56651c2b638a2253a7e1e01c1c8b7b09d692051e2b063e53daf32daf1cd949.jpg",
         "Distribuidora": "GOG",
         "Borde": "border-color: #00ff00;"
      },
      {
         "Nombre": "Immortal Redneck",
         "Informacion": "Immortal Redneck es un FPS ambientado en Egipto con elementos rogue-lite. El juego combina la acci\u00f3n de disparos en primera persona de la vieja escuela con una mec\u00e1nica rogue-lite. Jugabilidad fren\u00e9tica, controles de contracci\u00f3n y una sensaci\u00f3n de estilo arcade se encuentran con mazmorras generadas aleatoriamente, un \u00e1rbol de habilidades completo, muerte permanente y 9 clases con...",
         "Desde": "",
         "Hasta": "2452/02/06 15:00",
         "URL": "https://www.gog.com/en/game/immortal_redneck",
         "IMG": "https://images.gog-statics.com/f8387855fa8cadfccb422a584e079f00fec37380adba91a47c72a6d06c8fb8ef.jpg",
         "Distribuidora": "GOG",
         "Borde": "border-color: #00ff00;"
      },
      {
         "Nombre": "Master of Magic Classic",
         "Informacion": "Master of Magic Classic es un cl\u00e1sico, uno de los juegos de estrategia m\u00e1s populares de los a\u00f1os 90. Es un juego de estrategia de fantas\u00eda 4X que te permite jugar como un mago extremadamente poderoso, liderando tus tropas y superando a tus oponentes m\u00e1gicos. Despu\u00e9s de m\u00e1s de 25 a\u00f1os, el juego ahora recibe el primer \u00e1rbitro...",
         "Desde": "",
         "Hasta": "2526/02/20 07:00",
         "URL": "https://www.gog.com/en/game/master_of_magic_classic",
         "IMG": "https://images.gog-statics.com/4c25af4a80fac03affce5f09449c918d0dc33b75ad6f52b629dec567147f796d.jpg",
         "Distribuidora": "GOG",
         "Borde": "border-color: #00ff00;"
      },
      {
         "Nombre": " A Plague Tale Digital Goodies Pack",
         "Informacion": "`\u00a1Lo hice por \u00e9l! \u00a1Y los matar\u00e9 de nuevo si tengo que hacerlo! \u00a1Los matar\u00e9 a todos!` \u2013 Amicia de Rune.Sum\u00e9rgete m\u00e1s profundamente en el mundo de A Plague Tale: Innocence y A Plague Tale: Requiem con este Paquete de obsequios digitales especial y gratuito, que contiene artes conceptuales de ambos juegos, \u00a1y m\u00e1s! Una Plaga T...",
         "Desde": "",
         "Hasta": "2576/05/01 15:00",
         "URL": "https://www.gog.com/en/game/a_plague_tale_requiem_digital_goodie_pack",
         "IMG": "https://images.gog-statics.com/cea28e4c25bb07b96848d7eb4ed08e6621296137161491c9529a1d13f71acb75.jpg",
         "Distribuidora": "GOG",
         "Borde": "border-color: #00ff00;"
      },
      {
         "Nombre": "Genesis Alpha One Deluxe Edition",
         "Informacion": "La edici\u00f3n Deluxe nueva y mejorada incluye: Libro de ilustraciones Banda sonora DLC de Rocket Star Corporation En un futuro cercano devastado por guerras, reg\u00edmenes corruptos y una contaminaci\u00f3n devastadora, corporaciones influyentes han creado el programa G\u00e9nesis en un \u00faltimo intento por salvar a la humanidad. Como Capit\u00e1n de...",
         "Desde": "",
         "Hasta": "2602/10/20 07:00",
         "URL": "https://www.gog.com/en/game/genesis_alpha_one_deluxe_edition",
         "IMG": "https://images.gog-statics.com/a8ab44a298480c2b187e3f9aa9ae3bb3d1a5e9155571c9c8fab5c82cc7202061.jpg",
         "Distribuidora": "GOG",
         "Borde": "border-color: #00ff00;"
      },
      {
         "Nombre": "Jazz Jackrabbit 2 Collection",
         "Informacion": "\u00a1EL JAZZ EST\u00c1 DE VUELTA! La infame tortuga, Devan Shell, ha construido una m\u00e1quina del tiempo como parte de un plan diab\u00f3lico para reescribir el pasado de Carrotus. \u00a1Ahora, solo nuestro h\u00e9roe junto con su hermano peque\u00f1o perdido, Spaz, pueden evitar que le d\u00e9 la vuelta a la historia! La colecci\u00f3n Jazz Jackrabbit 2 incluye: Jazz Jackrabbi...",
         "Desde": "",
         "Hasta": "2613/10/02 07:00",
         "URL": "https://www.gog.com/en/game/jazz_jackrabbit_2_collection",
         "IMG": "https://images.gog-statics.com/c2941f12a019aea90d3b4c88d16d0c8eb5af95ec4f743f97c03e217f0ebe1278.jpg",
         "Distribuidora": "GOG",
         "Borde": "border-color: #00ff00;"
      },
      {
         "Nombre": "Narita Boy",
         "Informacion": "Historia Flashback a los a\u00f1os 80. El Creador, un genio de su tiempo, crea una consola de videojuegos llamada Narita One cuyo t\u00edtulo principal es un juego llamado Narita Boy. \u00a1Narita Boy se convierte en un gran \u00e9xito! Las copias de los cartuchos est\u00e1n volando de los estantes f\u00edsicos en todo el mundo. Dentro de unas semanas, Narita Bo...",
         "Desde": "",
         "Hasta": "2673/12/26 07:00",
         "URL": "https://www.gog.com/en/game/narita_boy",
         "IMG": "https://images.gog-statics.com/381ff77fa8bcf9abe8d94152d61c1092dc5a4871f89fb3101cf58675c09f7295.jpg",
         "Distribuidora": "GOG",
         "Borde": "border-color: #00ff00;"
      },
      {
         "Nombre": "Terroir",
         "Informacion": "Terroir es un juego magnate en 3D basado en mosaicos en el que administras tu propio vi\u00f1edo. En Terroir, cultivas una variedad de diferentes varietales de uva, elaboras tu vino y expandes y administras tu finca. Tambi\u00e9n tendr\u00e1s que lidiar con factores como el clima y eventos aleatorios, que pueden hacer o deshacer tu...",
         "Desde": "",
         "Hasta": "2682/03/14 07:00",
         "URL": "https://www.gog.com/en/game/terroir",
         "IMG": "https://images.gog-statics.com/81a3950765951238768ca6e709d89ff4a2c483af3e6b002eb281eb47b82e6912.jpg",
         "Distribuidora": "GOG",
         "Borde": "border-color: #00ff00;"
      },
      {
         "Nombre": "Knights of Honor II - Goodie Pack",
         "Informacion": "Una colecci\u00f3n de impresionantes im\u00e1genes fijas y artes de Knights of Honor II: Sovereign, que puedes usar como fondos de pantalla o simplemente como algo para contemplar.Knights of Honor II: SovereignConvi\u00e9rtete en el rey y lucha por Europa en esta nueva versi\u00f3n estrategia. Administra provincias, re\u00fane ej\u00e9rcitos,...",
         "Desde": "",
         "Hasta": "2712/10/09 23:00",
         "URL": "https://www.gog.com/en/game/knights_of_honor_ii_sovereign_goodie_pack",
         "IMG": "https://images.gog-statics.com/4f8e61670d6a3ef98ebde08395258e47e703f24ee0522d1522ec8289ee638fc7.jpg",
         "Distribuidora": "GOG",
         "Borde": "border-color: #00ff00;"
      },
      {
         "Nombre": "Idle Champions de Forgotten Realms",
         "Informacion": "Idle Champions es un videojuego de gesti\u00f3n estrat\u00e9gica con licencia de Dungeons & Dragons en el que personajes emblem\u00e1ticos de las novelas, las campa\u00f1as y las series se unen en una \u00e9pica aventura.",
         "Desde": "",
         "Hasta": "2712/10/09 23:00",
         "URL": "https://store.epicgames.com/p/idle-champions-of-the-forgotten-realms",
         "IMG": "https://cdn1.epicgames.com/offer/7e508f543b05465abe3a935960eb70ac/EpicCarousel_2560x1440_3KeyartENG2_2560x1440-6c23d0f0576846fc88d1356df3a0c1cf",
         "Distribuidora": "Epic Game",
         "Borde": "border-color: #00ff00;"
      },
      {
         "Nombre": "Backbone: Prologue",
         "Informacion": "Backbone: Prologue is the first act of a noir roleplaying detective adventure. You are raccoon private eye Howard Lotor, a second-class citizen of dystopian Vancouver, BC inhabited by animals. Interrogate a diverse cast of characters, collect evidence, and choose which leads to follow.",
         "Desde": "",
         "Hasta": "2999/02/10 19:00",
         "URL": "https://www.humblebundle.com/store/backbone-prologue",
         "IMG": "https://hb.imgix.net/199751202b253069287b845c2380fff0eef5d62a.jpg?auto=compress,format&fit=crop&h=353&w=616&s=8ee7384524e09308706c4fbd7ba10b25",
         "Distribuidora": "Humble Bundle",
         "Borde": "border-color: #00ff00;"
      },
      {
         "Nombre": "Crying Suns Demo",
         "Informacion": "Crying Suns es un rogue-lite de exploraci\u00f3n t\u00e1ctica en el que encarnas a un gran almirante que explora su imperio ca\u00eddo. Descubre la verdad sobre el Imperio y sobre ti mismo en una historia inspirada por cl\u00e1sicos como Fundaci\u00f3n y Dune.",
         "Desde": "",
         "Hasta": "3000/01/01 09:00",
         "URL": "https://www.humblebundle.com/store/crying-suns-demo",
         "IMG": "https://i.ytimg.com/vi/cmwFRlxMhW0/maxresdefault.jpg",
         "Distribuidora": "Humble Bundle",
         "Borde": "border-color: #00ff00;"
      },
      {
         "Nombre": "Influent",
         "Informacion": "Influent es un juego de aprendizaje de idiomas centrado en la adquisici\u00f3n de vocabulario y pronunciaci\u00f3n que ofrece a los jugadores la libertad de elegir las palabras que quieren aprender sin la necesidad de l\u00e1pices o libros.",
         "Desde": "",
         "Hasta": "3000/01/01 09:00",
         "URL": "https://www.humblebundle.com/store/influent",
         "IMG": "https://cdn.cloudflare.steamstatic.com/steam/apps/274980/header.jpg?t=1600321339",
         "Distribuidora": "Humble Bundle",
         "Borde": "border-color: #00ff00;"
      },
      {
         "Nombre": "Ring Of Pain Demo",
         "Informacion": "Entra en Ring of Pain, un juego de exploraci\u00f3n con cartas plagado de retos. Cada paso es una decisi\u00f3n crucial. \u00bfCoges el bot\u00edn, o acabas antes con el monstruo que te acecha? Haz amigos extra\u00f1os que traen regalos y elige bien tu equipo...",
         "Desde": "",
         "Hasta": "3000/01/01 09:00",
         "URL": "https://www.humblebundle.com/store/ring-of-pain-demoo",
         "IMG": "https://hb.imgix.net/6145445f0d86d32ec8f1a0748cbf338bc3d9fa47.jpeg?auto=compress,format&fit=crop&h=353&w=616&s=e6e79af9f583074ab47d60ea8152564f",
         "Distribuidora": "Humble Bundle",
         "Borde": "border-color: #00ff00;"
      },
      {
         "Nombre": "Unsighted Demo",
         "Informacion": "Los pocos androides que quedan en Arcadia, una vez una metr\u00f3polis poblada, se est\u00e1n quedando sin Anima, la energ\u00eda que da a todos los robots su conciencia. Explora esta ciudad olvidada y evita que los androides restantes se conviertan en no videntes.",
         "Desde": "",
         "Hasta": "3000/01/01 09:59",
         "URL": "https://www.humblebundle.com/store/unsighted-demo",
         "IMG": "https://hb.imgix.net/f3b0f5b3d1ba8e578903c91b62d307893c18c048.jpg?auto=compress,format&fit=crop&h=353&w=616&s=c450193f05d2b79452a25106719466de",
         "Distribuidora": "Humble Bundle",
         "Borde": "border-color: #00ff00;"
      },
      {
         "Nombre": "Into The Pit Demo",
         "Informacion": "Como miembros de una familia de m\u00edsticos cazadores de historias, tu prima, Luridia, y t\u00fa recorren por separado esta tierra, atra\u00eddos por los rumores de poderes oscuros. Despu\u00e9s de descubrir un foso demoniaco en un pueblo cercano, las cartas de Luridia, que antes eran asiduas, se detuvieron.",
         "Desde": "",
         "Hasta": "3000/01/01 10:00",
         "URL": "https://www.humblebundle.com/store/into-the-pit-demo",
         "IMG": "https://hb.imgix.net/2d242b1cab5af73bbff37686305c784eac467cf0.png?auto=compress,format&fit=crop&h=353&w=616&s=f5c4140117e67917eefdcf97cf74acad",
         "Distribuidora": "Humble Bundle",
         "Borde": "border-color: #00ff00;"
      }
   ]
}